Workbook
Name SegmentaciónDeDatos_Data: #N/A
Name SegmentaciónDeDatos_Linia_Negoci: #N/A

Sheet Agenda_05
A1: COMPTE DE RESULTATS 2026 | B1: Gener | C1: Febrer | D1: Març | E1: Abril | F1: Maig | G1: Juny | H1: Juliol | I1: Agost | J1: Setembre | K1: Octubre | L1: Novembre | M1: Desembre | N1: TOTAL
A2: . VENDES | B2: 11598.18 | C2: 13093.09 | D2: 22719.31 | E2: 19204.84 | F2: 34909.12 | N2: =SUM(B2:M2) -> 101524.54
A3: . PRESTACIO DE SEVEIS | B3: 0 | C3: 0 | D3: 0 | E3: 0 | F3: 0 | N3: =SUM(B3:M3) -> 0
A4: . ALTRES INGRESSOS | B4: 3004.21 | C4: 3004.21 | D4: 3004.21 | E4: 3004.21 | F4: 3004.21 | N4: =SUM(B4:M4) -> 15021.05
A5: . VARIACIO EXISTENCIES | B5: 0 | C5: 0 | D5: 0 | E5: 0 | F5: 0 | N5: =SUM(B5:M5) -> 0
A6: TOTAL INGRESSOS EXPLOTACIO | B6: =SUM(B2:B5) -> 14602.39 | C6: =SUM(C2:C5) -> 16097.3 | D6: =SUM(D2:D5) -> 25723.52 | E6: =SUM(E2:E5) -> 22209.05 | F6: =SUM(F2:F5) -> 37913.33 | G6: =SUM(G2:G5) -> 0 | H6: =SUM(H2:H5) -> 0 | I6: =SUM(I2:I5) -> 0 | ... M6: =SUM(M2:M5) -> 0 | N6: =SUM(B6:M6) -> 116545.59
A7: 0.25 | B7: =-$A$7*B6 -> -3650.5975 | C7: =-$A$7*C6 -> -4024.325 | D7: =-$A$7*D6 -> -6430.88 | E7: =-$A$7*E6 -> -5552.2625 | F7: =-$A$7*F6 -> -9478.3325
A8: . ALTRES APROVISIONAMENTS | B8: 84 | C8: 0 | D8: 0 | E8: 0 | F8: 0 | N8: =SUM(B8:M8) -> 84
A9: . VARIACIO EXISTENICIES COMPRES | B9: 0 | C9: 0 | D9: 0 | E9: 0 | F9: 0 | N9: =SUM(B9:M9) -> 0
A10: TOTAL COMPRES | B10: =B7+B8 -> -3566.5975 | C10: =C7+C8 -> -4024.325 | D10: =D7+D8 -> -6430.88 | E10: =E7+E8 -> -5552.2625 | F10: =F7+F8 -> -9478.3325 | G10: =G7+G8 -> 0 | H10: =H7+H8 -> 0 | I10: =I7+I8 -> 0 | ... M10: =M7+M8 -> 0 | N10: =SUM(B10:M10) -> -29052.397 | O10: =N10/$N$6 -> -0.24927925
A11: . SOUS I SALARIS | B11: -414614.43 | C11: -414827.96 | D11: -441884.46 | E11: -443403.37 | F11: -495789.03 | N11: =SUM(B11:M11) -> -2210519.2
A12: 0.15 | B12: =B6*-$A$12 -> -2190.3585 | C12: =C6*-$A$12 -> -2414.595 | D12: =D6*-$A$12 -> -3858.528 | E12: =E6*-$A$12 -> -3331.3575 | F12: =F6*-$A$12 -> -5686.9995 | G12: =G6*-$A$12 -> 0 | H12: =H6*-$A$12 -> 0 | I12: =I6*-$A$12 -> 0 | ... M12: =M6*-$A$12 -> 0 | N12: =SUM(B12:M12) -> -17481.838
A13: . ESTRUCTURA FIX | B13: -5000 | C13: -5000 | D13: -5000 | E13: -5000 | F13: -5000
A14: . INDEMNITZACIONS | B14: 0 | C14: 0 | D14: 0 | N14: =SUM(B14:M14) -> 0
A15: . SEGURETAT SOCIAL | N15: =SUM(B15:M15) -> 0
A16: . ALTRES DESPESES SOCIALS | N16: =SUM(B16:M16) -> 0
A17: TOTAL COST SALARIAL | B17: =SUM(B12:B16) -> -7190.3585 | C17: =SUM(C12:C16) -> -7414.595 | D17: =SUM(D12:D16) -> -8858.528 | E17: =SUM(E12:E16) -> -8331.3575 | F17: =SUM(F12:F16) -> -10686.999 | G17: =SUM(G11:G16) -> 0 | H17: =SUM(H11:H16) -> 0 | I17: =SUM(I11:I16) -> 0 | J17: =SUM(J11:J16) -> 0 | K17: =SUM(K11:K16) -> 0 | L17: =SUM(L11:L16) -> 0 | M17: =SUM(M11:M16) -> 0 | N17: =SUM(B17:M17) -> -42481.838 | O17: =N17/$N$6 -> -0.36450833
A18: TOTAL DESPESES GESTIO CENTRAL | B18: -79477.48 | C18: -65034.81 | D18: -100634.18 | E18: -133357.73 | F18: -131629.55 | N18: =SUM(B18:M18) -> -510133.75
A19: 0.1 | B19: =$A$19*B18 -> -7947.748 | C19: =$A$19*C18 -> -6503.481 | D19: =$A$19*D18 -> -10063.418 | E19: =$A$19*E18 -> -13335.773 | F19: =$A$19*F18 -> -13162.955 | G19: =$A$19*G18 -> 0 | H19: =$A$19*H18 -> 0 | I19: =$A$19*I18 -> 0 | ... M19: =$A$19*M18 -> 0
A20: TOTAL DESPESES GESTIO | B20: =SUM(B19) -> -7947.748 | C20: =SUM(C19) -> -6503.481 | D20: =SUM(D19) -> -10063.418 | E20: =SUM(E19) -> -13335.773 | F20: =SUM(F19) -> -13162.955 | G20: =SUM(G19) -> 0 | H20: =SUM(H19) -> 0 | I20: =SUM(I19) -> 0 | ... M20: =SUM(M19) -> 0 | N20: =SUM(B20:M20) -> -51013.375
A21: TOTAL GESTIO + SALARIS | B21: =B20+B17 -> -15138.106 | C21: =C20+C17 -> -13918.076 | D21: =D20+D17 -> -18921.946 | E21: =E20+E17 -> -21667.13 | F21: =F20+F17 -> -23849.954 | G21: =G20+G17 -> 0 | H21: =H20+H17 -> 0 | I21: =I20+I17 -> 0 | ... M21: =M20+M17 -> 0
A22: EBITDA | B22: =B6+(B10+B17+B20) -> -4102.314 | C22: =C6+(C10+C17+C20) -> -1845.101 | D22: =D6+(D10+D17+D20) -> 370.694 | E22: =E6+(E10+E17+E20) -> -5010.343 | F22: =F6+(F10+F17+F20) -> 4585.043 | G22: =G6+(G10+G17+G20) -> 0 | H22: =H6+(H10+H17+H20) -> 0 | I22: =I6+(I10+I17+I20) -> 0 | ... M22: =M6+(M10+M17+M20) -> 0 | N22: =SUM(B22:M22) -> -6002.021
A23: % | B23: =B22/B6 -> -0.28093442 | C23: =C22/C6 -> -0.11462177 | D23: =D22/D6 -> 0.014410703 | E23: =E22/E6 -> -0.22559916 | F23: =F22/F6 -> 0.12093485

Sheet Dades
A3: LN00000 | B3: PRECUINATS
A4: TOTAL INGRESSOS EXPLOTACIO | B4: Les sumen en el total, en el desglos de cada LN no ho tenim en compte
A5: TOTAL COMPRES | B5: Porcentatge repartim endtre les diferents LN
B6: En el total em de treure la compra interna de LN00001 sino estariem doblant valor
B7: Hem de restar del total el 45% sobre vendes de LN00004 i cal.lcular porcentatges en fucnio a de le svendes deñl 2025
A8: TOTAL COST SALARIAL | B8: Restem els 20.000 mensuals imputat ja en la LN00001
B9: Hem de veure quins departaments impliquen a totes les LN i en aquest fer la part % segons vendes del 2025
B10: El % que no implica a totes LN assignar a cada LN segon % vendes
A11: TOTAL DESPESES GESTIO
A13: LN00000 | B13: AGENDA
A14: TOTAL INGRESSOS EXPLOTACIO | B14: Vendes
A15: TOTAL COMPRES | B15: Imputem un fixe 25% sobre vendes
A16: TOTAL COST SALARIAL | B16: Imputem un fixe de 5000, d'estructura
B17: 10% de perosnal sobre vendes
A18: TOTAL DESPESES GESTIO | B18: Un fixe sobre els cosotso fixes de la central del 10%
A20: LN00001 | B20: RESTAURACIO
A21: TOTAL INGRESSOS EXPLOTACIO | B21: Ja te la seva propia C.Explotació.
A22: TOTAL COMPRES | B22: Restar de del total de compres el consum intern a les comprs de LN00000
A23: TOTAL COST SALARIAL | B23: S'hauria de fer els traspassos intenrs de les hores treallades fora de centre en una altre LN
A24: TOTAL DESPESES GESTIO | B24: Ja te imputades les seves pròpies
A26: LN00002 | B26: EMPRESA
A27: TOTAL INGRESSOS EXPLOTACIO
A28: TOTAL COMPRES | B28: % vendes del 2025 treient les vendes, LN0000, LN00001 , LN00006, LN00005 i LN00004 i aquest % sera el que aplicaem sobre la compra restant
A29: TOTAL COST SALARIAL | B29: % de vendes del 2025 excepte LN00001 sobre tots els departements
B30: Restar el 20.0000 de Restauracio i el % GreenVita
A31: TOTAL DESPESES GESTIO | B31: Restem el % LN00006
B32: % apliquem de les vendes del 2025
A34: LN00003 | B34: CASAMENTS
A35: TOTAL INGRESSOS EXPLOTACIO
A36: TOTAL COMPRES | B36: % vendes del 2025 treient les vendes, LN0000, LN00001 , LN00006, LN00005 i LN00004 i aquest % sera el que aplicaem sobre la compra restant
A37: TOTAL COST SALARIAL | B37: % de vendes del 2025 excepte LN00001 sobre tots els departements
B38: Restar el 20.0000 de Restauracio i els 10.000 GreenVita
A39: TOTAL DESPESES GESTIO | B39: Restem el % LN00006
B40: % apliquem de les vendes del 2025
A42: LN00004 | B42: PRECUINATS
A43: TOTAL INGRESSOS EXPLOTACIO | B43: S'ha d'aplicar el rappel del 2%
B44: Total sortira aquest 2% menys
A45: TOTAL COMPRES | B45: 45% sobre la facturacio
A46: TOTAL COST SALARIAL | B46: Imputem el cost empresa mensual de 1 treballador logistica 3500
B47: % de le vendes 2025 sobre departaments de RRHH. Comptabilitat, Compres, Cuina Central, Manteniment
B48: % de vendes del 2025 excepte LN00001 en dept de producció, marqueting, logisitca
A49: TOTAL DESPESES GESTIO | B49: Restem el % LN00006
B50: % apliquem de les vendes del 2025
A52: LN00005 | B52: FOODLOVERS
A53: TOTAL INGRESSOS EXPLOTACIO
A54: TOTAL COMPRES | B54: POTSER FER % FIXE? 28% si fem aixi hem de retar la factuaracio del 2025 i pujar porcentatges de empresa i casaments
A57: TOTAL COST SALARIAL | B57: fixe 5000 mensual per estructura
B58: Personal especific
B59: Faltaria personal de catering o restaurant que no estan imputats directament
A60: TOTAL DESPESES GESTIO
B61: % apliquem de les vendes del 2025
A63: LN00006 | B63: GREEN VITA
A64: TOTAL INGRESSOS EXPLOTACIO
A65: TOTAL COMPRES | B65: Un fixe del 25% sobre les vendes de LN00006
A66: TOTAL COST SALARIAL | B66: 10% sobre la venda
A67: TOTAL DESPESES GESTIO | B67: % sobre les vendes 2026 | C67: 0.04
A72: Description | B72: TOTAL | C72: LN00000 | D72: LN00001 | E72: LN00002 | F72: LN00003 | G72: LN00004 | H72: LN00005
A73: COMPTE DE RESULTATS | B73: 0 | C73: 0 | D73: 0 | E73: 0 | F73: 0 | G73: 0 | H73: 0 | K73: Compres i Personal | O73: Despesses de Gestio
A74: . VENDES | B74: 23893002 | C74: 181172.5 | D74: 5696163.8 | E74: 8037122.9 | F74: 2721686.6 | G74: 5763172.4 | H74: 1493683.3
A75: . PRESTACIO DE SEVEIS | B75: 0 | C75: 0 | D75: 0 | E75: 0 | F75: 0 | G75: 0 | H75: 0 | J75: LN00001 | K75: Personal | L75: 20000 | M75: menusal | N75: =L75*12 -> 240000
A76: . ALTRES INGRESSOS | B76: 153211.19 | C76: 42787.58 | D76: 55097.46 | E76: 14895.69 | F76: 34611.17 | G76: 0 | H76: 5819.29 | J76: LN00002 | K76: Porcentatge de vendes | L76: =E78/L93 -> 0.33467047 | O76: LN00002 | P76: Porcentatge de vendes | Q76: =E78/($L$92-$K$95) -> 0.43980198 | R76: 0.43
A77: . VARIACIO EXISTENCIES | B77: 13330.43 | C77: 13330.43 | D77: 0 | E77: 0 | F77: 0 | G77: 0 | H77: 0 | J77: LN00003 | K77: Porcentatge de vendes | L77: =F78/L93 -> 0.11456152 | O77: LN00003 | P77: Porcentatge de vendes | Q77: =G78/($L$92-$K$95) -> 0.31478499 | R77: 0.14
A78: TOTAL INGRESSOS EXPLOTACIO | B78: 24059543 | C78: 237290.51 | D78: 5751261.3 | E78: 8052018.6 | F78: 2756297.8 | G78: 5763172.4 | H78: 1499502.6 | J78: LN00004 | K78: Imputem costos directes | L78: =G78/L93 -> 0.2395379 | O78: LN00004 | P78: Imputem costos directes | Q78: =F78/($L$92-$K$95) -> 0.15054923 | R78: 0.3
A79: . COMPRES | B79: -6669397 | C79: -5254370.6 | D79: -1261571.8 | E79: -32501.27 | F79: -9935.07 | G79: -5780.92 | H79: -105237.36 | J79: LN00005 | K79: Porcentatge de vendes | L79: =H78/L93 -> 0.06232465 | O79: LN00005 | P79: Porcentatge de vendes | Q79: =H78/($L$92-$K$95) -> 0.081902967
A80: . ALTRES APROVISIONAMENTS | B80: -1126484.4 | C80: -894954.7 | D80: -78775.83 | E80: -13825.99 | F80: -6409.44 | G80: -10029.11 | H80: -122489.38 | J80: LN00006 | K80: Green Vita | L80: 0.04 | O80: LN00006 | P80: Green Vita | Q80: 0.04
A81: . CONSUMS INTERNS | B81: 0 | C81: 0 | D81: 0 | E81: 0 | F81: 0 | G81: 0 | H81: 0 | Q81: =SUM(Q76:Q80) -> 1.0270392
A82: . VARIACIO EXISTENICIES COMPRES | B82: -7086.67 | C82: -7086.67 | D82: 0 | E82: 0 | F82: 0 | G82: 0 | H82: 0
A83: TOTAL COMPRES | B83: -7802968.1 | C83: -6156412 | D83: -1340347.6 | E83: -46327.26 | F83: -16344.51 | G83: -15810.03 | H83: -227726.74
A84: MARGE BRUT TOTAL | B84: 16256575 | C84: -5919121.5 | D84: 4410913.7 | E84: 8005691.3 | F84: 2739953.3 | G84: 5747362.3 | H84: 1271775.9
A85: . SOUS I SALARIS | B85: -7850222.3 | C85: -4493704 | D85: -2239592.7 | E85: -234556.16 | F85: -173807.82 | G85: -552911.19 | H85: -155650.45 | J85: Total Cost | M85: LN00002 | N85: LN00003 | O85: LN00004 | P85: LN00005
A86: . INDEMNITZACIONS | B86: -38022.75 | C86: -12022.75 | D86: -22000 | E86: -4000 | F86: 0 | G86: 0 | H86: 0 | J86: Estrucutra | K86: Cost Personal | L86: =5857479.14-N75 -> 5617479.1 | M86: =$L$76*L86 -> 1880004.4 | N86: =$L$77*L86 -> 643546.94 | O86: =$L$78*L86 -> 1345599.1 | P86: =$L$79*L86 -> 350107.42
A87: . SEGURETAT SOCIAL | B87: -2198225.5 | C87: -1246163.8 | D87: -640792.77 | E87: -75841.02 | F87: -52170.58 | G87: -129378.74 | H87: -53878.58 | K87: Compres | L87: 6156412 | M87: =$L$76*L87 -> 2060369.3 | N87: =$L$77*L87 -> 705287.9 | O87: 0.45 | P87: =$L$79*L87 -> 383696.22
A88: . ALTRES DESPESES SOCIALS | B88: -133340.46 | C88: -105588.55 | D88: -18970.62 | E88: -3947.7 | F88: -1648.12 | G88: -2219.47 | H88: -966 | K88: Gestió | L88: 1061489.8 | M88: =$L$76*L88 -> 355249.27 | N88: =$L$77*L88 -> 121605.88 | O88: =$L$78*L88 -> 254267.02 | P88: =$L$79*L88 -> 66156.977
A89: TOTAL COST SALARIAL | B89: -10219811 | C89: -5857479.1 | D89: -2921356 | E89: -318344.88 | F89: -227626.52 | G89: -684509.4 | H89: -210495.03
A90: . ARRENDAMENTS I CANONS | B90: -1440438.6 | C90: -128912.4 | D90: -301810.64 | E90: -397259.69 | F90: -371687.28 | G90: -8563.03 | H90: -232205.6
A91: . REPARACIONS I CONSERVACIO | B91: -493733.6 | C91: -264968.29 | D91: -151545.57 | E91: -40175.36 | F91: -8199.32 | G91: -20302.38 | H91: -8542.68 | J91: Vendes Totals
A92: . SERVEIS PROFESSIONALS | B92: -676309.5 | C92: -65044.5 | D92: -46974.01 | E92: -385827.79 | F92: -111348.95 | G92: -323.66 | H92: -66790.59 | J92: TOTAL | L92: 24059543
A93: . TRANSPORTS | B93: -103637.36 | C93: -94131.35 | D93: -17.6 | E93: -4656.91 | F93: 0 | G93: -3575.5 | H93: -1256 | J93: Restem | K93: LN00001 i LN00004 | L93: =L92-K99 -> 24059543
A94: . PRIMES D'ASSEGURANCES | B94: -62155.57 | C94: -45501.63 | D94: -16557.94 | E94: -96 | F94: 0 | G94: 0 | H94: 0 | N94: =L92-K100 -> 16571489 | O94: =E78/N94 -> 0.48589591 | P94: Empresa
A95: . SERVEIS BANCARIS | B95: -45010.59 | C95: -10528.36 | D95: -26099.04 | E95: -2171.95 | F95: -1472.57 | G95: 0 | H95: -4738.67 | J95: LN00001 | K95: =D78 -> 5751261.3 | O95: =F78/N94 -> 0.16632771 | P95: Casaments
A96: . PUBLICITAT I PROPAGANDA | B96: -66544.63 | C96: -19092.66 | D96: -14426.64 | E96: -14820.3 | F96: -13828.65 | G96: -70 | H96: -4306.38 | J96: LN00004 | O96: =G78/N94 -> 0.34777638
A97: . SUBMINISTRAMENTS | B97: -362824.55 | C97: -146604.81 | D97: -147814.04 | E97: 0 | F97: 0 | G97: -68028.84 | H97: -376.86 | J97: LN00005 | K97: =H78 -> 1499502.6
A98: . ALTRES DESPESES | B98: -666549.11 | C98: -260157.15 | D98: -117331.29 | E98: -189240.3 | F98: -60239.11 | G98: -4523.23 | H98: -35058.01 | J98: LN00000 | K98: =C78 -> 237290.51
A99: . ALTRES TRIBUTS | B99: -45550.32 | C99: -26548.6 | D99: -19001.72 | E99: 0 | F99: 0 | G99: 0 | H99: 0 | K99: =K96+K96 -> 0
A100: . DOTACIO PER INSOLVENCIA | B100: -119051.82 | C100: 0 | D100: 0 | E100: 0 | F100: 0 | G100: 0 | H100: -119051.82 | K100: =SUM(K95:K98) -> 7488054.4
A101: MOVIMENTS INTERNS | B101: 0 | C101: 0 | D101: 0 | E101: 0 | F101: 0 | G101: 0 | H101: 0
A102: TOTAL DESPESES GESTIO | B102: -4081805.7 | C102: -1061489.8 | D102: -841578.49 | E102: -1034248.3 | F102: -566775.88 | G102: -105386.64 | H102: -472326.61 | J102: Càl.lcul cost Personal
A103: TOTAL GESTIO + SALARIS | B103: -14182565 | C103: -6918968.9 | D103: -3762934.5 | E103: -1352593.2 | F103: -794402.4 | G103: -789896.04 | H103: -563769.82
A104: EBITDA | B104: 1954958.3 | C104: -12838090 | D104: 647979.14 | E104: 6653098.1 | F104: 1945550.9 | G104: 4957466.3 | H104: 588954.22
A105: . INGRESSOS FINANCERS | B105: 26901.98 | C105: 26901.98 | D105: 0 | E105: 0 | F105: 0 | G105: 0 | H105: 0
A106: . DESPESSES FINANCERES | B106: -116524.73 | C106: -116333.36 | D106: 0 | E106: 0 | F106: -191.37 | G106: 0 | H106: 0
A107: RESULTAT FINANCER | B107: -89622.75 | C107: -89431.38 | D107: 0 | E107: 0 | F107: -191.37 | G107: 0 | H107: 0
A108: . INGRESOS EXCEPCIONALS | B108: 71325.93 | C108: 71191.58 | D108: 16.38 | E108: 0 | F108: 0 | G108: 0 | H108: 117.97
A109: . DESPESSES EXCEPCIONALS | B109: -21747.65 | C109: -13232.85 | D109: 0 | E109: 0 | F109: -8514.8 | G109: 0 | H109: 0
A110: RESULTAT EXCEPCIONAL | B110: 49578.28 | C110: 57958.73 | D110: 16.38 | E110: 0 | F110: -8514.8 | G110: 0 | H110: 117.97
A111: . AMORTITZACIONS | B111: -708361.98 | C111: -491276.9 | D111: -130523.02 | E111: -72281.28 | F111: -1412.16 | G111: -805.17 | H111: -12063.45
A112: RESULTAT ABANS D'IMPOSTOS | B112: 1206551.9 | C112: -13360840 | D112: 517472.5 | E112: 6580816.8 | F112: 1935432.6 | G112: 4956661.1 | H112: 577008.74
A113: . IMPOST SOBRE BENEFICIS | B113: -60000 | C113: -60000 | D113: 0 | E113: 0 | F113: 0 | G113: 0 | H113: 0
A114: RESULTAT DESPRES D'IMPOSTOS | B114: 1146551.9 | C114: -13420840 | D114: 517472.5 | E114: 6580816.8 | F114: 1935432.6 | G114: 4956661.1 | H114: 577008.74
A115: RESULTAT ACUMULAT | B115: 0 | C115: 0 | D115: 0 | E115: 0 | F115: 0 | G115: 0 | H115: 0
...

Sheet Restaurants_05
A1: COMPTE DE RESULTATS 2026 | B1: Gener | C1: Febrer | D1: Març | E1: Abril | F1: Maig | G1: Juny | H1: Juliol | I1: Agost | J1: Setembre | K1: Octubre | L1: Novembre | M1: Desembre | N1: TOTAL
A2: . VENDES | B2: 387044.54 | C2: 451350.88 | D2: 581201.05 | E2: 570984.57 | F2: 640094.54 | N2: =SUM(B2:M2) -> 2630675.6
A3: . ALTRES | B3: 1069 | C3: 18189 | D3: 1100 | E3: 17092 | F3: 2185.44 | N3: =SUM(B3:M3) -> 39635.44
A4: . PRESTACIO DE SEVEIS | B4: 0 | C4: 0 | D4: 0 | E4: 0 | F4: 0 | N4: =SUM(B4:M4) -> 0
A5: . ALTRES INGRESSOS | B5: 4617.95 | C5: 4617.95 | D5: 4617.95 | E5: 4617.95 | F5: 4617.95 | N5: =SUM(B5:M5) -> 23089.75
A6: . VARIACIO EXISTENCIES | B6: 0 | C6: 0 | D6: 0 | E6: 0 | F6: 0 | N6: =SUM(B6:M6) -> 0
A7: TOTAL INGRESSOS EXPLOTACIO | B7: =SUM(B2:B6) -> 392731.49 | C7: =SUM(C2:C6) -> 474157.83 | D7: =SUM(D2:D6) -> 586919 | E7: =SUM(E2:E6) -> 592694.52 | F7: =SUM(F2:F6) -> 646897.93 | G7: =SUM(G2:G6) -> 0 | H7: =SUM(H2:H6) -> 0 | I7: =SUM(I2:I6) -> 0 | ... M7: =SUM(M2:M6) -> 0 | N7: =SUM(B7:M7) -> 2693400.8
A8: . COMPRES | B8: -83569.37 | C8: -102354.42 | D8: -119547.25 | E8: -125816.95 | F8: -129731.94 | N8: =SUM(B8:M8) -> -561019.93
A9: . ALTRES APROVISIONAMENTS | B9: -8313.31 | C9: -9250.55 | D9: -9342.87 | E9: -5630.13 | F9: -8068.66 | N9: =SUM(B9:M9) -> -40605.52
B10: =SUM(B8:B9) -> -91882.68 | C10: =SUM(C8:C9) -> -111604.97 | D10: =SUM(D8:D9) -> -128890.12 | E10: =SUM(E8:E9) -> -131447.08 | F10: =SUM(F8:F9) -> -137800.6 | N10: =SUM(B10:M10) -> -601625.45
A11: . CONSUMS INTERNS | B11: -38863.39 | C11: -37571.38 | D11: -53459.6 | E11: -68084.45 | F11: -74144.71 | N11: =SUM(B11:M11) -> -272123.53 | O11: =N11/N7 -> -0.10103343
A12: . VARIACIO EXISTENICIES COMPRES | B12: 0 | C12: 0 | D12: 0 | E12: 0 | F12: 0 | N12: =SUM(B12:M12) -> 0
A13: TOTAL COMPRES | B13: =SUM(B10:B12) -> -130746.07 | C13: =SUM(C10:C12) -> -149176.35 | D13: =SUM(D10:D12) -> -182349.72 | E13: =SUM(E10:E12) -> -199531.53 | F13: =SUM(F10:F12) -> -211945.31 | G13: =SUM(G8:G12) -> 0 | H13: =SUM(H8:H12) -> 0 | I13: =SUM(I8:I12) -> 0 | J13: =SUM(J8:J12) -> 0 | K13: =SUM(K8:K12) -> 0 | L13: =SUM(L8:L12) -> 0 | M13: =SUM(M8:M12) -> 0 | N13: =SUM(B13:M13) -> -873748.98 | O13: =N13/$N$7 -> -0.32440363
A14: . ESTRUCTURA FIX | B14: -20000 | C14: -20000 | D14: -20000 | E14: -20000 | F14: -20000 | N14: =SUM(B14:M14) -> -100000
A15: . SOUS I SALARIS | B15: =-240865.21 -> -240865.21 | C15: =-229230.19 -> -229230.19 | D15: =-253674.15 -> -253674.15 | E15: =-256915.37 -> -256915.37 | F15: =-253123.37 -> -253123.37 | N15: =SUM(B15:M15) -> -1233808.3
A16: . SALARIS | B16: -6442.71 | C16: 8493.25 | D16: -8727.71 | E16: -5870.32 | F16: -4972.41 | N16: =SUM(B16:M16) -> -17519.9
A17: . INDEMNITZACIONS | B17: -2000 | C17: -21000 | D17: 0 | E17: 0 | F17: -2200 | N17: =SUM(B17:M17) -> -25200
A18: . SEGURETAT SOCIAL | B18: -62895.34 | C18: -64940.94 | D18: -67531.7 | E18: -75595.64 | F18: -75385.48 | N18: =SUM(B18:M18) -> -346349.1
A19: . ALTRES DESPESES SOCIALS | B19: -2425.78 | C19: -1494.4 | D19: -1480.31 | E19: -2502.05 | F19: -1778.57 | N19: =SUM(B19:M19) -> -9681.11
A20: TOTAL COST SALARIAL | B20: =SUM(B14:B19) -> -334629.04 | C20: =SUM(C14:C19) -> -328172.28 | D20: =SUM(D14:D19) -> -351413.87 | E20: =SUM(E14:E19) -> -360883.38 | F20: =SUM(F14:F19) -> -357459.83 | G20: =SUM(G14:G19) -> 0 | H20: =SUM(H14:H19) -> 0 | I20: =SUM(I14:I19) -> 0 | ... M20: =SUM(M14:M19) -> 0 | N20: =SUM(B20:M20) -> -1732558.4 | O20: =N20/$N$7 -> -0.64326053
A21: . ARRENDAMENTS I CANONS | B21: -24126.84 | C21: -31160.25 | D21: -34984.2 | E21: -45678.55 | F21: -44091.64 | N21: =SUM(B21:M21) -> -180041.48
A22: . REPARACIONS I CONSERVACIO | B22: -15891.89 | C22: -11100.92 | D22: -18424.79 | E22: -18690.59 | F22: -16432.73 | N22: =SUM(B22:M22) -> -80540.92
A23: . SERVEIS PROFESSIONALS | B23: -1882.99 | C23: -1712.87 | D23: -2627.16 | E23: -2317.08 | F23: -6583.63 | N23: =SUM(B23:M23) -> -15123.73
A24: . SERVEIS PROFESSIONALS | C24: -415 | D24: -710 | E24: -280 | F24: -200
A25: . TRANSPORTS | B25: -350 | C25: 0 | D25: -25.2 | E25: 0 | F25: 0 | N25: =SUM(B25:M25) -> -375.2
A26: . PRIMES D'ASSEGURANCES | B26: -1513.17 | C26: -1417.17 | D26: -1417.17 | E26: -1417.17 | F26: -1417.17 | N26: =SUM(B26:M26) -> -7181.85
A27: . SERVEIS BANCARIS | B27: -1572.02 | C27: -2033.07 | D27: -2931.03 | E27: -3147.63 | F27: -2927.84 | N27: =SUM(B27:M27) -> -12611.59
A28: . PUBLICITAT I PROPAGANDA | B28: -933.97 | C28: -323.96 | D28: -1628.25 | E28: -1839.79 | F28: -810.74 | N28: =SUM(B28:M28) -> -5536.71
A29: . SUBMINISTRAMENTS | B29: -22044.31 | C29: -17620.1 | D29: -18511.09 | E29: -21222.18 | F29: -18492.4 | N29: =SUM(B29:M29) -> -97890.08
A30: . ALTRES DESPESES | B30: -8766.98 | C30: -16450.01 | D30: -18198.81 | E30: -12204.85 | F30: -8652.39 | N30: =SUM(B30:M30) -> -64273.04
A31: . ALTRES TRIBUTS | B31: -3010.38 | C31: -2533.33 | D31: -2533.33 | E31: -2879.9 | F31: -2891.37 | N31: =SUM(B31:M31) -> -13848.31
A32: . DOTACIO PER INSOLVENCIA | B32: 0 | C32: 0 | D32: 0 | E32: 0 | F32: 0 | N32: =SUM(B32:M32) -> 0
A33: MOVIMENTS INTERNS | B33: 0 | C33: 0 | D33: 0 | E33: 0 | F33: 0 | N33: =SUM(B33:M33) -> 0
A34: TOTAL DESPESES GESTIO | B34: =SUM(B21:B33) -> -80092.55 | C34: =SUM(C21:C33) -> -84766.68 | D34: =SUM(D21:D33) -> -101991.03 | E34: =SUM(E21:E33) -> -109677.74 | F34: =SUM(F21:F33) -> -102499.91 | G34: =SUM(G21:G33) -> 0 | H34: =SUM(H21:H33) -> 0 | I34: =SUM(I21:I33) -> 0 | ... M34: =SUM(M21:M33) -> 0 | N34: =SUM(B34:M34) -> -479027.91 | O34: =N34/$N$7 -> -0.17785244
A35: TOTAL GESTIO + SALARIS | B35: =B34+B20 -> -414721.59 | C35: =C34+C20 -> -412938.96 | D35: =D34+D20 -> -453404.9 | E35: =E34+E20 -> -470561.12 | F35: =F34+F20 -> -459959.74 | G35: =G34+G20 -> 0 | H35: =H34+H20 -> 0 | I35: =I34+I20 -> 0 | ... M35: =M34+M20 -> 0 | N35: =SUM(B35:M35) -> -2211586.3
A36: EBITDA | B36: =B7+(B13+B20+B34) -> -152736.17 | C36: =C7+(C13+C20+C34) -> -87957.48 | D36: =D7+(D13+D20+D34) -> -48835.62 | E36: =E7+(E13+E20+E34) -> -77398.13 | F36: =F7+(F13+F20+F34) -> -25007.12 | G36: =G7+(G13+G20+G34) -> 0 | H36: =H7+(H13+H20+H34) -> 0 | I36: =I7+(I13+I20+I34) -> 0 | ... M36: =M7+(M13+M20+M34) -> 0 | N36: =SUM(B36:M36) -> -391934.52
A37: % | B37: =B36/B7 -> -0.38890737 | C37: =C36/C7 -> -0.18550254 | D37: =D36/D7 -> -0.083206746 | E37: =E36/E7 -> -0.13058688 | F37: =F36/F7 -> -0.038656979 | N37: =N36/N7 -> -0.1455166

Sheet Empresa_05
A1: COMPTE DE RESULTATS 2026 | B1: Gener | C1: Febrer | D1: Març | E1: Abril | F1: Maig | G1: Juny | H1: Juliol | I1: Agost | J1: Setembre | K1: Octubre | L1: Novembre | M1: Desembre | N1: TOTAL
A2: . VENDES | B2: 289300.57 | C2: 522944.53 | D2: 693442.52 | E2: 532165.29 | F2: 1272615.1 | N2: =SUM(B2:M2) -> 3310468
A3: . PRESTACIO DE SEVEIS | B3: 0 | C3: 0 | D3: 0 | E3: 0 | F3: 0 | N3: =SUM(B3:M3) -> 0
A4: . ALTRES INGRESSOS | B4: 0 | C4: 0 | D4: 0 | E4: 0 | F4: 0 | N4: =SUM(B4:M4) -> 0
A5: . VARIACIO EXISTENCIES | B5: 0 | C5: 0 | D5: 0 | E5: 0 | F5: 0 | N5: =SUM(B5:M5) -> 0
A6: TOTAL INGRESSOS EXPLOTACIO | B6: =SUM(B2:B5) -> 289300.57 | C6: =SUM(C2:C5) -> 522944.53 | D6: =SUM(D2:D5) -> 693442.52 | E6: =SUM(E2:E5) -> 532165.29 | F6: =SUM(F2:F5) -> 1272615.1 | G6: =SUM(G2:G5) -> 0 | H6: =SUM(H2:H5) -> 0 | I6: =SUM(I2:I5) -> 0 | ... M6: =SUM(M2:M5) -> 0 | N6: =SUM(B6:M6) -> 3310468
A7: . COMPRES | B7: -64 | C7: 0 | D7: 0 | E7: -253.4 | F7: -497.64 | N7: =SUM(B7:M7) -> -815.04
A8: . ALTRES APROVISIONAMENTS | B8: -1275.3 | C8: -802.97 | D8: -558.52 | E8: -2165.52 | F8: -478.97 | N8: =SUM(B8:M8) -> -5281.28
A9: . COMPRA LN00000 | B9: -408725.23 | C9: -510110.91 | D9: -622510.5 | E9: -536165.77 | F9: -727844.97 | N9: =SUM(B9:M9) -> -2805357.4
A10: Precuinats | B10: =Precuinats_05!B11 -> -248909.16 | C10: =Precuinats_05!C11 -> -226949.34 | D10: =Precuinats_05!D11 -> -246027.31 | E10: =Precuinats_05!E11 -> -258992.74 | F10: =Precuinats_05!F11 -> -247173 | G10: =Precuinats_05!G11 -> 0 | H10: =Precuinats_05!H11 -> 0 | I10: =Precuinats_05!I11 -> 0 | ... M10: =Precuinats_05!M11 -> 0 | N10: =SUM(B10:M10) -> -1228051.6
A11: Green Vita | B11: ='Green Vita_05'!B8 -> -10867.987 | C11: ='Green Vita_05'!C8 -> -24849.577 | D11: ='Green Vita_05'!D8 -> -27767.548 | E11: ='Green Vita_05'!E8 -> -17762.685 | F11: ='Green Vita_05'!F8 -> -22083.3 | G11: ='Green Vita_05'!G8 -> 0 | H11: ='Green Vita_05'!H8 -> 0 | I11: ='Green Vita_05'!I8 -> 0 | ... M11: ='Green Vita_05'!M8 -> 0 | N11: =SUM(B11:M11) -> -103331.1
A12: Agenda | B12: =Agenda_05!B10 -> -3566.5975 | C12: =Agenda_05!C10 -> -4024.325 | D12: =Agenda_05!D10 -> -6430.88 | E12: =Agenda_05!E10 -> -5552.2625 | F12: =Agenda_05!F10 -> -9478.3325 | G12: =Agenda_05!G10 -> 0 | H12: =Agenda_05!H10 -> 0 | I12: =Agenda_05!I10 -> 0 | ... M12: =Agenda_05!M10 -> 0 | N12: =SUM(B12:M12) -> -29052.397
A13: Foodlovers | B13: =Foodlovers_05!B7 -> -267.12 | C13: =Foodlovers_05!C7 -> -11688.172 | D13: =Foodlovers_05!D7 -> -16802.674 | E13: =Foodlovers_05!E7 -> -34620.922 | F13: =Foodlovers_05!F7 -> -47688.346 | G13: =Foodlovers_05!G7 -> 0 | H13: =Foodlovers_05!H7 -> 0 | I13: =Foodlovers_05!I7 -> 0 | ... M13: =Foodlovers_05!M7 -> 0 | N13: =SUM(B13:M13) -> -111067.23
B14: =B9-(B10+B11+B12+B13) -> -145114.37 | C14: =C9-(C10+C11+C12+C13) -> -242599.5 | D14: =D9-(D10+D11+D12+D13) -> -325482.09 | E14: =E9-(E10+E11+E12+E13) -> -219237.16 | F14: =F9-(F10+F11+F12+F13) -> -401421.99 | G14: =G9-(G10+G11+G12+G13) -> 0 | H14: =H9-(H10+H11+H12+H13) -> 0 | I14: =I9-(I10+I11+I12+I13) -> 0 | ... M14: =M9-(M10+M11+M12+M13) -> 0 | N14: =SUM(B14:M14) -> -1333855.1
A15: Pestanya dades % aplicar | B15: =B14*Dades!C120 -> -133008.25 | C15: =C14*Dades!E120 -> -223258.99 | D15: =D14*Dades!G120 -> -289591.7 | E15: =E14*Dades!I120 -> -156550.6 | F15: =F14*Dades!K120 -> -258342.72 | G15: =G14*Dades!L120 -> 0 | I15: =I14*Dades!N120 -> 0 | J15: =J14*Dades!O120 -> 0 | K15: =K14*Dades!P120 -> 0 | L15: =L14*Dades!Q120 -> 0 | M15: =M14*Dades!R120 -> 0 | N15: =N14*Dades!S120 -> 0
A16: TOTAL COMPRES | B16: =B7+B8+B15 -> -134347.55 | C16: =C7+C8+C15 -> -224061.96 | D16: =D7+D8+D15 -> -290150.22 | E16: =E7+E8+E15 -> -158969.52 | F16: =F7+F8+F15 -> -259319.33 | G16: =SUM(G7:G15) -> 0 | H16: =SUM(H7:H15) -> 0 | I16: =SUM(I7:I15) -> 0 | J16: =SUM(J7:J15) -> 0 | K16: =SUM(K7:K15) -> 0 | L16: =SUM(L7:L15) -> 0 | M16: =SUM(M7:M15) -> 0 | N16: =SUM(B16:M16) -> -1066848.6 | O16: =N16/$N$6 -> -0.32226519
A17: . ESTRUCTURA LN00000 | B17: -532718.66 | C17: -537228.61 | D17: -580718.51 | E17: -607883.8 | F17: -646229.83 | N17: =SUM(B17:M17) -> -2904779.4
A18: Restem LN0001 | B18: -20000 | C18: -20000 | D18: -20000 | E18: -20000 | F18: -20000 | N18: =SUM(B18:M18) -> -100000
A19: Restem Green Vita | B19: ='Green Vita_05'!B14 -> -11520.792 | C19: ='Green Vita_05'!C14 -> -19909.747 | D19: ='Green Vita_05'!D14 -> -21660.529 | E19: ='Green Vita_05'!E14 -> -15657.611 | F19: ='Green Vita_05'!F14 -> -18249.98 | G19: ='Green Vita_05'!G14 -> 0 | H19: ='Green Vita_05'!H14 -> 0 | I19: ='Green Vita_05'!I14 -> 0 | ... M19: ='Green Vita_05'!M14 -> 0 | N19: =SUM(B19:M19) -> -86998.659
A20: Foodlovers | B20: =Foodlovers_05!B13 -> -5162.18 | C20: =Foodlovers_05!C13 -> -12096.39 | D20: =Foodlovers_05!D13 -> -15201.624 | E20: =Foodlovers_05!E13 -> -26019.845 | F20: =Foodlovers_05!F13 -> -33953.638 | G20: =Foodlovers_05!G13 -> 0 | H20: =Foodlovers_05!H13 -> 0 | I20: =Foodlovers_05!I13 -> 0 | ... M20: =Foodlovers_05!M13 -> 0 | N20: =SUM(B20:M20) -> -92433.677
A21: Agenda | B21: =Agenda_05!B17 -> -7190.3585 | C21: =Agenda_05!C17 -> -7414.595 | D21: =Agenda_05!D17 -> -8858.528 | E21: =Agenda_05!E17 -> -8331.3575 | F21: =Agenda_05!F17 -> -10686.999 | G21: =Agenda_05!G17 -> 0 | H21: =Agenda_05!H17 -> 0 | I21: =Agenda_05!I17 -> 0 | ... M21: =Agenda_05!M17 -> 0 | N21: =SUM(B21:M21) -> -42481.838
B22: =B18+B19+B20+B21 -> -43873.331 | C22: =C18+C19+C20+C21 -> -59420.731 | D22: =D18+D19+D20+D21 -> -65720.68 | E22: =E18+E19+E20+E21 -> -70008.814 | F22: =F18+F19+F20+F21 -> -82890.618 | G22: =G18+G19+G20+G21 -> 0 | H22: =H18+H19+H20+H21 -> 0 | I22: =I18+I19+I20+I21 -> 0 | ... M22: =M18+M19+M20+M21 -> 0 | N22: =SUM(B22:M22) -> -321914.17
A23: Pestanya dades % aplicar | B23: =(B17-B22)*Dades!C125 -> -162786.8 | C23: =(C17-C22)*Dades!E125 -> -232959.27 | D23: =(D17-D22)*Dades!G125 -> -269299.72 | E23: =(E17-E22)*Dades!I125 -> -216716.54 | F23: =(F17-F22)*Dades!K125 -> -283734.48 | G23: =(G17-G22)*Dades!H125 -> 0 | H23: =(H17-H22)*Dades!I125 -> 0 | I23: =(I17-I22)*Dades!J125 -> 0 | J23: =(J17-J22)*Dades!K125 -> 0 | K23: =(K17-K22)*Dades!L125 -> 0 | M23: =(M17-M22)*Dades!N125 -> 0 | N23: =SUM(B23:M23) -> -1165496.8
A24: . SOUS I SALARIS dept. | B24: -22116.05 | C24: -18130.26 | D24: -22980.88 | E24: -23486.13 | F24: -24690.8 | N24: =SUM(B24:M24) -> -111404.12
B25: -2589.05 | C25: -4174.93 | D25: -8686.08 | E25: -10808.41 | F25: -25630.83 | N25: =SUM(B25:M25) -> -51889.3
A26: Pestanya dades % aplicar | B26: =B25*Dades!$C$120 -> -2373.0594 | C26: =C25*Dades!$E$120 -> -3842.0964 | D26: =D25*Dades!$G$120 -> -7728.28 | E26: =E25*Dades!$I$120 -> -7717.9576 | F26: =F25*Dades!$K$120 -> -16495.206 | G26: =G25*Dades!$C$120 -> 0 | H26: =H25*Dades!$C$120 -> 0 | I26: =I25*Dades!$C$120 -> 0 | J26: =J25*Dades!$C$120 -> 0 | K26: =K25*Dades!$C$120 -> 0 | L26: =L25*Dades!$C$120 -> 0 | M26: =M25*Dades!$C$120 -> 0 | N26: =SUM(B26:M26) -> -38156.599
A27: . TRASPASSOS INTERNS | N27: =SUM(B27:M27) -> 0
A28: . INDEMNITZACIONS | B28: 0 | C28: 0 | D28: 0 | E28: 0 | F28: 0 | N28: =SUM(B28:M28) -> 0
A29: . SEGURETAT SOCIAL | B29: -7063.2 | C29: -5963.44 | D29: -7214.03 | E29: -7630.44 | F29: -7736.57 | N29: =SUM(B29:M29) -> -35607.68
A30: . ALTRES DESPESES SOCIALS | B30: -329.83 | C30: -375.09 | D30: -52.52 | E30: -218.24 | F30: -238.9 | N30: =SUM(B30:M30) -> -1214.58
A31: TOTAL COST SALARIAL | B31: =B23+B24+B26+B29+B30 -> -194668.94 | C31: =C23+C24+C26+C29+C30 -> -261270.16 | D31: =D23+D24+D26+D29+D30 -> -307275.43 | E31: =E23+E24+E26+E29+E30 -> -255769.31 | F31: =F23+F24+F26+F29+F30 -> -332895.95 | G31: =G23+G24+G26+G29+G30 -> 0 | H31: =H23+H24+H26+H29+H30 -> 0 | I31: =I23+I24+I26+I29+I30 -> 0 | ... M31: =M23+M24+M26+M29+M30 -> 0 | N31: =SUM(B31:M31) -> -1351879.8 | O31: =N31/$N$6 -> -0.40836516
A32: . GESTIO DE LN00000 | B32: -79477.48 | C32: -65034.81 | D32: -100634.18 | E32: -133354.73 | F32: -131629.55
A33: 0.44 | B33: =$A$33*B32 -> -34970.091 | C33: =$A$33*C32 -> -28615.316 | D33: =$A$33*D32 -> -44279.039 | E33: =$A$33*E32 -> -58676.081 | F33: =$A$33*F32 -> -57917.002
A34: . ARRENDAMENTS I CANONS | B34: -1857.14 | C34: -12920.01 | D34: -22596.34 | E34: -24236.09 | F34: -28175.89 | N34: =SUM(B34:M34) -> -89785.47
A35: . REPARACIONS I CONSERVACIO | B35: -520.83 | C35: -4988.08 | D35: -2969.32 | E35: -3469.82 | F35: -412.78 | N35: =SUM(B35:M35) -> -12360.83
A36: . SERVEIS PROFESSIONALS | B36: -11590.09 | C36: -34114.73 | D36: -52997.76 | E36: -21287.48 | F36: -77626.68 | N36: =SUM(B36:M36) -> -197616.74
A37: . TRANSPORTS | B37: -186.85 | C37: -376.97 | D37: -81.79 | E37: -86.5 | F37: -134.26 | N37: =SUM(B37:M37) -> -866.37
A38: . PRIMES D'ASSEGURANCES | B38: -96 | C38: 0 | D38: 0 | E38: 0 | F38: 0 | N38: =SUM(B38:M38) -> -96
A39: . SERVEIS BANCARIS | B39: -59.26 | C39: -108.3 | D39: -413.62 | E39: -747.22 | F39: -202.08 | N39: =SUM(B39:M39) -> -1530.48
A40: . PUBLICITAT I PROPAGANDA | B40: -5629.55 | C40: -1265.91 | D40: -3506.86 | E40: -5083.88 | F40: -186.99 | N40: =SUM(B40:M40) -> -15673.19
A41: . SUBMINISTRAMENTS | B41: 0 | C41: 0 | D41: 0 | E41: 0 | F41: 0 | N41: =SUM(B41:M41) -> 0
A42: . ALTRES DESPESES | B42: -11122.01 | C42: -13364.27 | D42: -18351.24 | E42: -44163.69 | F42: -66576.72 | N42: =SUM(B42:M42) -> -153577.93
A43: . ALTRES DESPESES | C43: -630 | D43: -806 | F43: -1082
A44: . DOTACIO PER INSOLVENCIA | B44: 0 | C44: 0 | D44: 0 | E44: 0 | F44: 0 | N44: =SUM(B44:M44) -> 0
A45: MOVIMENTS INTERNS | B45: 0 | C45: 0 | D45: 0 | E45: 0 | F45: 0 | N45: =SUM(B45:M45) -> 0
A46: TOTAL DESPESES GESTIO | B46: =SUM(B33:B45) -> -66031.821 | C46: =SUM(C33:C45) -> -96383.586 | D46: =SUM(D33:D45) -> -146001.97 | E46: =SUM(E33:E45) -> -157750.76 | F46: =SUM(F33:F45) -> -232314.4 | G46: =SUM(G34:G45) -> 0 | H46: =SUM(H34:H45) -> 0 | I46: =SUM(I34:I45) -> 0 | J46: =SUM(J34:J45) -> 0 | K46: =SUM(K34:K45) -> 0 | L46: =SUM(L34:L45) -> 0 | M46: =SUM(M34:M45) -> 0 | N46: =SUM(B46:M46) -> -698482.54 | O46: =N46/$N$6 -> -0.21099208
A47: TOTAL GESTIO + SALARIS | B47: =B46+B31 -> -260700.76 | C47: =C46+C31 -> -357653.75 | D47: =D46+D31 -> -453277.39 | E47: =E46+E31 -> -413520.07 | F47: =F46+F31 -> -565210.35 | G47: =G46+G31 -> 0 | H47: =H46+H31 -> 0 | I47: =I46+I31 -> 0 | ... M47: =M46+M31 -> 0 | N47: =SUM(B47:M47) -> -2050362.3
A48: EBITDA | B48: =B6+(B16+B31+B46) -> -105747.74 | C48: =C6+(C16+C31+C46) -> -58771.177 | D48: =D6+(D16+D31+D46) -> -49985.096 | E48: =E6+(E16+E31+E46) -> -40324.302 | F48: =F6+(F16+F31+F46) -> 448085.38 | G48: =G6+(G16+G31+G46) -> 0 | H48: =H6+(H16+H31+H46) -> 0 | I48: =I6+(I16+I31+I46) -> 0 | ... M48: =M6+(M16+M31+M46) -> 0 | N48: =SUM(B48:M48) -> 193257.07
A49: % | B49: =B48/B6 -> -0.36552899 | C49: =C48/C6 -> -0.11238511 | D49: =D48/D6 -> -0.072082537 | E49: =E48/E6 -> -0.075774018 | F49: =F48/F6 -> 0.35209813 | N49: =N48/N6 -> 0.058377567

Sheet Casaments_05
A1: COMPTE DE RESULTATS 2026 | B1: Gener | C1: Febrer | D1: Març | E1: Abril | F1: Maig | G1: Juny | H1: Juliol | I1: Agost | J1: Setembre | K1: Octubre | L1: Novembre | M1: Desembre | N1: TOTAL
A2: . VENDES | B2: 19110.49 | C2: 33824.11 | D2: 85941.41 | E2: 197120.54 | F2: 628068.27 | N2: =SUM(B2:M2) -> 964064.82
A3: . ALTRES | B3: 7221 | C3: 11477.6 | E3: 14471 | F3: 68830.62 | N3: =SUM(B3:M3) -> 102000.22
A4: . PRESTACIO DE SEVEIS | B4: 0 | C4: 0 | D4: 0 | E4: 0 | F4: 0 | N4: =SUM(B4:M4) -> 0
A5: . ALTRES INGRESSOS | B5: 0 | C5: 0 | D5: 0 | E5: 1500 | F5: 3870 | N5: =SUM(B5:M5) -> 5370
A6: . INGRESSOS | F6: 4050 | N6: =SUM(B6:M6) -> 4050
A7: . VARIACIO EXISTENCIES | B7: 0 | C7: 0 | D7: 0 | E7: 0 | F7: 0 | N7: =SUM(B7:M7) -> 0
A8: TOTAL INGRESSOS EXPLOTACIO | B8: =SUM(B2:B7) -> 26331.49 | C8: =SUM(C2:C7) -> 45301.71 | D8: =SUM(D2:D7) -> 85941.41 | E8: =SUM(E2:E7) -> 213091.54 | F8: =SUM(F2:F7) -> 704818.89 | G8: =SUM(G2:G7) -> 0 | H8: =SUM(H2:H7) -> 0 | I8: =SUM(I2:I7) -> 0 | ... M8: =SUM(M2:M7) -> 0 | N8: =SUM(B8:M8) -> 1075485
A9: . COMPRA LN00000 s/precuintas | B9: -408725.23 | C9: -510110.91 | D9: -622510.5 | E9: -536165.77 | F9: -727844.97 | N9: =SUM(B9:M9) -> -2805357.4
A10: Precuinats | B10: =Precuinats_05!B11 -> -248909.16 | C10: =Precuinats_05!C11 -> -226949.34 | D10: =Precuinats_05!D11 -> -246027.31 | E10: =Precuinats_05!E11 -> -258992.74 | F10: =Precuinats_05!F11 -> -247173 | G10: =Precuinats_05!G11 -> 0 | H10: =Precuinats_05!H11 -> 0 | I10: =Precuinats_05!I11 -> 0 | ... M10: =Precuinats_05!M11 -> 0 | N10: =SUM(B10:M10) -> -1228051.6
A11: Green Vita | B11: ='Green Vita_05'!B8 -> -10867.987 | C11: ='Green Vita_05'!C8 -> -24849.577 | D11: ='Green Vita_05'!D8 -> -27767.548 | E11: ='Green Vita_05'!E8 -> -17762.685 | F11: ='Green Vita_05'!F8 -> -22083.3 | G11: ='Green Vita_05'!G8 -> 0 | H11: ='Green Vita_05'!H8 -> 0 | I11: ='Green Vita_05'!I8 -> 0 | ... M11: ='Green Vita_05'!M8 -> 0 | N11: =SUM(B11:M11) -> -103331.1
A12: Agenda | B12: =Agenda_05!B10 -> -3566.5975 | C12: =Agenda_05!C10 -> -4024.325 | D12: =Agenda_05!D10 -> -6430.88 | E12: =Agenda_05!E10 -> -5552.2625 | F12: =Agenda_05!F10 -> -9478.3325 | G12: =Agenda_05!G10 -> 0 | H12: =Agenda_05!H10 -> 0 | I12: =Agenda_05!I10 -> 0 | ... M12: =Agenda_05!M10 -> 0 | N12: =SUM(B12:M12) -> -29052.397
A13: Foodlovers | B13: =Foodlovers_05!B7 -> -267.12 | C13: =Foodlovers_05!C7 -> -11688.172 | D13: =Foodlovers_05!D7 -> -16802.674 | E13: =Foodlovers_05!E7 -> -34620.922 | F13: =Foodlovers_05!F7 -> -47688.346 | G13: =Foodlovers_05!G7 -> 0 | H13: =Foodlovers_05!H7 -> 0 | I13: =Foodlovers_05!I7 -> 0 | ... M13: =Foodlovers_05!M7 -> 0 | N13: =SUM(B13:M13) -> -111067.23
B14: =B9-(B10+B11+B12+B13) -> -145114.37 | C14: =C9-(C10+C11+C12+C13) -> -242599.5 | D14: =D9-(D10+D11+D12+D13) -> -325482.09 | E14: =E9-(E10+E11+E12+E13) -> -219237.16 | F14: =F9-(F10+F11+F12+F13) -> -401421.99 | G14: =G9-(G10+G11+G12+G13) -> 0 | H14: =H9-(H10+H11+H12+H13) -> 0 | I14: =I9-(I10+I11+I12+I13) -> 0 | ... M14: =M9-(M10+M11+M12+M13) -> 0 | N14: =SUM(B14:M14) -> -1333855.1
A15: Pestanya dades % aplicar | B15: =Dades!C121*B14 -> -12106.113 | C15: =Dades!E121*C14 -> -19340.51 | D15: =Dades!G121*D14 -> -35890.385 | E15: =Dades!I121*E14 -> -62686.555 | F15: =Dades!K121*F14 -> -143079.27 | G15: =Dades!L121*G14 -> 0 | I15: =Dades!N121*I14 -> 0 | J15: =Dades!O121*J14 -> 0 | K15: =Dades!P121*K14 -> 0 | L15: =Dades!Q121*L14 -> 0 | M15: =Dades!R121*M14 -> 0 | N15: =SUM(B15:M15) -> -273102.83
A16: . COMPRES | B16: -35 | C16: 0 | D16: 0 | E16: 0 | F16: -1472.78 | N16: =SUM(B16:M16) -> -1507.78
A17: . ALTRES APROVISIONAMENTS | B17: -494.07 | C17: -70.69 | D17: -700.47 | E17: -1110.1 | F17: -352.88 | N17: =SUM(B17:M17) -> -2728.21
A18: . APROVISIONAMENTS | E18: -53.52
A19: TOTAL COMPRES | B19: =SUM(B15:B17) -> -12635.183 | C19: =SUM(C15:C17) -> -19411.2 | D19: =SUM(D15:D17) -> -36590.855 | E19: =SUM(E15:E18) -> -63850.175 | F19: =SUM(F15:F17) -> -144904.93 | G19: =SUM(G16:G17) -> 0 | H19: =SUM(H16:H17) -> 0 | I19: =SUM(I16:I17) -> 0 | J19: =SUM(J16:J17) -> 0 | K19: =SUM(K16:K17) -> 0 | L19: =SUM(L16:L17) -> 0 | M19: =SUM(M16:M17) -> 0 | N19: =SUM(B19:M19) -> -277392.34 | O19: =N19/$N$8 -> -0.25792301
A20: . ESTRUCTURA LN00000 | B20: -532718.66 | C20: -537228.61 | D20: -580718.51 | E20: -607883.8 | F20: -646229.83 | N20: =SUM(B20:M20) -> -2904779.4
A21: Restem LN0001 | B21: -20000 | C21: -20000 | D21: -20000 | E21: -20000 | F21: -20000 | N21: =SUM(B21:M21) -> -100000
A22: Restem Green Vita | B22: ='Green Vita_05'!B20 -> -24563.585 | C22: ='Green Vita_05'!C20 -> -43419.493 | D22: ='Green Vita_05'!D20 -> -46702.057 | E22: ='Green Vita_05'!E20 -> -32602.222 | F22: ='Green Vita_05'!F20 -> -48606.81 | G22: ='Green Vita_05'!G20 -> 0 | H22: ='Green Vita_05'!H20 -> 0 | I22: ='Green Vita_05'!I20 -> 0 | ... M22: ='Green Vita_05'!M20 -> 0 | N22: =SUM(B22:M22) -> -195894.17
A23: Foodlovers | B23: =Foodlovers_05!B20 -> -14082.14 | C23: =Foodlovers_05!C20 -> -24870.01 | D23: =Foodlovers_05!D20 -> -28128.894 | E23: =Foodlovers_05!E20 -> -43343.766 | F23: =Foodlovers_05!F20 -> -48756.348 | G23: =Foodlovers_05!G20 -> 0 | H23: =Foodlovers_05!H20 -> 0 | I23: =Foodlovers_05!I20 -> 0 | ... M23: =Foodlovers_05!M20 -> 0 | N23: =SUM(B23:M23) -> -159181.16
A24: Agenda | B24: =Agenda_05!B17 -> -7190.3585 | C24: =Agenda_05!C17 -> -7414.595 | D24: =Agenda_05!D17 -> -8858.528 | E24: =Agenda_05!E17 -> -8331.3575 | F24: =Agenda_05!F17 -> -10686.999 | G24: =Agenda_05!G17 -> 0 | H24: =Agenda_05!H17 -> 0 | I24: =Agenda_05!I17 -> 0 | ... M24: =Agenda_05!M17 -> 0 | N24: =SUM(B24:M24) -> -42481.838
B25: =B21+B22+B23+B24 -> -65836.083 | C25: =C21+C22+C23+C24 -> -95704.098 | D25: =D21+D22+D23+D24 -> -103689.48 | E25: =E21+E22+E23+E24 -> -104277.35 | F25: =F21+F22+F23+F24 -> -128050.16 | G25: =G21+G22+G23+G24 -> 0 | H25: =H21+H22+H23+H24 -> 0 | I25: =I21+I22+I23+I24 -> 0 | ... M25: =M21+M22+M23+M24 -> 0 | N25: =SUM(B25:M25) -> -497557.16
A26: Pestanya dades % aplicar | B26: =(B20-B25)*Dades!C126 -> -14150.817 | C26: =(C20-C25)*Dades!E126 -> -18648.353 | D26: =(D20-D25)*Dades!G126 -> -30914.862 | E26: =(E20-E25)*Dades!I126 -> -81249.681 | F26: =(F20-F25)*Dades!K126 -> -144544.97 | G26: =(G20-G25)*Dades!H126 -> 0 | H26: =(H20-H25)*Dades!I126 -> 0 | I26: =(I20-I25)*Dades!J126 -> 0 | J26: =(J20-J25)*Dades!K126 -> 0 | K26: =(K20-K25)*Dades!L126 -> 0 | M26: =(M20-M25)*Dades!N126 -> 0 | N26: =SUM(B26:M26) -> -289508.68
A27: . SOUS I SALARIS dept. | B27: -14593.57 | C27: -14965.37 | D27: -15581.39 | E27: -16901.53 | F27: -18629.55 | N27: =SUM(B27:M27) -> -80671.41
B28: -2589.05 | C28: -4174.93 | D28: -8686.08 | E28: -10808.41 | F28: -25630.83 | N28: =SUM(B28:M28) -> -51889.3
A29: Pestanya dades % aplicar | B29: =B28*Dades!C121 -> -215.99056 | C29: =C28*Dades!$E$121 -> -332.83365 | D29: =D28*Dades!$G$121 -> -957.80004 | E29: =E28*Dades!$I$121 -> -3090.4524 | F29: =F28*Dades!$K$121 -> -9135.624 | G29: =G28*Dades!$C$121 -> 0 | H29: =H28*Dades!$C$121 -> 0 | I29: =I28*Dades!$C$121 -> 0 | J29: =J28*Dades!$C$121 -> 0 | K29: =K28*Dades!$C$121 -> 0 | L29: =L28*Dades!$C$121 -> 0 | M29: =M28*Dades!$C$121 -> 0 | N29: =SUM(B29:M29) -> -13732.701
A30: . INDEMNITZACIONS | B30: 0 | C30: 0 | D30: 0 | E30: 0 | F30: 0 | N30: =SUM(B30:M30) -> 0
A31: . SEGURETAT SOCIAL | B31: -4626.15 | C31: -4451.84 | D31: -4671.13 | E31: -5328.14 | F31: -5253.39 | N31: =SUM(B31:M31) -> -24330.65
A32: . ALTRES DESPESES SOCIALS | B32: 0 | C32: -126 | D32: -517.12 | E32: -199.96 | F32: -202.5 | N32: =SUM(B32:M32) -> -1045.58
A33: TOTAL COST SALARIAL | B33: =B26+B27+B29+B31+B32+B30 -> -33586.528 | C33: =C26+C27+C29+C31+C32+C30 -> -38524.397 | D33: =D26+D27+D29+D31+D32+D30 -> -52642.302 | E33: =E26+E27+E29+E31+E32+E30 -> -106769.76 | F33: =F26+F27+F29+F31+F32+F30 -> -177766.03 | G33: =G26+G27+G29+G31+G32+G30 -> 0 | H33: =H26+H27+H29+H31+H32+H30 -> 0 | I33: =I26+I27+I29+I31+I32+I30 -> 0 | ... M33: =M26+M27+M29+M31+M32+M30 -> 0 | N33: =SUM(B33:M33) -> -409289.02 | O33: =N33/$N$8 -> -0.38056226
A34: . GESTIO DE LN00000 | B34: -79477.48 | C34: -65034.81 | D34: -100634.18 | E34: -133354.73 | F34: -131629.55
A35: =Dades!R77 -> 0.14 | B35: =$A$35*B34 -> -11126.847 | C35: =$A$35*C34 -> -9104.8734 | D35: =$A$35*D34 -> -14088.785 | E35: =$A$35*E34 -> -18669.662 | F35: =$A$35*F34 -> -18428.137
A36: . ARRENDAMENTS I CANONS | B36: -24238.12 | C36: -25118.02 | D36: -26499.01 | E36: -26682.33 | F36: -25826.93 | N36: =SUM(B36:M36) -> -128364.41
A37: . REPARACIONS I CONSERVACIO | B37: -299.81 | C37: 0 | D37: -485.07 | E37: -670.45 | F37: -669.71 | N37: =SUM(B37:M37) -> -2125.04
A38: . SERVEIS PROFESSIONALS | B38: 0 | C38: -2286.08 | D38: -2322.8 | E38: -8013.02 | F38: -18171.29 | N38: =SUM(B38:M38) -> -30793.19
A39: . SERVEIS PROFESSIONALS | D39: -175 | E39: -630 | F39: -1830
A40: . TRANSPORTS | B40: 0 | C40: -1.2 | D40: 0 | E40: 0 | F40: 0 | N40: =SUM(B40:M40) -> -1.2
A41: . PRIMES D'ASSEGURANCES | B41: 0 | C41: 0 | D41: 0 | E41: 0 | F41: 0 | N41: =SUM(B41:M41) -> 0
A42: . SERVEIS BANCARIS | B42: -35.1 | C42: -74.91 | D42: -90.6 | E42: -39.45 | F42: -220.92 | N42: =SUM(B42:M42) -> -460.98
A43: . PUBLICITAT I PROPAGANDA | B43: -1610 | C43: -1946.92 | D43: -1937.19 | E43: -3922.8 | F43: -2809.07 | N43: =SUM(B43:M43) -> -12225.98
A44: . SUBMINISTRAMENTS | B44: 0 | C44: 0 | D44: 0 | E44: 0 | F44: 0 | N44: =SUM(B44:M44) -> 0
A45: . ALTRES DESPESES | B45: -2584.84 | C45: -1682.4 | D45: -3442.4 | E45: -3319.28 | F45: -13107.19 | N45: =SUM(B45:M45) -> -24136.11
A46: . DOTACIO PER INSOLVENCIA | B46: 0 | C46: 0 | D46: 0 | E46: 0 | F46: 0 | N46: =SUM(B46:M46) -> 0
A47: MOVIMENTS INTERNS | B47: 0 | C47: 0 | D47: 0 | E47: 0 | F47: 0 | N47: =SUM(B47:M47) -> 0
A48: TOTAL DESPESES GESTIO | B48: =SUM(B35:B47) -> -39894.717 | C48: =SUM(C35:C47) -> -40214.403 | D48: =SUM(D35:D47) -> -49040.855 | E48: =SUM(E35:E47) -> -61946.992 | F48: =SUM(F35:F47) -> -81063.247 | G48: =SUM(G36:G47) -> 0 | H48: =SUM(H36:H47) -> 0 | I48: =SUM(I36:I47) -> 0 | J48: =SUM(J36:J47) -> 0 | K48: =SUM(K36:K47) -> 0 | L48: =SUM(L36:L47) -> 0 | M48: =SUM(M36:M47) -> 0 | N48: =SUM(B48:M48) -> -272160.21 | O48: =N48/$N$8 -> -0.25305811
A49: TOTAL GESTIO + SALARIS | B49: =B48+B33 -> -73481.245 | C49: =C48+C33 -> -78738.8 | D49: =D48+D33 -> -101683.16 | E49: =E48+E33 -> -168716.76 | F49: =F48+F33 -> -258829.28 | G49: =G48+G33 -> 0 | H49: =H48+H33 -> 0 | I49: =I48+I33 -> 0 | ... M49: =M48+M33 -> 0 | N49: =SUM(B49:M49) -> -681449.24
A50: EBITDA | B50: =B8+(B19+B33+B48) -> -59784.939 | C50: =C8+(C19+C33+C48) -> -52848.29 | D50: =D8+(D19+D33+D48) -> -52332.602 | E50: =E8+(E19+E33+E48) -> -19475.391 | F50: =F8+(F19+F33+F48) -> 301084.69 | G50: =G8+(G19+G33+G48) -> 0 | H50: =H8+(H19+H33+H48) -> 0 | I50: =I8+(I19+I33+I48) -> 0 | ... M50: =M8+(M19+M33+M48) -> 0 | N50: =SUM(B50:M50) -> 116643.46
A51: % | B51: =B50/B8 -> -2.2704731 | C51: =C50/C8 -> -1.1665849 | D51: =D50/D8 -> -0.60893349 | E51: =E50/E8 -> -0.091394482 | F51: =F50/F8 -> 0.42718022 | N51: =N50/N8 -> 0.10845661

Sheet Precuinats_05
A1: COMPTE DE RESULTATS 2026 | B1: Gener | C1: Febrer | D1: Març | E1: Abril | F1: Maig | G1: Juny | H1: Juliol | I1: Agost | J1: Setembre | K1: Octubre | L1: Novembre | M1: Desembre | N1: TOTAL
A2: . VENDES | B2: 553131.46 | C2: 504331.86 | D2: 546727.36 | E2: 575539.43 | F2: 549273.34 | N2: =SUM(B2:M2) -> 2729003.4
A3: . RAPPEL 2% | B3: =-B2*0.02 -> -11062.629 | C3: =-C2*0.02 -> -10086.637 | D3: =-D2*0.02 -> -10934.547 | E3: =-E2*0.02 -> -11510.789 | F3: =-F2*0.02 -> -10985.467 | N3: =SUM(B3:M3) -> -54580.069
A4: . ALTRES INGRESSOS | B4: 0 | C4: 0 | D4: 0 | E4: 0 | F4: 0 | N4: =SUM(B4:M4) -> 0
A5: . VARIACIO EXISTENCIES | B5: 0 | C5: 0 | D5: 0 | E5: 0 | F5: 0 | N5: =SUM(B5:M5) -> 0
A6: TOTAL INGRESSOS EXPLOTACIO | B6: =SUM(B2:B5) -> 542068.83 | C6: =SUM(C2:C5) -> 494245.22 | D6: =SUM(D2:D5) -> 535792.81 | E6: =SUM(E2:E5) -> 564028.64 | F6: =SUM(F2:F5) -> 538287.87 | G6: =SUM(G2:G5) -> 0 | H6: =SUM(H2:H5) -> 0 | I6: =SUM(I2:I5) -> 0 | ... M6: =SUM(M2:M5) -> 0 | N6: =SUM(B6:M6) -> 2674423.4
A7: . COMPRES | F7: =SUM(G7:I7) -> 0 | N7: =SUM(B7:M7) -> 0
A8: . ALTRES APROVISIONAMENTS | F8: 0 | N8: =SUM(B8:M8) -> 0
A9: 0.45 | B9: =-B2*$A$9 -> -248909.16 | C9: =-C2*$A$9 -> -226949.34 | D9: =-D2*$A$9 -> -246027.31 | E9: =-E2*$A$9 -> -258992.74 | F9: =-F2*$A$9 -> -247173 | G9: =-G2*$A$9 -> 0 | H9: =-H2*$A$9 -> 0 | I9: =-I2*$A$9 -> 0 | ... M9: =-M2*$A$9 -> 0 | N9: =SUM(B9:M9) -> -1228051.6
A10: . VARIACIO EXISTENICIES COMPRES | F10: 0 | N10: =SUM(B10:M10) -> 0
A11: TOTAL COMPRES | B11: =SUM(B7:B10) -> -248909.16 | C11: =SUM(C7:C10) -> -226949.34 | D11: =SUM(D7:D10) -> -246027.31 | E11: =SUM(E7:E10) -> -258992.74 | F11: =SUM(F7:F10) -> -247173 | G11: =SUM(G7:G10) -> 0 | H11: =SUM(H7:H10) -> 0 | I11: =SUM(I7:I10) -> 0 | ... M11: =SUM(M7:M10) -> 0 | N11: =SUM(B11:M11) -> -1228051.6 | O11: =N11/$N$6 -> -0.45918367
A12: . ESTRUCTURA LN00000 | B12: -532718.66 | C12: -537228.61 | D12: -580718.51 | E12: -607883.8 | F12: -646229.83 | N12: =SUM(B12:M12) -> -2904779.4
A13: Restem LN0001 | B13: -20000 | C13: -20000 | D13: -20000 | E13: -20000 | F13: -20000 | N13: =SUM(B13:M13) -> -100000
A14: Restem Green Vita | B14: ='Green Vita_05'!B20 -> -24563.585 | C14: ='Green Vita_05'!C20 -> -43419.493 | D14: ='Green Vita_05'!D20 -> -46702.057 | E14: ='Green Vita_05'!E20 -> -32602.222 | F14: ='Green Vita_05'!F20 -> -48606.81 | G14: ='Green Vita_05'!G20 -> 0 | H14: ='Green Vita_05'!H20 -> 0 | I14: ='Green Vita_05'!I20 -> 0 | ... M14: ='Green Vita_05'!M20 -> 0 | N14: =SUM(B14:M14) -> -195894.17
A15: Foodlovers | B15: =Foodlovers_05!B20 -> -14082.14 | C15: =Foodlovers_05!C20 -> -24870.01 | D15: =Foodlovers_05!D20 -> -28128.894 | E15: =Foodlovers_05!E20 -> -43343.766 | F15: =Foodlovers_05!F20 -> -48756.348 | G15: =Foodlovers_05!G20 -> 0 | H15: =Foodlovers_05!H20 -> 0 | I15: =Foodlovers_05!I20 -> 0 | ... M15: =Foodlovers_05!M20 -> 0 | N15: =SUM(B15:M15) -> -159181.16
A16: Agenda | B16: =Agenda_05!B17 -> -7190.3585 | C16: =Agenda_05!C17 -> -7414.595 | D16: =Agenda_05!D17 -> -8858.528 | E16: =Agenda_05!E17 -> -8331.3575 | F16: =Agenda_05!F17 -> -10686.999 | G16: =Agenda_05!G17 -> 0 | H16: =Agenda_05!H17 -> 0 | I16: =Agenda_05!I17 -> 0 | ... M16: =Agenda_05!M17 -> 0 | N16: =SUM(B16:M16) -> -42481.838
B17: =SUM(B13:B16) -> -65836.083 | C17: =SUM(C13:C16) -> -95704.098 | D17: =SUM(D13:D16) -> -103689.48 | E17: =SUM(E13:E16) -> -104277.35 | F17: =SUM(F13:F16) -> -128050.16 | G17: =SUM(G13:G16) -> 0 | H17: =SUM(H13:H16) -> 0 | I17: =SUM(I13:I16) -> 0 | ... M17: =SUM(M13:M16) -> 0 | N17: =SUM(B17:M17) -> -497557.16
A18: Pestanya dades % aplicar | B18: =(B12-B17)*Dades!C127 -> -297258.62 | C18: =(C12-C17)*Dades!E127 -> -207607.15 | D18: =(D12-D17)*Dades!G127 -> -196668.88 | E18: =(E12-E17)*Dades!I127 -> -219447.45 | F18: =(F12-F17)*Dades!K127 -> -112645.53 | G18: =(G12-G17)*Dades!H127 -> 0 | H18: =(H12-H17)*Dades!I127 -> 0 | I18: =(I12-I17)*Dades!J127 -> 0 | J18: =(J12-J17)*Dades!K127 -> 0 | K18: =(K12-K17)*Dades!L127 -> 0 | L18: =(L12-L17)*Dades!M127 -> 0 | M18: =(M12-M17)*Dades!N127 -> 0 | N18: =SUM(B18:M18) -> -1033627.6
A19: . SOUS I SALARIS dept. | B19: -50301.51 | C19: -51584.76 | D19: -58122.77 | E19: -58505.6 | F19: -61890.8 | N19: =SUM(B19:M19) -> -280405.44
A20: . INDEMNITZACIONS | B20: 0 | C20: 0 | D20: -28100 | E20: 0 | F20: 0 | N20: =SUM(B20:M20) -> -28100
A21: . SEGURETAT SOCIAL | B21: -10903.14 | C21: -13495.5 | D21: -16003.53 | E21: -16541.71 | F21: -17869.29 | N21: =SUM(B21:M21) -> -74813.17
A22: . ALTRES DESPESES SOCIALS | B22: -437.49 | C22: -397.2 | D22: -852.13 | E22: -589.11 | F22: -289.8 | N22: =SUM(B22:M22) -> -2565.73
A23: TOTAL COST SALARIAL | B23: =SUM(B18:B22) -> -358900.76 | C23: =SUM(C18:C22) -> -273084.61 | D23: =SUM(D18:D22) -> -299747.31 | E23: =SUM(E18:E22) -> -295083.87 | F23: =SUM(F18:F22) -> -192695.42 | G23: =SUM(G18:G22) -> 0 | H23: =SUM(H18:H22) -> 0 | I23: =SUM(I18:I22) -> 0 | ... M23: =SUM(M18:M22) -> 0 | N23: =SUM(B23:M23) -> -1419512 | O23: =N23/$N$6 -> -0.53077309
A24: . GESTIO DE LN00000 | B24: -79477.48 | C24: -65034.81 | D24: -100634.18 | E24: -133354.73 | F24: -131629.55
A25: 0.3 | B25: =$A$25*B24 -> -23843.244 | C25: =$A$25*C24 -> -19510.443 | D25: =$A$25*D24 -> -30190.254 | E25: =$A$25*E24 -> -40006.419 | F25: =$A$25*F24 -> -39488.865 | G25: =$A$25*G24 -> 0 | H25: =$A$25*H24 -> 0 | I25: =$A$25*I24 -> 0 | ... L25: =$A$25*L24 -> 0
A26: . ARRENDAMENTS I CANONS | B26: -651 | C26: -588 | D26: -651 | E26: -630 | F26: 0 | N26: =SUM(B26:M26) -> -2520
A27: . REPARACIONS I CONSERVACIO | B27: -4139.51 | C27: -6150.86 | D27: -3917.62 | E27: -3576.16 | F27: -3301.79 | N27: =SUM(B27:M27) -> -21085.94
A28: . SERVEIS PROFESSIONALS | B28: 0 | C28: 0 | D28: 0 | E28: 0 | F28: 0 | N28: =SUM(B28:M28) -> 0
A29: . TRANSPORTS | B29: -739.5 | C29: -876.61 | D29: -901 | E29: -831.5 | F29: 0 | N29: =SUM(B29:M29) -> -3348.61
A30: . PRIMES D'ASSEGURANCES | B30: 0 | C30: 0 | D30: 0 | E30: 0 | F30: 0 | N30: =SUM(B30:M30) -> 0
A31: . SERVEIS BANCARIS | B31: 0 | C31: 0 | D31: 0 | E31: 0 | F31: 0 | N31: =SUM(B31:M31) -> 0
A32: . PUBLICITAT I PROPAGANDA | B32: 0 | C32: -1000 | D32: 0 | E32: 0 | F32: 0 | N32: =SUM(B32:M32) -> -1000
A33: . SUBMINISTRAMENTS | B33: -6018.27 | C33: -5218.85 | D33: -5349.47 | E33: -4620.58 | F33: -6679.36 | N33: =SUM(B33:M33) -> -27886.53
A34: . ALTRES DESPESES | B34: -281.94 | C34: 0 | D34: -157.16 | E34: -604.93 | F34: -1690 | N34: =SUM(B34:M34) -> -2734.03
A35: . DOTACIO PER INSOLVENCIA | B35: 0 | C35: 0 | D35: 0 | E35: 0 | F35: 0 | N35: =SUM(B35:M35) -> 0
A36: MOVIMENTS INTERNS | B36: 0 | C36: 0 | D36: 0 | E36: 0 | F36: 0 | N36: =SUM(B36:M36) -> 0
A37: TOTAL DESPESES GESTIO | B37: =SUM(B25:B36) -> -35673.464 | C37: =SUM(C25:C36) -> -33344.763 | D37: =SUM(D25:D36) -> -41166.504 | E37: =SUM(E25:E36) -> -50269.589 | F37: =SUM(F25:F36) -> -51160.015 | G37: =SUM(G25:G36) -> 0 | H37: =SUM(H25:H36) -> 0 | I37: =SUM(I25:I36) -> 0 | ... M37: =SUM(M25:M36) -> 0 | N37: =SUM(B37:M37) -> -211614.34 | O37: =N37/$N$6 -> -0.079125219
A38: TOTAL GESTIO + SALARIS | B38: =B37+B23 -> -394574.22 | C38: =C37+C23 -> -306429.37 | D38: =D37+D23 -> -340913.81 | E38: =E37+E23 -> -345353.46 | F38: =F37+F23 -> -243855.43 | G38: =G37+G23 -> 0 | H38: =H37+H23 -> 0 | I38: =I37+I23 -> 0 | ... M38: =M37+M23 -> 0 | N38: =SUM(B38:M38) -> -1631126.3
A39: EBITDA | B39: =B6+(B11+B23+B37) -> -101414.55 | C39: =C6+(C11+C23+C37) -> -39133.483 | D39: =D6+(D11+D23+D37) -> -51148.314 | E39: =E6+(E11+E23+E37) -> -40317.562 | F39: =F6+(F11+F23+F37) -> 47259.437 | G39: =G6+(G11+G23+G37) -> 0 | H39: =H6+(H11+H23+H37) -> 0 | I39: =I6+(I11+I23+I37) -> 0 | ... M39: =M6+(M11+M23+M37) -> 0 | N39: =SUM(B39:M39) -> -184754.47
A40: % | B40: =B39/B6 -> -0.18708795 | C40: =C39/C6 -> -0.079178273 | D40: =D39/D6 -> -0.095462859 | E40: =E39/E6 -> -0.071481409 | F40: =F39/F6 -> 0.087795841 | N40: =N39/N6 -> -0.069081982

Sheet Foodlovers_05
A1: COMPTE DE RESULTATS 2026 | B1: Gener | C1: Febrer | D1: Març | E1: Abril | F1: Maig | G1: Juny | H1: Juliol | I1: Agost | J1: Setembre | K1: Octubre | L1: Novembre | M1: Desembre | N1: TOTAL
A2: . VENDES | B2: 954 | C2: 41743.47 | D2: 60009.55 | E2: 123646.15 | F2: 170315.52 | N2: =SUM(B2:M2) -> 396668.69
A3: . PRESTACIO DE SEVEIS | B3: 0 | C3: 0 | D3: 0 | E3: 0 | F3: 0 | N3: =SUM(B3:M3) -> 0
A4: . ALTRES INGRESSOS | B4: 0 | C4: 0 | D4: 0 | E4: 0 | F4: 0 | N4: =SUM(B4:M4) -> 0
A5: . VARIACIO EXISTENCIES | B5: 0 | C5: 0 | D5: 0 | E5: 0 | F5: 0 | N5: =SUM(B5:M5) -> 0
A6: TOTAL INGRESSOS EXPLOTACIO | B6: =SUM(B2:B5) -> 954 | C6: =SUM(C2:C5) -> 41743.47 | D6: =SUM(D2:D5) -> 60009.55 | E6: =SUM(E2:E5) -> 123646.15 | F6: =SUM(F2:F5) -> 170315.52 | G6: =SUM(G2:G5) -> 0 | H6: =SUM(H2:H5) -> 0 | I6: =SUM(I2:I5) -> 0 | ... M6: =SUM(M2:M5) -> 0 | N6: =SUM(B6:M6) -> 396668.69
A7: 0.28 | B7: =-$A$7*B6 -> -267.12 | C7: =-$A$7*C6 -> -11688.172 | D7: =-$A$7*D6 -> -16802.674 | E7: =-$A$7*E6 -> -34620.922 | F7: =-$A$7*F6 -> -47688.346 | G7: =-$A$7*G6 -> 0 | H7: =-$A$7*H6 -> 0 | I7: =-$A$7*I6 -> 0 | ... M7: =-$A$7*M6 -> 0
B8: -8528.89 | C8: -5084.08 | D8: -1316.73 | E8: -15787.2 | F8: -532.89
A9: . ALTRES APROVISIONAMENTS | B9: -384.3 | C9: -1422.11 | D9: -1176.8 | E9: -278.62 | F9: 0 | N9: =SUM(B9:M9) -> -3261.83
A10: TOTAL COMPRES | B10: =SUM(B7:B9) -> -9180.31 | C10: =SUM(C7:C9) -> -18194.362 | D10: =SUM(D7:D9) -> -19296.204 | E10: =SUM(E7:E9) -> -50686.742 | F10: =SUM(F7:F9) -> -48221.236 | G10: =SUM(G7:G9) -> 0 | H10: =SUM(H7:H9) -> 0 | I10: =SUM(I7:I9) -> 0 | ... M10: =SUM(M7:M9) -> 0 | N10: =SUM(B10:M10) -> -145578.85 | O10: =N10/$N$6 -> -0.36700364
A11: . ESTRUCTURA Fixe | B11: -5000 | C11: -5000 | D11: -5000 | E11: -5000 | F11: -5000 | N11: =SUM(B11:M11) -> -25000
A12: 0.17 | B12: =-$A$12*B6 -> -162.18 | C12: =-$A$12*C6 -> -7096.3899 | D12: =-$A$12*D6 -> -10201.624 | E12: =-$A$12*E6 -> -21019.845 | F12: =-$A$12*F6 -> -28953.638 | N12: =SUM(B12:M12) -> -67433.677
B13: =SUM(B11:B12) -> -5162.18 | C13: =SUM(C11:C12) -> -12096.39 | D13: =SUM(D11:D12) -> -15201.624 | E13: =SUM(E11:E12) -> -26019.845 | F13: =SUM(F11:F12) -> -33953.638 | G13: =SUM(G11:G12) -> 0 | H13: =SUM(H11:H12) -> 0 | I13: =SUM(I11:I12) -> 0 | ... M13: =SUM(M11:M12) -> 0 | N13: =SUM(B13:M13) -> -92433.677
A14: . SOUS I SALARIS dept. | B14: -6809.58 | C14: -8658.47 | D14: -9486.11 | E14: -12134.68 | F14: -10741.55 | N14: =SUM(B14:M14) -> -47830.39
A15: . SALARIS | B15: 70 | C15: -1324.57 | D15: -317.75 | E15: -1038.5 | F15: -505 | N15: =SUM(B15:M15) -> -3115.82
A16: . INDEMNITZACIONS | B16: 0 | C16: 0 | D16: 0 | E16: 0 | F16: 0 | N16: =SUM(B16:M16) -> 0
A17: . SEGURETAT SOCIAL | B17: -2180.38 | C17: -2790.58 | D17: -3070.89 | E17: -4150.74 | F17: -3556.16 | N17: =SUM(B17:M17) -> -15748.75
A18: . ALTRES DESPESES SOCIALS | B18: 0 | C18: 0 | D18: -52.52 | E18: 0 | F18: 0 | N18: =SUM(B18:M18) -> -52.52
A19: . TRASPAS INTERN
A20: TOTAL COST SALARIAL | B20: =SUM(B13:B18) -> -14082.14 | C20: =SUM(C13:C18) -> -24870.01 | D20: =SUM(D13:D18) -> -28128.894 | E20: =SUM(E13:E18) -> -43343.766 | F20: =SUM(F13:F18) -> -48756.348 | G20: =SUM(G13:G18) -> 0 | H20: =SUM(H13:H18) -> 0 | I20: =SUM(I13:I18) -> 0 | ... M20: =SUM(M13:M18) -> 0 | N20: =SUM(B20:M20) -> -159181.16 | O20: =N20/$N$6 -> -0.40129499
A21: . GESTIO DE LN00000 | B21: -79477.48 | C21: -65034.81 | D21: -100634.18 | E21: -133354.73 | F21: -131629.55
A22: 0.08 | B22: =$A$22*B21 -> -6358.1984 | C22: =$A$22*C21 -> -5202.7848 | D22: =$A$22*D21 -> -8050.7344 | E22: =$A$22*E21 -> -10668.378 | F22: =$A$22*F21 -> -10530.364
A23: . ARRENDAMENTS I CANONS | B23: -9514.67 | C23: -13247.72 | D23: -16195.92 | E23: -34991.26 | F23: -17280.98 | N23: =SUM(B23:M23) -> -91230.55
A24: . REPARACIONS I CONSERVACIO | B24: -697.57 | C24: -594.98 | D24: -593.01 | E24: -1005.81 | F24: -567.37 | N24: =SUM(B24:M24) -> -3458.74
A25: . SERVEIS PROFESSIONALS | B25: -42 | C25: -1106.54 | D25: 0 | E25: -4526.66 | F25: -1619.27 | N25: =SUM(B25:M25) -> -7294.47
A26: . TRANSPORTS | B26: 0 | C26: 0 | D26: 0 | E26: -31.8 | F26: 0 | N26: =SUM(B26:M26) -> -31.8
A27: . PRIMES D'ASSEGURANCES | B27: 0 | C27: 0 | D27: 0 | E27: 0 | F27: 0 | N27: =SUM(B27:M27) -> 0
A28: . SERVEIS BANCARIS | B28: 1.1 | C28: -243.43 | D28: -77.85 | E28: -1036.19 | F28: -9.24 | N28: =SUM(B28:M28) -> -1365.61
A29: . PUBLICITAT I PROPAGANDA | B29: 0 | C29: -160 | D29: -87 | E29: -682 | F29: -112.93 | N29: =SUM(B29:M29) -> -1041.93
A30: . SUBMINISTRAMENTS | B30: 0 | C30: -257.85 | D30: 0 | E30: 0 | F30: -380 | N30: =SUM(B30:M30) -> -637.85
A31: . ALTRES DESPESES | B31: -1999.65 | C31: -738.04 | D31: -49 | E31: -3416.85 | F31: -208 | N31: =SUM(B31:M31) -> -6411.54
A32: . DOTACIO PER INSOLVENCIA | B32: 0 | C32: 0 | D32: 0 | E32: 0 | F32: 0 | N32: =SUM(B32:M32) -> 0
A33: MOVIMENTS INTERNS | B33: 0 | C33: 0 | D33: 0 | E33: 0 | F33: 0 | N33: =SUM(B33:M33) -> 0
A34: TOTAL DESPESES GESTIO | B34: =SUM(B22:B33) -> -18610.988 | C34: =SUM(C22:C33) -> -21551.345 | D34: =SUM(D22:D33) -> -25053.514 | E34: =SUM(E22:E33) -> -56358.948 | F34: =SUM(F22:F33) -> -30708.154 | G34: =SUM(G23:G33) -> 0 | H34: =SUM(H23:H33) -> 0 | I34: =SUM(I23:I33) -> 0 | J34: =SUM(J23:J33) -> 0 | K34: =SUM(K23:K33) -> 0 | L34: =SUM(L23:L33) -> 0 | M34: =SUM(M23:M33) -> 0 | N34: =SUM(B34:M34) -> -152282.95 | O34: =N34/$N$6 -> -0.38390464
A35: TOTAL GESTIO + SALARIS | B35: =B34+B20 -> -32693.128 | C35: =C34+C20 -> -46421.355 | D35: =D34+D20 -> -53182.408 | E35: =E34+E20 -> -99702.714 | F35: =F34+F20 -> -79464.502 | G35: =G34+G20 -> 0 | H35: =H34+H20 -> 0 | I35: =I34+I20 -> 0 | ... M35: =M34+M20 -> 0 | N35: =SUM(B35:M35) -> -311464.11
A36: EBITDA | B36: =B6+(B10+B20+B34) -> -40919.438 | C36: =C6+(C10+C20+C34) -> -22872.246 | D36: =D6+(D10+D20+D34) -> -12469.062 | E36: =E6+(E10+E20+E34) -> -26743.306 | F36: =F6+(F10+F20+F34) -> 42629.782 | G36: =G6+(G10+G20+G34) -> 0 | H36: =H6+(H10+H20+H34) -> 0 | I36: =I6+(I10+I20+I34) -> 0 | ... M36: =M6+(M10+M20+M34) -> 0 | N36: =SUM(B36:M36) -> -60374.271
A37: % | B37: =B36/B6 -> -42.892493 | C37: =C36/C6 -> -0.54792393 | D37: =D36/D6 -> -0.20778463 | E37: =E36/E6 -> -0.21628903 | F37: =F36/F6 -> 0.25029887 | N37: =N36/N6 -> -0.15220327

Sheet Green Vita_05
A1: COMPTE DE RESULTATS 2026 | B1: Gener | C1: Febrer | D1: Març | E1: Abril | F1: Maig | G1: Juny | H1: Juliol | I1: Agost | J1: Setembre | K1: Octubre | L1: Novembre | M1: Desembre | N1: TOTAL
A2: . VENDES | B2: 43471.95 | C2: 99398.31 | D2: 111070.19 | E2: 71050.74 | F2: 88333.2 | N2: =SUM(B2:M2) -> 413324.39
A3: . PRESTACIO DE SEVEIS | B3: 0 | C3: 0 | D3: 0 | E3: 0 | F3: 0 | N3: =SUM(B3:M3) -> 0
A4: . ALTRES INGRESSOS | B4: 0 | C4: 0 | D4: 0 | E4: 0 | F4: 0 | N4: =SUM(B4:M4) -> 0
A5: . VARIACIO EXISTENCIES | B5: 0 | C5: 0 | D5: 0 | E5: 0 | F5: 0 | N5: =SUM(B5:M5) -> 0
A6: TOTAL INGRESSOS EXPLOTACIO | B6: =SUM(B2:B5) -> 43471.95 | C6: =SUM(C2:C5) -> 99398.31 | D6: =SUM(D2:D5) -> 111070.19 | E6: =SUM(E2:E5) -> 71050.74 | F6: =SUM(F2:F5) -> 88333.2 | G6: =SUM(G2:G5) -> 0 | H6: =SUM(H2:H5) -> 0 | I6: =SUM(I2:I5) -> 0 | ... M6: =SUM(M2:M5) -> 0 | N6: =SUM(B6:M6) -> 413324.39
N7: =SUM(B7:M7) -> 0
A8: 0.25 | B8: =-B6*$A$8 -> -10867.987 | C8: =-C6*$A$8 -> -24849.577 | D8: =-D6*$A$8 -> -27767.548 | E8: =-E6*$A$8 -> -17762.685 | F8: =-F6*$A$8 -> -22083.3
A9: . COMPRES | B9: 0 | C9: 0 | D9: 0 | E9: -1790.1 | F9: -1643.31 | N9: =SUM(B9:M9) -> -3433.41
A10: . ALTRES APROVISIONAMENTS | B10: 0 | C10: 0 | D10: 0 | E10: -533.85 | F10: -581.74 | N10: =SUM(B10:M10) -> -1115.59
A11: TOTAL COMPRES | B11: =B9+B10+B8 -> -10867.987 | C11: =C9+C10+C8 -> -24849.577 | D11: =D9+D10+D8 -> -27767.548 | E11: =E9+E10+E8 -> -20086.635 | F11: =F9+F10+F8 -> -24308.35 | G11: =SUM(G9:G10) -> 0 | H11: =SUM(H9:H10) -> 0 | I11: =SUM(I9:I10) -> 0 | J11: =SUM(J9:J10) -> 0 | K11: =SUM(K9:K10) -> 0 | L11: =SUM(L9:L10) -> 0 | M11: =SUM(M9:M10) -> 0 | N11: =SUM(B11:M11) -> -107880.1 | O11: =N11/$N$6 -> -0.26100588
A12: ESTRUCTURA FIXE | B12: -5000 | C12: -5000 | D12: -5000 | E12: -5000 | F12: -5000 | N12: =SUM(B12:M12) -> -25000
A13: 0.15 | B13: =$A$13*-B6 -> -6520.7925 | C13: =$A$13*-C6 -> -14909.746 | D13: =$A$13*-D6 -> -16660.529 | E13: =$A$13*-E6 -> -10657.611 | F13: =$A$13*-F6 -> -13249.98 | N13: =SUM(B13:M13) -> -61998.658
B14: =SUM(B12:B13) -> -11520.792 | C14: =SUM(C12:C13) -> -19909.747 | D14: =SUM(D12:D13) -> -21660.529 | E14: =SUM(E12:E13) -> -15657.611 | F14: =SUM(F12:F13) -> -18249.98 | G14: =SUM(G12:G13) -> 0 | H14: =SUM(H12:H13) -> 0 | I14: =SUM(I12:I13) -> 0 | ... M14: =SUM(M12:M13) -> 0 | N14: =SUM(B14:M14) -> -86998.659
A15: . SOUS I SALARIS dept. | B15: 0 | C15: 0 | D15: 0 | E15: 0 | F15: -9291.48 | N15: =SUM(B15:M15) -> -9291.48
A16: . INDEMNITZACIONS | B16: 0 | C16: 0 | D16: 0 | E16: 0 | F16: 0 | N16: =SUM(B16:M16) -> 0
A17: . SEGURETAT SOCIAL | B17: 0 | C17: 0 | D17: 0 | E17: 0 | F17: -2815.37 | N17: =SUM(B17:M17) -> -2815.37
A18: . ALTRES DESPESES SOCIALS | B18: 0 | C18: 0 | D18: 0 | E18: 0 | F18: 0 | N18: =SUM(B18:M18) -> 0
A19: . TRASPAS INTERN | B19: -1522 | C19: -3600 | D19: -3381 | E19: -1287 | N19: =SUM(B19:M19) -> -9790
A20: TOTAL COST SALARIAL | B20: =SUM(B12:B19) -> -24563.585 | C20: =SUM(C12:C19) -> -43419.493 | D20: =SUM(D12:D19) -> -46702.057 | E20: =SUM(E12:E19) -> -32602.222 | F20: =SUM(F12:F19) -> -48606.81 | G20: =SUM(G12:G18) -> 0 | H20: =SUM(H12:H18) -> 0 | I20: =SUM(I12:I18) -> 0 | J20: =SUM(J12:J18) -> 0 | K20: =SUM(K12:K18) -> 0 | L20: =SUM(L12:L18) -> 0 | M20: =SUM(M12:M18) -> 0 | N20: =SUM(B20:M20) -> -195894.17 | O20: =N20/$N$6 -> -0.47394776
A21: . GESTIO DE LN00000 | B21: -79477.48 | C21: -65034.81 | D21: -100634.18 | E21: -133354.73 | F21: -131629.55
A22: 0.04 | B22: =$A$22*B21 -> -3179.0992 | C22: =$A$22*C21 -> -2601.3924 | D22: =$A$22*D21 -> -4025.3672 | E22: =$A$22*E21 -> -5334.1892 | F22: =$A$22*F21 -> -5265.182
A23: . ARRENDAMENTS I CANONS | B23: -6967.35 | C23: -19408.74 | D23: -14214.11 | E23: -6327.02 | F23: 0 | N23: =SUM(B23:M23) -> -46917.22
A24: . REPARACIONS I CONSERVACIO | B24: 0 | C24: 0 | D24: 0 | E24: 0 | F24: -40 | N24: =SUM(B24:M24) -> -40
A25: . SERVEIS PROFESSIONALS | B25: 0 | C25: 0 | D25: 0 | E25: 0 | F25: 0 | N25: =SUM(B25:M25) -> 0
A26: . TRANSPORTS | B26: 0 | C26: 0 | D26: 0 | E26: 0 | F26: 0 | N26: =SUM(B26:M26) -> 0
A27: . PRIMES D'ASSEGURANCES | B27: 0 | C27: 0 | D27: 0 | E27: 0 | F27: 0 | N27: =SUM(B27:M27) -> 0
A28: . SERVEIS BANCARIS | B28: 0 | C28: 0 | D28: 0 | E28: 0 | F28: 0 | N28: =SUM(B28:M28) -> 0
A29: . PUBLICITAT I PROPAGANDA | B29: 0 | C29: -1991.16 | D29: 0 | E29: 0 | F29: 0 | N29: =SUM(B29:M29) -> -1991.16
A30: . SUBMINISTRAMENTS | B30: 0 | C30: 0 | D30: 0 | E30: 0 | F30: 0 | N30: =SUM(B30:M30) -> 0
A31: . ALTRES DESPESES | B31: 0 | C31: 0 | D31: -2588.09 | E31: -1974.45 | F31: -21911.7 | N31: =SUM(B31:M31) -> -26474.24
A32: . DOTACIO PER INSOLVENCIA | B32: 0 | C32: 0 | D32: -733.14 | E32: 0 | F32: 0 | N32: =SUM(B32:M32) -> -733.14
A33: MOVIMENTS INTERNS | B33: 0 | C33: 0 | D33: 0 | E33: 0 | F33: 0 | N33: =SUM(B33:M33) -> 0
A34: TOTAL DESPESES GESTIO | B34: =SUM(B22:B33) -> -10146.449 | C34: =SUM(C22:C33) -> -24001.292 | D34: =SUM(D22:D33) -> -21560.707 | E34: =SUM(E22:E33) -> -13635.659 | F34: =SUM(F22:F33) -> -27216.882 | G34: =SUM(G23:G33) -> 0 | H34: =SUM(H23:H33) -> 0 | I34: =SUM(I23:I33) -> 0 | J34: =SUM(J23:J33) -> 0 | K34: =SUM(K23:K33) -> 0 | L34: =SUM(L23:L33) -> 0 | M34: =SUM(M23:M33) -> 0 | N34: =SUM(B34:M34) -> -96560.99 | O34: =N34/$N$6 -> -0.23362035
A35: TOTAL GESTIO + SALARIS | B35: =B34+B20 -> -34710.034 | C35: =C34+C20 -> -67420.785 | D35: =D34+D20 -> -68262.764 | E35: =E34+E20 -> -46237.881 | F35: =F34+F20 -> -75823.692 | G35: =G34+G20 -> 0 | H35: =H34+H20 -> 0 | I35: =I34+I20 -> 0 | ... M35: =M34+M20 -> 0 | N35: =SUM(B35:M35) -> -292455.16
A36: EBITDA | B36: =B6+(B11+B20+B34) -> -2106.0717 | C36: =C6+(C11+C20+C34) -> 7127.9471 | D36: =D6+(D11+D20+D34) -> 15039.878 | E36: =E6+(E11+E20+E34) -> 4726.2238 | F36: =F6+(F11+F20+F34) -> -11798.842 | G36: =G6+(G11+G20+G34) -> 0 | H36: =H6+(H11+H20+H34) -> 0 | I36: =I6+(I11+I20+I34) -> 0 | ... M36: =M6+(M11+M20+M34) -> 0 | N36: =SUM(B36:M36) -> 12989.135
A37: % | B37: =B36/B6 -> -0.048446681 | C37: =C36/C6 -> 0.071710949 | D37: =D36/D6 -> 0.13540877 | E37: =E36/E6 -> 0.066518995 | F37: =F36/F6 -> -0.133572 | N37: =N36/N6 -> 0.031426008

Sheet TOTAL
A1: COMPTE DE RESULTATS 2026 | B1: Gener | C1: Febrer | D1: Març | E1: Abril | F1: Maig | G1: Juny | H1: Juliol | I1: Agost | J1: Setembre | K1: Octubre | L1: Novembre | M1: Desembre | N1: TOTAL
A2: . VENDES | N2: =SUM(B2:M2) -> 0
A3: . PRESTACIO DE SEVEIS | N3: =SUM(B3:M3) -> 0
A4: . ALTRES INGRESSOS | N4: =SUM(B4:M4) -> 0
A5: . VARIACIO EXISTENCIES | N5: =SUM(B5:M5) -> 0
A6: TOTAL INGRESSOS EXPLOTACIO | B6: =Precuinats_05!B6+Empresa_05!B6+Casaments_05!B8+Foodlovers_05!B6+'Green Vita_05'!B6+Restaurants_05!B7+Agenda_05!B6 -> 1309460.7 | C6: =Precuinats_05!C6+Empresa_05!C6+Casaments_05!C8+Foodlovers_05!C6+'Green Vita_05'!C6+Restaurants_05!C7+Agenda_05!C6 -> 1693888.4 | D6: =Precuinats_05!D6+Empresa_05!D6+Casaments_05!D8+Foodlovers_05!D6+'Green Vita_05'!D6+Restaurants_05!D7+Agenda_05!D6 -> 2098899 | E6: =Precuinats_05!E6+Empresa_05!E6+Casaments_05!E8+Foodlovers_05!E6+'Green Vita_05'!E6+Restaurants_05!E7+Agenda_05!E6 -> 2118885.9 | F6: =Precuinats_05!F6+Empresa_05!F6+Casaments_05!F8+Foodlovers_05!F6+'Green Vita_05'!F6+Restaurants_05!F7+Agenda_05!F6 -> 3459181.8 | G6: =Precuinats_05!G6+Empresa_05!G6+Casaments_05!G8+Foodlovers_05!G6+'Green Vita_05'!G6+Restaurants_05!G7+Agenda_05!G6 -> 0 | H6: =Precuinats_05!H6+Empresa_05!H6+Casaments_05!H8+Foodlovers_05!H6+'Green Vita_05'!H6+Restaurants_05!H7+Agenda_05!H6 -> 0 | I6: =Precuinats_05!I6+Empresa_05!I6+Casaments_05!I8+Foodlovers_05!I6+'Green Vita_05'!I6+Restaurants_05!I7+Agenda_05!I6 -> 0 | ... M6: =Precuinats_05!M6+Empresa_05!M6+Casaments_05!M8+Foodlovers_05!M6+'Green Vita_05'!M6+Restaurants_05!M7+Agenda_05!M6 -> 0 | N6: =SUM(B6:M6)+REAL_05!D5 -> 10683320 | O6: =N6+(Precuinats_05!N3*-1) -> 10737900
A7: . COMPRES | G7: =Precuinats_05!G11+Empresa_05!G16+Casaments_05!G19+Foodlovers_05!G10+'Green Vita_05'!G11+Restaurants_05!G13+Agenda_05!G10 -> 0 | H7: =Precuinats_05!H11+Empresa_05!H16+Casaments_05!H19+Foodlovers_05!H10+'Green Vita_05'!H11+Restaurants_05!H13+Agenda_05!H10 -> 0 | I7: =Precuinats_05!I11+Empresa_05!I16+Casaments_05!I19+Foodlovers_05!I10+'Green Vita_05'!I11+Restaurants_05!I13+Agenda_05!I10 -> 0 | J7: =Precuinats_05!J11+Empresa_05!J16+Casaments_05!J19+Foodlovers_05!J10+'Green Vita_05'!J11+Restaurants_05!J13+Agenda_05!J10 -> 0 | K7: =Precuinats_05!K11+Empresa_05!K16+Casaments_05!K19+Foodlovers_05!K10+'Green Vita_05'!K11+Restaurants_05!K13+Agenda_05!K10 -> 0 | L7: =Precuinats_05!L11+Empresa_05!L16+Casaments_05!L19+Foodlovers_05!L10+'Green Vita_05'!L11+Restaurants_05!L13+Agenda_05!L10 -> 0 | M7: =Precuinats_05!M11+Empresa_05!M16+Casaments_05!M19+Foodlovers_05!M10+'Green Vita_05'!M11+Restaurants_05!M13+Agenda_05!M10 -> 0 | N7: =SUM(B7:M7) -> 0
A8: . ALTRES APROVISIONAMENTS | N8: =SUM(B8:M8) -> 0
A9: . CONSUMS INTERNS | N9: =SUM(B9:M9) -> 0
A10: . VARIACIO EXISTENICIES COMPRES | N10: =SUM(B10:M10) -> 0
A11: TOTAL COMPRES | B11: =Agenda_05!B10+Restaurants_05!B10+Empresa_05!B16+Casaments_05!B19+Precuinats_05!B11+Foodlovers_05!B10+'Green Vita_05'!B11 -> -511389.47 | C11: =Agenda_05!C10+Restaurants_05!C10+Empresa_05!C16+Casaments_05!C19+Precuinats_05!C11+Foodlovers_05!C10+'Green Vita_05'!C11 -> -629095.73 | D11: =Agenda_05!D10+Restaurants_05!D10+Empresa_05!D16+Casaments_05!D19+Precuinats_05!D11+Foodlovers_05!D10+'Green Vita_05'!D11 -> -755153.14 | E11: =Agenda_05!E10+Restaurants_05!E10+Empresa_05!E16+Casaments_05!E19+Precuinats_05!E11+Foodlovers_05!E10+'Green Vita_05'!E11 -> -689585.16 | F11: =Agenda_05!F10+Restaurants_05!F10+Empresa_05!F16+Casaments_05!F19+Precuinats_05!F11+Foodlovers_05!F10+'Green Vita_05'!F11 -> -871205.78 | G11: =Agenda_05!G10+Restaurants_05!G10+Empresa_05!G16+Casaments_05!G19+Precuinats_05!G11+Foodlovers_05!G10+'Green Vita_05'!G11 -> 0 | H11: =Agenda_05!H10+Restaurants_05!H10+Empresa_05!H16+Casaments_05!H19+Precuinats_05!H11+Foodlovers_05!H10+'Green Vita_05'!H11 -> 0 | I11: =Agenda_05!I10+Restaurants_05!I10+Empresa_05!I16+Casaments_05!I19+Precuinats_05!I11+Foodlovers_05!I10+'Green Vita_05'!I11 -> 0 | ... M11: =Agenda_05!M10+Restaurants_05!M10+Empresa_05!M16+Casaments_05!M19+Precuinats_05!M11+Foodlovers_05!M10+'Green Vita_05'!M11 -> 0 | N11: =SUM(B11:M11) -> -3456429.3 | O11: =N11/$O$6 -> -0.32189062
A12: . ESTRUCTURA FIX | N12: =SUM(B12:M12) -> 0
A13: . SOUS I SALARIS | N13: =SUM(B13:M13) -> 0
A14: . INDEMNITZACIONS | N14: =SUM(B14:M14) -> 0
A15: . SEGURETAT SOCIAL | N15: =SUM(B15:M15) -> 0
A16: . ALTRES DESPESES SOCIALS | N16: =SUM(B16:M16) -> 0
A17: TOTAL COST SALARIAL | B17: =Precuinats_05!B23+Empresa_05!B31+Casaments_05!B33+Foodlovers_05!B20+'Green Vita_05'!B20+Restaurants_05!B20+Agenda_05!B17 -> -967621.35 | C17: =Precuinats_05!C23+Empresa_05!C31+Casaments_05!C33+Foodlovers_05!C20+'Green Vita_05'!C20+Restaurants_05!C20+Agenda_05!C17 -> -976755.54 | D17: =Precuinats_05!D23+Empresa_05!D31+Casaments_05!D33+Foodlovers_05!D20+'Green Vita_05'!D20+Restaurants_05!D20+Agenda_05!D17 -> -1094768.4 | E17: =Precuinats_05!E23+Empresa_05!E31+Casaments_05!E33+Foodlovers_05!E20+'Green Vita_05'!E20+Restaurants_05!E20+Agenda_05!E17 -> -1102783.7 | F17: =Precuinats_05!F23+Empresa_05!F31+Casaments_05!F33+Foodlovers_05!F20+'Green Vita_05'!F20+Restaurants_05!F20+Agenda_05!F17 -> -1168867.4 | G17: =Precuinats_05!G23+Empresa_05!G31+Casaments_05!G33+Foodlovers_05!G20+'Green Vita_05'!G20+Restaurants_05!G20+Agenda_05!G17 -> 0 | H17: =Precuinats_05!H23+Empresa_05!H31+Casaments_05!H33+Foodlovers_05!H20+'Green Vita_05'!H20+Restaurants_05!H20+Agenda_05!H17 -> 0 | I17: =Precuinats_05!I23+Empresa_05!I31+Casaments_05!I33+Foodlovers_05!I20+'Green Vita_05'!I20+Restaurants_05!I20+Agenda_05!I17 -> 0 | ... M17: =Precuinats_05!M23+Empresa_05!M31+Casaments_05!M33+Foodlovers_05!M20+'Green Vita_05'!M20+Restaurants_05!M20+Agenda_05!M17 -> 0 | N17: =SUM(B17:M17) -> -5310796.3 | O17: =N17/$O$6 -> -0.49458426
A18: . ARRENDAMENTS I CANONS
A19: . REPARACIONS I CONSERVACIO
A20: . SERVEIS PROFESSIONALS
A21: . TRANSPORTS
A22: . PRIMES D'ASSEGURANCES
A23: . SERVEIS BANCARIS
A24: . PUBLICITAT I PROPAGANDA
A25: . SUBMINISTRAMENTS
A26: . ALTRES DESPESES
A27: . ALTRES TRIBUTS
A28: . DOTACIO PER INSOLVENCIA
A29: MOVIMENTS INTERNS
A30: TOTAL DESPESES GESTIO | B30: =Restaurants_05!B34+Empresa_05!B46+Casaments_05!B48+Precuinats_05!B37+Foodlovers_05!B34+'Green Vita_05'!B34 -> -250449.99 | C30: =Restaurants_05!C34+Empresa_05!C46+Casaments_05!C48+Precuinats_05!C37+Foodlovers_05!C34+'Green Vita_05'!C34 -> -300262.07 | D30: =Restaurants_05!D34+Empresa_05!D46+Casaments_05!D48+Precuinats_05!D37+Foodlovers_05!D34+'Green Vita_05'!D34 -> -384814.58 | E30: =Restaurants_05!E34+Empresa_05!E46+Casaments_05!E48+Precuinats_05!E37+Foodlovers_05!E34+'Green Vita_05'!E34 -> -449639.69 | F30: =Restaurants_05!F34+Empresa_05!F46+Casaments_05!F48+Precuinats_05!F37+Foodlovers_05!F34+'Green Vita_05'!F34 -> -524962.61 | G30: =Restaurants_05!G34+Empresa_05!G46+Casaments_05!G48+Precuinats_05!G37+Foodlovers_05!G34+'Green Vita_05'!G34 -> 0 | H30: =Restaurants_05!H34+Empresa_05!H46+Casaments_05!H48+Precuinats_05!H37+Foodlovers_05!H34+'Green Vita_05'!H34 -> 0 | I30: =Restaurants_05!I34+Empresa_05!I46+Casaments_05!I48+Precuinats_05!I37+Foodlovers_05!I34+'Green Vita_05'!I34 -> 0 | ... M30: =Restaurants_05!M34+Empresa_05!M46+Casaments_05!M48+Precuinats_05!M37+Foodlovers_05!M34+'Green Vita_05'!M34 -> 0 | N30: =SUM(B30:M30) -> -1910128.9 | O30: =N30/$O$6 -> -0.17788664
A31: TOTAL GESTIO + SALARIS | B31: =B30+B17 -> -1218071.3 | C31: =C30+C17 -> -1277017.6 | D31: =D30+D17 -> -1479583 | E31: =E30+E17 -> -1552423.4 | F31: =F30+F17 -> -1693830 | G31: =G30+G17 -> 0 | H31: =H30+H17 -> 0 | I31: =I30+I17 -> 0 | ... M31: =M30+M17 -> 0 | N31: =SUM(B31:M31) -> -7220925.3
A32: EBITDA | B32: =B6+(B11+B17+B30) -> -420000.08 | C32: =C6+(C11+C17+C30) -> -212224.97 | D32: =D6+(D11+D17+D30) -> -135837.1 | E32: =E6+(E11+E17+E30) -> -123122.59 | F32: =F6+(F11+F17+F30) -> 894146.03 | G32: =G6+(G11+G17+G30) -> 0 | H32: =H6+(H11+H17+H30) -> 0 | I32: =I6+(I11+I17+I30) -> 0 | ... M32: =M6+(M11+M17+M30) -> 0 | N32: =O6+(N11+N17+N30) -> 60545.569
A33: % | B33: =B32/B6 -> -0.32074279 | C33: =C32/C6 -> -0.12528864 | D33: =D32/D6 -> -0.064718266 | E33: =E32/E6 -> -0.058107228 | F33: =F32/F6 -> 0.25848483 | N33: =N32/N6 -> 0.005667299

Sheet REAL_05
A1: Node | B1: Description | C1: TOTAL | D1: LN00000 | E1: LN00001 | F1: LN00002 | G1: LN00003 | H1: LN00004 | I1: LN00005 | J1: LN00006 | K1: Sin LN
A2: 1 | B2: COMPTE DE RESULTATS | C2: 0 | D2: 0 | E2: 0 | F2: 0 | G2: 0 | H2: 0 | I2: 0 | J2: 0 | K2: 0
A3: 2 | B3: . VENDES | C3: =SUM(D3:J3)+71792.57 -> 3455401.6 | D3: 34909.12 | E3: 640094.54 | F3: 1272615.1 | G3: 628068.27 | H3: 549273.34 | I3: 170315.52 | J3: 88333.2 | K3: 0
A4: 3 | B4: . PRESTACIO DE SEVEIS | C4: =SUM(D4:J4) -> 0 | D4: 0 | E4: 0 | F4: 0 | G4: 0 | H4: 0 | I4: 0 | J4: 0 | K4: 0
A5: 4 | B5: . ALTRES INGRESSOS | C5: =SUM(D5:J5)+4800 -> 16292.16 | D5: 3004.21 | E5: 4617.95 | F5: 0 | G5: 3870 | H5: 0 | I5: 0 | J5: 0 | K5: 0
A6: 5 | B6: . VARIACIO EXISTENCIES | C6: =SUM(D6:J6) -> 0 | D6: 0 | E6: 0 | F6: 0 | G6: 0 | H6: 0 | I6: 0 | J6: 0 | K6: 0
A7: 6 | B7: TOTAL INGRESSOS EXPLOTACIO | C7: =SUM(C3:C6) -> 3471693.8 | D7: =SUM(D3:D6) -> 37913.33 | E7: =SUM(E3:E6) -> 644712.49 | F7: =SUM(F3:F6) -> 1272615.1 | G7: =SUM(G3:G6) -> 631938.27 | H7: =SUM(H3:H6) -> 549273.34 | I7: =SUM(I3:I6) -> 170315.52 | J7: =SUM(J3:J6) -> 88333.2 | K7: 0
A8: 7 | B8: . COMPRES | C8: =SUM(D8:J8) -> -756705.33 | D8: -622826.77 | E8: -129731.94 | F8: -497.64 | G8: -1472.78 | H8: 0 | I8: -532.89 | J8: -1643.31 | K8: 0
A9: 8 | B9: . ALTRES APROVISIONAMENTS | C9: =SUM(D9:J9) -> -114500.45 | D9: -105018.2 | E9: -8068.66 | F9: -478.97 | G9: -352.88 | H9: 0 | I9: 0 | J9: -581.74 | K9: 0
A10: 9 | B10: . CONSUMS INTERNS | C10: =SUM(D10:J10) -> 0 | D10: 0 | E10: 0 | F10: 0 | G10: 0 | H10: 0 | I10: 0 | J10: 0 | K10: 0
A11: 10 | B11: . VARIACIO EXISTENICIES COMPRES | C11: =SUM(D11:J11) -> 0 | D11: 0 | E11: 0 | F11: 0 | G11: 0 | H11: 0 | I11: 0 | J11: 0 | K11: 0
A12: 11 | B12: TOTAL COMPRES | C12: =SUM(C8:C11) -> -871205.78 | D12: =SUM(D8:D11) -> -727844.97 | E12: =SUM(E8:E11) -> -137800.6 | F12: =SUM(F8:F11) -> -976.61 | G12: =SUM(G8:G11) -> -1825.66 | H12: =SUM(H8:H11) -> 0 | I12: =SUM(I8:I11) -> -532.89 | J12: =SUM(J8:J11) -> -2225.05 | K12: 0
A13: 12 | B13: MARGE BRUT TOTAL | C13: 2523895.4 | D13: -689931.64 | E13: 506911.89 | F13: 1271638.5 | G13: 630112.61 | H13: 549273.34 | I13: 169782.63 | J13: 86108.15 | K13: 0
A14: 13 | B14: . SOUS I SALARIS | C14: =SUM(D14:J14)-47110.02 -> -926239.01 | D14: -495789.03 | E14: =-253123.37-4972.41 -> -258095.78 | F14: -24690.8 | G14: -18629.55 | H14: -61890.8 | I14: -10741.55 | J14: -9291.48 | K14: 0
A15: 14 | B15: . INDEMNITZACIONS | C15: =SUM(D15:J15) -> -4200 | D15: -2000 | E15: -2200 | F15: 0 | G15: 0 | H15: 0 | I15: 0 | J15: 0 | K15: 0
A16: 15 | B16: . SEGURETAT SOCIAL | C16: =SUM(D16:J16) -> -252422.23 | D16: -139805.97 | E16: -75385.48 | F16: -7736.57 | G16: -5253.39 | H16: -17869.29 | I16: -3556.16 | J16: -2815.37 | K16: 0
A17: 16 | B17: . ALTRES DESPESES SOCIALS | C17: =SUM(D17:J17) -> -11144.6 | D17: -8634.83 | E17: -1778.57 | F17: -238.9 | G17: -202.5 | H17: -289.8 | I17: 0 | J17: 0 | K17: 0
A18: 17 | B18: TOTAL COST SALARIAL | C18: =SUM(C14:C17) -> -1194005.8 | D18: =SUM(D14:D17) -> -646229.83 | E18: =SUM(E14:E17) -> -337459.83 | F18: =SUM(F14:F17) -> -32666.27 | G18: =SUM(G14:G17) -> -24085.44 | H18: =SUM(H14:H17) -> -80049.89 | I18: =SUM(I14:I17) -> -14297.71 | J18: =SUM(J14:J17) -> -12106.85 | K18: 0
A19: 18 | B19: . ARRENDAMENTS I CANONS | C19: =SUM(D19:J19) -> -123870.15 | D19: -7843.71 | E19: -44091.64 | F19: -28175.89 | G19: -25826.93 | H19: -651 | I19: -17280.98 | J19: 0 | K19: 0
A20: 19 | B20: . REPARACIONS I CONSERVACIO | C20: =SUM(D20:J20) -> -56019.12 | D20: -34594.74 | E20: -16432.73 | F20: -412.78 | G20: -669.71 | H20: -3301.79 | I20: -567.37 | J20: -40 | K20: 0
A21: 20 | B21: . SERVEIS PROFESSIONALS | C21: =SUM(D21:J21)-2030 -> -112074.46 | D21: -5922.29 | E21: -6583.63 | F21: -77747.98 | G21: -18171.29 | H21: 0 | I21: -1619.27 | J21: 0 | K21: 0
A22: 21 | B22: . TRANSPORTS | C22: =SUM(D22:J22) -> -14353.35 | D22: -14219.09 | E22: 0 | F22: -134.26 | G22: 0 | H22: 0 | I22: 0 | J22: 0 | K22: 0
A23: 22 | B23: . PRIMES D'ASSEGURANCES | C23: =SUM(D23:J23) -> -4797.19 | D23: -3380.02 | E23: -1417.17 | F23: 0 | G23: 0 | H23: 0 | I23: 0 | J23: 0 | K23: 0
A24: 23 | B24: . SERVEIS BANCARIS | C24: =SUM(D24:J24) -> -4335.28 | D24: -975.2 | E24: -2927.84 | F24: -202.08 | G24: -220.92 | H24: 0 | I24: -9.24 | J24: 0 | K24: 0
A25: 24 | B25: . PUBLICITAT I PROPAGANDA | C25: =SUM(D25:J25)-100 -> -9923.33 | D25: -5903.6 | E25: -810.74 | F25: -186.99 | G25: -2809.07 | H25: 0 | I25: -112.93 | J25: 0 | K25: 0
A26: 25 | B26: . SUBMINISTRAMENTS | C26: =SUM(D26:J26) -> -40702.98 | D26: -15151.22 | E26: -18492.4 | F26: 0 | G26: 0 | H26: -6679.36 | I26: -380 | J26: 0 | K26: 0
A27: 26 | B27: . ALTRES DESPESES | C27: =SUM(D27:J27)-14735.55 -> -169492.57 | D27: -42611.02 | E27: -8652.39 | F27: -66576.72 | G27: -13107.19 | H27: -1690 | I27: -208 | J27: -21911.7 | K27: 0
A28: 27 | B28: . ALTRES TRIBUTS | C28: =SUM(D28:J28)-433.15 -> -4353.18 | D28: -1028.66 | E28: -2891.37 | F28: 0 | G28: 0 | H28: 0 | I28: 0 | J28: 0 | K28: 0
A29: 28 | B29: . DOTACIO PER INSOLVENCIA | C29: =SUM(D29:J29) -> 0 | D29: 0 | E29: 0 | F29: 0 | G29: 0 | H29: 0 | I29: 0 | J29: 0 | K29: 0
A30: 29 | B30: MOVIMENTS INTERNS | C30: =SUM(D30:J30) -> 0 | D30: 0 | E30: 0 | F30: 0 | G30: 0 | H30: 0 | I30: 0 | J30: 0 | K30: 0
A31: 30 | B31: TOTAL DESPESES GESTIO | C31: =SUM(C19:C30) -> -539921.61 | D31: =SUM(D19:D30) -> -131629.55 | E31: =SUM(E19:E30) -> -102299.91 | F31: =SUM(F19:F30) -> -173436.7 | G31: =SUM(G19:G30) -> -60805.11 | H31: =SUM(H19:H30) -> -12322.15 | I31: =SUM(I19:I30) -> -20177.79 | J31: =SUM(J19:J30) -> -21951.7 | K31: 0
A32: 31 | B32: TOTAL GESTIO + SALARIS | C32: -1664546.3 | D32: -777859.38 | E32: -434787.33 | F32: -206102.97 | G32: -84890.55 | H32: -92372.04 | I32: -34475.5 | J32: -34058.55 | K32: 0
A33: 32 | B33: EBITDA | C33: =C7+(C12+C18+C31) -> 866560.56 | D33: -1467791 | E33: 72124.56 | F33: 1065535.5 | G33: 545222.06 | H33: 456901.3 | I33: 135307.13 | J33: 52049.6 | K33: 0
A34: 33 | B34: . INGRESSOS FINANCERS | C34: 1365.43 | D34: 1365.43 | E34: 0 | F34: 0 | G34: 0 | H34: 0 | I34: 0 | J34: 0 | K34: 0
A35: 34 | B35: . DESPESSES FINANCERES | C35: -10097.12 | D35: -10097.12 | E35: 0 | F35: 0 | G35: 0 | H35: 0 | I35: 0 | J35: 0 | K35: 0
A36: 35 | B36: RESULTAT FINANCER | C36: -8731.69 | D36: -8731.69 | E36: 0 | F36: 0 | G36: 0 | H36: 0 | I36: 0 | J36: 0 | K36: 0
A37: 36 | B37: . INGRESOS EXCEPCIONALS | C37: 3544.18 | D37: 16.68 | E37: 969.6 | F37: 0 | G37: 0 | H37: 0 | I37: 112.98 | J37: 2444.92 | K37: 0
A38: 37 | B38: . DESPESSES EXCEPCIONALS | C38: -123.64 | D38: -123.64 | E38: 0 | F38: 0 | G38: 0 | H38: 0 | I38: 0 | J38: 0 | K38: 0
A39: 38 | B39: RESULTAT EXCEPCIONAL | C39: 3420.54 | D39: -106.96 | E39: 969.6 | F39: 0 | G39: 0 | H39: 0 | I39: 112.98 | J39: 2444.92 | K39: 0
A40: 39 | B40: . AMORTITZACIONS | C40: -71644.16 | D40: -53371.4 | E40: -10975.33 | F40: -6069.09 | G40: -194.57 | H40: -68.2 | I40: -965.57 | J40: 0 | K40: 0
A41: 40 | B41: RESULTAT ABANS D'IMPOSTOS | C41: 782393.81 | D41: -1530001.1 | E41: 62118.83 | F41: 1059466.4 | G41: 545027.49 | H41: 456833.1 | I41: 134454.54 | J41: 54494.52 | K41: 0
A42: 41 | B42: . IMPOST SOBRE BENEFICIS | C42: 0 | D42: 0 | E42: 0 | F42: 0 | G42: 0 | H42: 0 | I42: 0 | J42: 0 | K42: 0
A43: 42 | B43: RESULTAT DESPRES D'IMPOSTOS | C43: 782393.81 | D43: -1530001.1 | E43: 62118.83 | F43: 1059466.4 | G43: 545027.49 | H43: 456833.1 | I43: 134454.54 | J43: 54494.52 | K43: 0
A44: 43 | B44: RESULTAT ACUMULAT | C44: 0 | D44: 0 | E44: 0 | F44: 0 | G44: 0 | H44: 0 | I44: 0 | J44: 0 | K44: 0

Sheet ANUAL
A1: Node | B1: Description | C1: TOTAL | D1: LN00000 | E1: LN00001 | F1: LN00002 | G1: LN00003 | H1: LN00004 | I1: LN00005 | J1: LN00006 | K1: Sin LN
A2: 1 | B2: COMPTE DE RESULTATS | C2: 0 | D2: 0 | E2: 0 | F2: 0 | G2: 0 | H2: 0 | I2: 0 | J2: 0 | K2: 0
A3: 2 | B3: . VENDES | C3: 10545729 | D3: 101524.54 | E3: 2630675.6 | F3: 3310468 | G3: 964064.82 | H3: 2729003.5 | I3: 396668.69 | J3: 413324.39 | K3: 0
A4: 3 | B4: . PRESTACIO DE SEVEIS | C4: 0 | D4: 0 | E4: 0 | F4: 0 | G4: 0 | H4: 0 | I4: 0 | J4: 0 | K4: 0
A5: 4 | B5: . ALTRES INGRESSOS | C5: 43480.8 | D5: 15021.05 | E5: 23089.75 | F5: 0 | G5: 5370 | H5: 0 | I5: 0 | J5: 0 | K5: 0
A6: 5 | B6: . VARIACIO EXISTENCIES | C6: 0 | D6: 0 | E6: 0 | F6: 0 | G6: 0 | H6: 0 | I6: 0 | J6: 0 | K6: 0
A7: 6 | B7: TOTAL INGRESSOS EXPLOTACIO | C7: 10589210 | D7: 116545.59 | E7: 2653765.3 | F7: 3310468 | G7: 969434.82 | H7: 2729003.5 | I7: 396668.69 | J7: 413324.39 | K7: 0
A8: 7 | B8: . COMPRES | C8: -2929405.4 | D8: -2331379.4 | E8: -561019.93 | F8: -815.04 | G8: -1507.78 | H8: 0 | I8: -31249.79 | J8: -3433.41 | K8: 0
A9: 8 | B9: . ALTRES APROVISIONAMENTS | C9: -526970.38 | D9: -473977.95 | E9: -40605.52 | F9: -5281.28 | G9: -2728.21 | H9: 0 | I9: -3261.83 | J9: -1115.59 | K9: 0
A10: 9 | B10: . CONSUMS INTERNS | C10: 0 | D10: 0 | E10: 0 | F10: 0 | G10: 0 | H10: 0 | I10: 0 | J10: 0 | K10: 0
A11: 10 | B11: . VARIACIO EXISTENICIES COMPRES | C11: 0 | D11: 0 | E11: 0 | F11: 0 | G11: 0 | H11: 0 | I11: 0 | J11: 0 | K11: 0
A12: 11 | B12: TOTAL COMPRES | C12: -3456375.8 | D12: -2805357.4 | E12: -601625.45 | F12: -6096.32 | G12: -4235.99 | H12: 0 | I12: -34511.62 | J12: -4549 | K12: 0
A13: 12 | B13: MARGE BRUT TOTAL | C13: 7132834.5 | D13: -2688811.8 | E13: 2052139.9 | F13: 3304371.7 | G13: 965198.83 | H13: 2729003.5 | I13: 362157.07 | J13: 408775.39 | K13: 0
... A45: 999 | B45: . No definido !!! | C45: -4658.75 | D45: -4658.75 | E45: 0 | F45: 0 | G45: 0 | H45: 0 | I45: 0 | J45: 0 | K45: 0

Sheet REAL mes
B1: COMPTE DE RESULTATS | C1: Gener | D1: Febrer | E1: Març | F1: Abril | G1: Maig
C2: 0 | D2: 0 | E2: 0 | F2: 0 | G2: 0
B3: . VENDES | C3: 1304611.2 | D3: 1666686.2 | E3: 2101111.4 | F3: 2089711.6 | G3: 3383609.1
B4: . PRESTACIO DE SEVEIS | C4: 0 | D4: 0 | E4: 0 | F4: 0 | G4: 0
B5: . ALTRES INGRESSOS | C5: 7622.16 | D5: 7622.16 | E5: 7622.16 | F5: 9122.16 | G5: 11492.16
B6: . VARIACIO EXISTENCIES | C6: 0 | D6: 0 | E6: 0 | F6: 0 | G6: 0
B7: TOTAL INGRESSOS EXPLOTACIO | C7: 1312233.4 | D7: 1674308.4 | E7: 2108733.5 | F7: 2098833.7 | G7: 3395101.2
B8: . COMPRES | C8: -416007.42 | D8: -558253.64 | E8: -635013.24 | F8: -563425.75 | G8: -756705.33
B9: . ALTRES APROVISIONAMENTS | C9: -95382.05 | D9: -70842.09 | E9: -120139.9 | F9: -126105.89 | G9: -114500.45
B10: . CONSUMS INTERNS | C10: 0 | D10: 0 | E10: 0 | F10: 0 | G10: 0
B11: . VARIACIO EXISTENICIES COMPRES | C11: 0 | D11: 0 | E11: 0 | F11: 0 | G11: 0
B12: TOTAL COMPRES | C12: -511389.47 | D12: -629095.73 | E12: -755153.14 | F12: -689531.64 | G12: -871205.78
B13: MARGE BRUT TOTAL | C13: 800843.88 | D13: 1045212.7 | E13: 1353580.4 | F13: 1409302.1 | G13: 2523895.4
B14: . SOUS I SALARIS | C14: -744640.26 | D14: -733187.02 | E14: -783828.69 | F14: -798547.98 | G14: -874156.58
... B33: EBITDA | C33: -411984.61 | D33: -228341.13 | E33: -85465.8 | F33: -115212.05 | G33: 859349.12
B34: EBITDA ACUMULAT | C34: =C33 -> -411984.61 | D34: =C34+D33 -> -640325.74 | E34: =D34+E33 -> -725791.54 | F34: =E34+F33 -> -841003.59 | G34: =F34+G33 -> 18345.53
B35: . INGRESSOS FINANCERS | C35: 1311.3 | D35: 4565.62 | E35: 1290.7 | F35: 1280.33 | G35: 1365.43
B36: . DESPESSES FINANCERES | C36: -9204.31 | D36: -66031.03 | E36: -9316.21 | F36: -9875.84 | G36: -10097.12
B37: RESULTAT FINANCER | C37: -7893.01 | D37: -61465.41 | E37: -8025.51 | F37: -8595.51 | G37: -8731.69
B38: . INGRESOS EXCEPCIONALS | C38: 2327.63 | D38: 6659.98 | E38: 10118.58 | F38: 99570.71 | G38: 3544.18
B39: . DESPESSES EXCEPCIONALS | C39: -100.07 | D39: -185465.38 | E39: -3181.19 | F39: -983.9 | G39: -123.64
B40: RESULTAT EXCEPCIONAL | C40: 2227.56 | D40: -178805.4 | E40: 6937.39 | F40: 98586.81 | G40: 3420.54
B41: . AMORTITZACIONS | C41: -67141.91 | D41: -60586.62 | E41: -68192.01 | F41: -69266.01 | G41: -71644.16
B42: RESULTAT ABANS D'IMPOSTOS | C42: -484791.97 | D42: -529198.56 | E42: -154745.93 | F42: -94486.76 | G42: 782393.81
B43: . IMPOST SOBRE BENEFICIS | C43: 0 | D43: 0 | E43: 0 | F43: 0 | G43: 0
B44: RESULTAT DESPRES D'IMPOSTOS | C44: -484791.97 | D44: -529198.56 | E44: -154745.93 | F44: -94486.76 | G44: 782393.81
B45: RESULTAT ACUMULAT | C45: =C44 -> -484791.97 | D45: =C45+D44 -> -1013990.5 | E45: =D45+E44 -> -1168736.5 | F45: =E45+F44 -> -1263223.2 | G45: =F45+G44 -> -480829.41

Sheet C.Explotacio Rsum
A3: TOTAL INGRESSOS
B4: ene | C4: feb | D4: mar | E4: abr | F4: may | G4: jun | H4: jul | I4: ago | J4: sep | K4: oct | L4: nov | M4: dic | N4: Total general
A7: Casaments | B7: 19110.49 | C7: 33824.11 | D7: 85941.41 | E7: 198620.54 | F7: 631938.27 | N7: 969434.82
A8: Empresa | B8: 289300.57 | C8: 522944.53 | D8: 693442.52 | E8: 532165.29 | F8: 1373718.1 | N8: 3411571
A9: FoodLovers | B9: 954 | C9: 41743.47 | D9: 60009.55 | E9: 123646.15 | F9: 170315.52 | N9: 396668.69
A10: Green Vita | B10: 43471.95 | C10: 99398.31 | D10: 111070.19 | E10: 71050.74 | F10: 88333.2 | N10: 413324.39
A11: Precuinats | B11: 542068.83 | C11: 494245.22 | D11: 535792.81 | E11: 564028.64 | F11: 538287.87 | N11: 2674423.4
A12: Restaurants | B12: 391662.49 | C12: 455968.83 | D12: 585819 | E12: 575602.52 | F12: 644712.49 | N12: 2653765.3
A13: Total general | B13: 1286568.3 | C13: 1648124.5 | D13: 2072075.5 | E13: 2065113.9 | F13: 3447305.4 | N13: 10519188
A16: TOTAL COST SALARIAL
B17: ene | C17: feb | D17: mar | E17: abr | F17: may | G17: jun | H17: jul | I17: ago | J17: sep | K17: oct | L17: nov | M17: dic | N17: Total general
A20: Casaments | B20: -95345.024 | C20: -95338.332 | D20: -102878.15 | E20: -109333.29 | F20: -98180.599 | N20: -501075.39
A21: Empresa | B21: -257884.99 | C21: -251854.16 | D21: -276572.97 | E21: -292045.78 | F21: -254133.09 | N21: -1332491
A22: FoodLovers | B22: -54665.142 | C22: -56926.123 | D22: -61874.628 | E22: -68427.614 | F22: -58432.195 | N22: -300325.7
A23: Green Vita | B23: -5216.634 | C23: -11927.797 | D23: -13328.423 | E23: -8526.0888 | F23: -22706.834 | N23: -61705.777
A24: Precuinats | B24: -218967.77 | C24: -222120.71 | D24: -272769.36 | E24: -255237.31 | F24: -220142.77 | N24: -1189237.9
A25: Restaurants | B25: -330298.94 | C25: -336169.62 | D25: -328499.1 | E25: -342214.36 | F25: -329435.85 | N25: -1666617.9
A26: Total general | B26: -962378.5 | C26: -974336.74 | D26: -1055922.6 | E26: -1075784.4 | F26: -983031.33 | N26: -5051453.6
A29: TOTAL COMPRA
B30: ene | C30: feb | D30: mar | E30: abr | F30: may | G30: jun | H30: jul | I30: ago | J30: sep | K30: oct | L30: nov | M30: dic | N30: Total general
A33: Casaments | B33: -42165.903 | C33: -66210.236 | D33: -88198.41 | E33: -68452.175 | F33: -114628.36 | N33: -379655.08
A34: Empresa | B34: -117198.31 | C34: -184843.45 | D34: -244031.05 | E34: -189805.56 | F34: -314862.38 | N34: -1050740.8
A35: FoodLovers | B35: -32447.052 | C35: -43889.412 | D35: -51948.888 | E35: -54128.732 | F35: -64290.938 | N35: -246705.02
A36: Green Vita | B36: -10867.987 | C36: -24849.577 | D36: -27767.548 | E36: -20086.635 | F36: -24308.35 | N36: -107880.1
A37: Precuinats | B37: -216827.53 | C37: -197698.09 | D37: -214317.13 | E37: -225611.46 | F37: -215315.15 | N37: -1069769.4
A38: Restaurants | B38: -120748.21 | C38: -145209.87 | D38: -182349.72 | E38: -199531.53 | F38: -211945.31 | N38: -859784.64
A39: Total general | B39: -540255 | C39: -662700.63 | D39: -808612.74 | E39: -757616.09 | F39: -945350.49 | N39: -3714534.9
A42: TOTAL DESPESES
B43: ene | C43: feb | D43: mar | E43: abr | F43: may | G43: jun | H43: jul | I43: ago | J43: sep | K43: oct | L43: nov | M43: dic | N43: Total general
A46: Casaments | B46: -39894.717 | C46: -40214.403 | D46: -48865.855 | E46: -61316.992 | F46: -79233.247 | N46: -269525.21
A47: Empresa | B47: -66031.821 | C47: -95753.586 | D47: -145195.97 | E47: -157750.76 | F47: -231232.4 | N47: -695964.54
A48: FoodLovers | B48: -18610.988 | C48: -21551.345 | D48: -25053.514 | E48: -56358.948 | F48: -30708.154 | N48: -152282.95
A49: Green Vita | B49: -10146.449 | C49: -24001.292 | D49: -21560.707 | E49: -13635.659 | F49: -27216.882 | N49: -96560.99
A50: Precuinats | B50: -35673.464 | C50: -33344.763 | D50: -41166.504 | E50: -50269.589 | F50: -51160.015 | N50: -211614.34
A51: Restaurants | B51: -80092.55 | C51: -84351.68 | D51: -101281.03 | E51: -109397.74 | F51: -102299.91 | N51: -477422.91
A52: Total general | B52: -250449.99 | C52: -299217.07 | D52: -383123.58 | E52: -448729.69 | F52: -521850.61 | N52: -1903370.9

Sheet Resum
B2: Linia Negoci | C2: Data | D2: TOTAL INGRESSOS | E2: TOTAL COMPRES | F2: TOTAL COST SALARIAL | G2: TOTAL DESPESES GESTIO | H2: EBITDA
B3: Restaurants | C3: =DATE(2025,1+INT((ROW(A1)-1)/6),1) -> 45658 | D3: {=INDEX(INDIRECT("'"&$B3&"_05'!$B$6:$M$6"),1,MONTH($C3))} -> 0 | E3: {=INDEX(INDIRECT("'"&$B3&"_05'!$B$11:$M$11"),1,MONTH($C3))} -> -38863.39 | F3: {=INDEX(INDIRECT("'"&$B3&"_05'!$B$17:$M$17"),1,MONTH($C3))} -> -2000 | G3: {=INDEX(INDIRECT("'"&$B3&"_05'!$B$30:$M$30"),1,MONTH($C3))} -> -8766.98 | H3: {=INDEX(INDIRECT("'"&$B3&"_05'!$B$32:$M$32"),1,MONTH($C3))} -> 0
B4: Empresa | C4: =DATE(2025,1+INT((ROW(A2)-1)/6),1) -> 45658 | D4: {=INDEX(INDIRECT("'"&$B4&"_05'!$B$6:$M$6"),1,MONTH($C4))} -> 289300.57 | E4: {=INDEX(INDIRECT("'"&$B4&"_05'!$B$14:$M$14"),1,MONTH($C4))} -> -145114.37 | F4: {=INDEX(INDIRECT("'"&$B4&"_05'!$B$24:$M$24"),1,MONTH($C4))} -> -22116.05 | G4: {=INDEX(INDIRECT("'"&$B4&"_05'!$B$38:$M$38"),1,MONTH($C4))} -> -96 | H4: {=INDEX(INDIRECT("'"&$B4&"_05'!$B$40:$M$40"),1,MONTH($C4))} -> -5629.55
B5: Casaments | C5: =DATE(2025,1+INT((ROW(A3)-1)/6),1) -> 45658 | D5: {=INDEX(INDIRECT("'"&$B5&"_05'!$B$6:$M$6"),1,MONTH($C5))} -> 0 | E5: {=INDEX(INDIRECT("'"&$B5&"_05'!$B$14:$M$14"),1,MONTH($C5))} -> -145114.37 | F5: {=INDEX(INDIRECT("'"&$B5&"_05'!$B$24:$M$24"),1,MONTH($C5))} -> -7190.3585 | G5: {=INDEX(INDIRECT("'"&$B5&"_05'!$B$38:$M$38"),1,MONTH($C5))} -> 0 | H5: {=INDEX(INDIRECT("'"&$B5&"_05'!$B$40:$M$40"),1,MONTH($C5))} -> 0
B6: Precuinats | C6: =DATE(2025,1+INT((ROW(A4)-1)/6),1) -> 45658 | D6: {=INDEX(INDIRECT("'"&$B6&"_05'!$B$6:$M$6"),1,MONTH($C6))} -> 542068.83 | E6: {=INDEX(INDIRECT("'"&$B6&"_05'!$B$11:$M$11"),1,MONTH($C6))} -> -248909.16 | F6: {=INDEX(INDIRECT("'"&$B6&"_05'!$B$21:$M$21"),1,MONTH($C6))} -> -10903.14 | G6: {=INDEX(INDIRECT("'"&$B6&"_05'!$B$35:$M$35"),1,MONTH($C6))} -> 0 | H6: {=INDEX(INDIRECT("'"&$B6&"_05'!$B$37:$M$37"),1,MONTH($C6))} -> -35673.464
B7: FoodLovers | C7: =DATE(2025,1+INT((ROW(A5)-1)/6),1) -> 45658 | D7: {=INDEX(INDIRECT("'"&$B7&"_05'!$B$6:$M$6"),1,MONTH($C7))} -> 954 | E7: {=INDEX(INDIRECT("'"&$B7&"_05'!$B$14:$M$14"),1,MONTH($C7))} -> -6809.58 | F7: {=INDEX(INDIRECT("'"&$B7&"_05'!$B$24:$M$24"),1,MONTH($C7))} -> -697.57 | G7: {=INDEX(INDIRECT("'"&$B7&"_05'!$B$38:$M$38"),1,MONTH($C7))} -> 0 | H7: {=INDEX(INDIRECT("'"&$B7&"_05'!$B$40:$M$40"),1,MONTH($C7))} -> 0
B8: Green Vita | C8: =DATE(2025,1+INT((ROW(A6)-1)/6),1) -> 45658 | D8: {=INDEX(INDIRECT("'"&$B8&"_05'!$B$6:$M$6"),1,MONTH($C8))} -> 43471.95 | E8: {=INDEX(INDIRECT("'"&$B8&"_05'!$B$11:$M$11"),1,MONTH($C8))} -> -10867.987 | F8: {=INDEX(INDIRECT("'"&$B8&"_05'!$B$17:$M$17"),1,MONTH($C8))} -> 0 | G8: {=INDEX(INDIRECT("'"&$B8&"_05'!$B$31:$M$31"),1,MONTH($C8))} -> 0 | H8: {=INDEX(INDIRECT("'"&$B8&"_05'!$B$33:$M$33"),1,MONTH($C8))} -> 0
B9: Restaurants | C9: =DATE(2025,1+INT((ROW(A7)-1)/6),1) -> 45689 | D9: {=INDEX(INDIRECT("'"&$B9&"_05'!$B$6:$M$6"),1,MONTH($C9))} -> 0 | E9: {=INDEX(INDIRECT("'"&$B9&"_05'!$B$11:$M$11"),1,MONTH($C9))} -> -37571.38 | F9: {=INDEX(INDIRECT("'"&$B9&"_05'!$B$17:$M$17"),1,MONTH($C9))} -> -21000 | G9: {=INDEX(INDIRECT("'"&$B9&"_05'!$B$30:$M$30"),1,MONTH($C9))} -> -16450.01 | H9: {=INDEX(INDIRECT("'"&$B9&"_05'!$B$32:$M$32"),1,MONTH($C9))} -> 0
B10: Empresa | C10: =DATE(2025,1+INT((ROW(A8)-1)/6),1) -> 45689 | D10: {=INDEX(INDIRECT("'"&$B10&"_05'!$B$6:$M$6"),1,MONTH($C10))} -> 522944.53 | E10: {=INDEX(INDIRECT("'"&$B10&"_05'!$B$14:$M$14"),1,MONTH($C10))} -> -242599.5 | F10: {=INDEX(INDIRECT("'"&$B10&"_05'!$B$24:$M$24"),1,MONTH($C10))} -> -18130.26 | G10: {=INDEX(INDIRECT("'"&$B10&"_05'!$B$38:$M$38"),1,MONTH($C10))} -> 0 | H10: {=INDEX(INDIRECT("'"&$B10&"_05'!$B$40:$M$40"),1,MONTH($C10))} -> -1265.91
B11: Casaments | C11: =DATE(2025,1+INT((ROW(A9)-1)/6),1) -> 45689 | D11: {=INDEX(INDIRECT("'"&$B11&"_05'!$B$6:$M$6"),1,MONTH($C11))} -> 0 | E11: {=INDEX(INDIRECT("'"&$B11&"_05'!$B$14:$M$14"),1,MONTH($C11))} -> -242599.5 | F11: {=INDEX(INDIRECT("'"&$B11&"_05'!$B$24:$M$24"),1,MONTH($C11))} -> -7414.595 | G11: {=INDEX(INDIRECT("'"&$B11&"_05'!$B$38:$M$38"),1,MONTH($C11))} -> -2286.08 | H11: {=INDEX(INDIRECT("'"&$B11&"_05'!$B$40:$M$40"),1,MONTH($C11))} -> -1.2
B12: Precuinats | C12: =DATE(2025,1+INT((ROW(A10)-1)/6),1) -> 45689 | D12: {=INDEX(INDIRECT("'"&$B12&"_05'!$B$6:$M$6"),1,MONTH($C12))} -> 494245.22 | E12: {=INDEX(INDIRECT("'"&$B12&"_05'!$B$11:$M$11"),1,MONTH($C12))} -> -226949.34 | F12: {=INDEX(INDIRECT("'"&$B12&"_05'!$B$21:$M$21"),1,MONTH($C12))} -> -13495.5 | G12: {=INDEX(INDIRECT("'"&$B12&"_05'!$B$35:$M$35"),1,MONTH($C12))} -> 0 | H12: {=INDEX(INDIRECT("'"&$B12&"_05'!$B$37:$M$37"),1,MONTH($C12))} -> -33344.763
B13: FoodLovers | C13: =DATE(2025,1+INT((ROW(A11)-1)/6),1) -> 45689 | D13: {=INDEX(INDIRECT("'"&$B13&"_05'!$B$6:$M$6"),1,MONTH($C13))} -> 41743.47 | E13: {=INDEX(INDIRECT("'"&$B13&"_05'!$B$14:$M$14"),1,MONTH($C13))} -> -8658.47 | F13: {=INDEX(INDIRECT("'"&$B13&"_05'!$B$24:$M$24"),1,MONTH($C13))} -> -594.98 | G13: {=INDEX(INDIRECT("'"&$B13&"_05'!$B$38:$M$38"),1,MONTH($C13))} -> 0 | H13: {=INDEX(INDIRECT("'"&$B13&"_05'!$B$40:$M$40"),1,MONTH($C13))} -> 0
B14: Green Vita | C14: =DATE(2025,1+INT((ROW(A12)-1)/6),1) -> 45689 | D14: {=INDEX(INDIRECT("'"&$B14&"_05'!$B$6:$M$6"),1,MONTH($C14))} -> 99398.31 | E14: {=INDEX(INDIRECT("'"&$B14&"_05'!$B$11:$M$11"),1,MONTH($C14))} -> -24849.577 | F14: {=INDEX(INDIRECT("'"&$B14&"_05'!$B$17:$M$17"),1,MONTH($C14))} -> 0 | G14: {=INDEX(INDIRECT("'"&$B14&"_05'!$B$31:$M$31"),1,MONTH($C14))} -> 0 | H14: {=INDEX(INDIRECT("'"&$B14&"_05'!$B$33:$M$33"),1,MONTH($C14))} -> 0
B15: Restaurants | C15: =DATE(2025,1+INT((ROW(A13)-1)/6),1) -> 45717 | D15: {=INDEX(INDIRECT("'"&$B15&"_05'!$B$6:$M$6"),1,MONTH($C15))} -> 0 | E15: {=INDEX(INDIRECT("'"&$B15&"_05'!$B$11:$M$11"),1,MONTH($C15))} -> -53459.6 | F15: {=INDEX(INDIRECT("'"&$B15&"_05'!$B$17:$M$17"),1,MONTH($C15))} -> 0 | G15: {=INDEX(INDIRECT("'"&$B15&"_05'!$B$30:$M$30"),1,MONTH($C15))} -> -18198.81 | H15: {=INDEX(INDIRECT("'"&$B15&"_05'!$B$32:$M$32"),1,MONTH($C15))} -> 0
B16: Empresa | C16: =DATE(2025,1+INT((ROW(A14)-1)/6),1) -> 45717 | D16: {=INDEX(INDIRECT("'"&$B16&"_05'!$B$6:$M$6"),1,MONTH($C16))} -> 693442.52 | E16: {=INDEX(INDIRECT("'"&$B16&"_05'!$B$14:$M$14"),1,MONTH($C16))} -> -325482.09 | F16: {=INDEX(INDIRECT("'"&$B16&"_05'!$B$24:$M$24"),1,MONTH($C16))} -> -22980.88 | G16: {=INDEX(INDIRECT("'"&$B16&"_05'!$B$38:$M$38"),1,MONTH($C16))} -> 0 | H16: {=INDEX(INDIRECT("'"&$B16&"_05'!$B$40:$M$40"),1,MONTH($C16))} -> -3506.86
B17: Casaments | C17: =DATE(2025,1+INT((ROW(A15)-1)/6),1) -> 45717 | D17: {=INDEX(INDIRECT("'"&$B17&"_05'!$B$6:$M$6"),1,MONTH($C17))} -> 0 | E17: {=INDEX(INDIRECT("'"&$B17&"_05'!$B$14:$M$14"),1,MONTH($C17))} -> -325482.09 | F17: {=INDEX(INDIRECT("'"&$B17&"_05'!$B$24:$M$24"),1,MONTH($C17))} -> -8858.528 | G17: {=INDEX(INDIRECT("'"&$B17&"_05'!$B$38:$M$38"),1,MONTH($C17))} -> -2322.8 | H17: {=INDEX(INDIRECT("'"&$B17&"_05'!$B$40:$M$40"),1,MONTH($C17))} -> 0
B18: Precuinats | C18: =DATE(2025,1+INT((ROW(A16)-1)/6),1) -> 45717 | D18: {=INDEX(INDIRECT("'"&$B18&"_05'!$B$6:$M$6"),1,MONTH($C18))} -> 535792.81 | E18: {=INDEX(INDIRECT("'"&$B18&"_05'!$B$11:$M$11"),1,MONTH($C18))} -> -246027.31 | F18: {=INDEX(INDIRECT("'"&$B18&"_05'!$B$21:$M$21"),1,MONTH($C18))} -> -16003.53 | G18: {=INDEX(INDIRECT("'"&$B18&"_05'!$B$35:$M$35"),1,MONTH($C18))} -> 0 | H18: {=INDEX(INDIRECT("'"&$B18&"_05'!$B$37:$M$37"),1,MONTH($C18))} -> -41166.504
B19: FoodLovers | C19: =DATE(2025,1+INT((ROW(A17)-1)/6),1) -> 45717 | D19: {=INDEX(INDIRECT("'"&$B19&"_05'!$B$6:$M$6"),1,MONTH($C19))} -> 60009.55 | E19: {=INDEX(INDIRECT("'"&$B19&"_05'!$B$14:$M$14"),1,MONTH($C19))} -> -9486.11 | F19: {=INDEX(INDIRECT("'"&$B19&"_05'!$B$24:$M$24"),1,MONTH($C19))} -> -593.01 | G19: {=INDEX(INDIRECT("'"&$B19&"_05'!$B$38:$M$38"),1,MONTH($C19))} -> 0 | H19: {=INDEX(INDIRECT("'"&$B19&"_05'!$B$40:$M$40"),1,MONTH($C19))} -> 0
B20: Green Vita | C20: =DATE(2025,1+INT((ROW(A18)-1)/6),1) -> 45717 | D20: {=INDEX(INDIRECT("'"&$B20&"_05'!$B$6:$M$6"),1,MONTH($C20))} -> 111070.19 | E20: {=INDEX(INDIRECT("'"&$B20&"_05'!$B$11:$M$11"),1,MONTH($C20))} -> -27767.548 | F20: {=INDEX(INDIRECT("'"&$B20&"_05'!$B$17:$M$17"),1,MONTH($C20))} -> 0 | G20: {=INDEX(INDIRECT("'"&$B20&"_05'!$B$31:$M$31"),1,MONTH($C20))} -> -2588.09 | H20: {=INDEX(INDIRECT("'"&$B20&"_05'!$B$33:$M$33"),1,MONTH($C20))} -> 0
B21: Restaurants | C21: =DATE(2025,1+INT((ROW(A19)-1)/6),1) -> 45748 | D21: {=INDEX(INDIRECT("'"&$B21&"_05'!$B$6:$M$6"),1,MONTH($C21))} -> 0 | E21: {=INDEX(INDIRECT("'"&$B21&"_05'!$B$11:$M$11"),1,MONTH($C21))} -> -68084.45 | F21: {=INDEX(INDIRECT("'"&$B21&"_05'!$B$17:$M$17"),1,MONTH($C21))} -> 0 | G21: {=INDEX(INDIRECT("'"&$B21&"_05'!$B$30:$M$30"),1,MONTH($C21))} -> -12204.85 | H21: {=INDEX(INDIRECT("'"&$B21&"_05'!$B$32:$M$32"),1,MONTH($C21))} -> 0
B22: Empresa | C22: =DATE(2025,1+INT((ROW(A20)-1)/6),1) -> 45748 | D22: {=INDEX(INDIRECT("'"&$B22&"_05'!$B$6:$M$6"),1,MONTH($C22))} -> 532165.29 | E22: {=INDEX(INDIRECT("'"&$B22&"_05'!$B$14:$M$14"),1,MONTH($C22))} -> -219237.16 | F22: {=INDEX(INDIRECT("'"&$B22&"_05'!$B$24:$M$24"),1,MONTH($C22))} -> -23486.13 | G22: {=INDEX(INDIRECT("'"&$B22&"_05'!$B$38:$M$38"),1,MONTH($C22))} -> 0 | H22: {=INDEX(INDIRECT("'"&$B22&"_05'!$B$40:$M$40"),1,MONTH($C22))} -> -5083.88
B23: Casaments | C23: =DATE(2025,1+INT((ROW(A21)-1)/6),1) -> 45748 | D23: {=INDEX(INDIRECT("'"&$B23&"_05'!$B$6:$M$6"),1,MONTH($C23))} -> 0 | E23: {=INDEX(INDIRECT("'"&$B23&"_05'!$B$14:$M$14"),1,MONTH($C23))} -> -219237.16 | F23: {=INDEX(INDIRECT("'"&$B23&"_05'!$B$24:$M$24"),1,MONTH($C23))} -> -8331.3575 | G23: {=INDEX(INDIRECT("'"&$B23&"_05'!$B$38:$M$38"),1,MONTH($C23))} -> -8013.02 | H23: {=INDEX(INDIRECT("'"&$B23&"_05'!$B$40:$M$40"),1,MONTH($C23))} -> 0
B24: Precuinats | C24: =DATE(2025,1+INT((ROW(A22)-1)/6),1) -> 45748 | D24: {=INDEX(INDIRECT("'"&$B24&"_05'!$B$6:$M$6"),1,MONTH($C24))} -> 564028.64 | E24: {=INDEX(INDIRECT("'"&$B24&"_05'!$B$11:$M$11"),1,MONTH($C24))} -> -258992.74 | F24: {=INDEX(INDIRECT("'"&$B24&"_05'!$B$21:$M$21"),1,MONTH($C24))} -> -16541.71 | G24: {=INDEX(INDIRECT("'"&$B24&"_05'!$B$35:$M$35"),1,MONTH($C24))} -> 0 | H24: {=INDEX(INDIRECT("'"&$B24&"_05'!$B$37:$M$37"),1,MONTH($C24))} -> -50269.589
B25: FoodLovers | C25: =DATE(2025,1+INT((ROW(A23)-1)/6),1) -> 45748 | D25: {=INDEX(INDIRECT("'"&$B25&"_05'!$B$6:$M$6"),1,MONTH($C25))} -> 123646.15 | E25: {=INDEX(INDIRECT("'"&$B25&"_05'!$B$14:$M$14"),1,MONTH($C25))} -> -12134.68 | F25: {=INDEX(INDIRECT("'"&$B25&"_05'!$B$24:$M$24"),1,MONTH($C25))} -> -1005.81 | G25: {=INDEX(INDIRECT("'"&$B25&"_05'!$B$38:$M$38"),1,MONTH($C25))} -> 0 | H25: {=INDEX(INDIRECT("'"&$B25&"_05'!$B$40:$M$40"),1,MONTH($C25))} -> 0
B26: Green Vita | C26: =DATE(2025,1+INT((ROW(A24)-1)/6),1) -> 45748 | D26: {=INDEX(INDIRECT("'"&$B26&"_05'!$B$6:$M$6"),1,MONTH($C26))} -> 71050.74 | E26: {=INDEX(INDIRECT("'"&$B26&"_05'!$B$11:$M$11"),1,MONTH($C26))} -> -20086.635 | F26: {=INDEX(INDIRECT("'"&$B26&"_05'!$B$17:$M$17"),1,MONTH($C26))} -> 0 | G26: {=INDEX(INDIRECT("'"&$B26&"_05'!$B$31:$M$31"),1,MONTH($C26))} -> -1974.45 | H26: {=INDEX(INDIRECT("'"&$B26&"_05'!$B$33:$M$33"),1,MONTH($C26))} -> 0
B27: Restaurants | C27: =DATE(2025,1+INT((ROW(A25)-1)/6),1) -> 45778 | D27: {=INDEX(INDIRECT("'"&$B27&"_05'!$B$6:$M$6"),1,MONTH($C27))} -> 0 | E27: {=INDEX(INDIRECT("'"&$B27&"_05'!$B$11:$M$11"),1,MONTH($C27))} -> -74144.71 | F27: {=INDEX(INDIRECT("'"&$B27&"_05'!$B$17:$M$17"),1,MONTH($C27))} -> -2200 | G27: {=INDEX(INDIRECT("'"&$B27&"_05'!$B$30:$M$30"),1,MONTH($C27))} -> -8652.39 | H27: {=INDEX(INDIRECT("'"&$B27&"_05'!$B$32:$M$32"),1,MONTH($C27))} -> 0
B28: Empresa | C28: =DATE(2025,1+INT((ROW(A26)-1)/6),1) -> 45778 | D28: {=INDEX(INDIRECT("'"&$B28&"_05'!$B$6:$M$6"),1,MONTH($C28))} -> 1272615.1 | E28: {=INDEX(INDIRECT("'"&$B28&"_05'!$B$14:$M$14"),1,MONTH($C28))} -> -401421.99 | F28: {=INDEX(INDIRECT("'"&$B28&"_05'!$B$24:$M$24"),1,MONTH($C28))} -> -24690.8 | G28: {=INDEX(INDIRECT("'"&$B28&"_05'!$B$38:$M$38"),1,MONTH($C28))} -> 0 | H28: {=INDEX(INDIRECT("'"&$B28&"_05'!$B$40:$M$40"),1,MONTH($C28))} -> -186.99
B29: Casaments | C29: =DATE(2025,1+INT((ROW(A27)-1)/6),1) -> 45778 | D29: {=INDEX(INDIRECT("'"&$B29&"_05'!$B$6:$M$6"),1,MONTH($C29))} -> 4050 | E29: {=INDEX(INDIRECT("'"&$B29&"_05'!$B$14:$M$14"),1,MONTH($C29))} -> -401421.99 | F29: {=INDEX(INDIRECT("'"&$B29&"_05'!$B$24:$M$24"),1,MONTH($C29))} -> -10686.999 | G29: {=INDEX(INDIRECT("'"&$B29&"_05'!$B$38:$M$38"),1,MONTH($C29))} -> -18171.29 | H29: {=INDEX(INDIRECT("'"&$B29&"_05'!$B$40:$M$40"),1,MONTH($C29))} -> 0
B30: Precuinats | C30: =DATE(2025,1+INT((ROW(A28)-1)/6),1) -> 45778 | D30: {=INDEX(INDIRECT("'"&$B30&"_05'!$B$6:$M$6"),1,MONTH($C30))} -> 538287.87 | E30: {=INDEX(INDIRECT("'"&$B30&"_05'!$B$11:$M$11"),1,MONTH($C30))} -> -247173 | F30: {=INDEX(INDIRECT("'"&$B30&"_05'!$B$21:$M$21"),1,MONTH($C30))} -> -17869.29 | G30: {=INDEX(INDIRECT("'"&$B30&"_05'!$B$35:$M$35"),1,MONTH($C30))} -> 0 | H30: {=INDEX(INDIRECT("'"&$B30&"_05'!$B$37:$M$37"),1,MONTH($C30))} -> -51160.015
B31: FoodLovers | C31: =DATE(2025,1+INT((ROW(A29)-1)/6),1) -> 45778 | D31: {=INDEX(INDIRECT("'"&$B31&"_05'!$B$6:$M$6"),1,MONTH($C31))} -> 170315.52 | E31: {=INDEX(INDIRECT("'"&$B31&"_05'!$B$14:$M$14"),1,MONTH($C31))} -> -10741.55 | F31: {=INDEX(INDIRECT("'"&$B31&"_05'!$B$24:$M$24"),1,MONTH($C31))} -> -567.37 | G31: {=INDEX(INDIRECT("'"&$B31&"_05'!$B$38:$M$38"),1,MONTH($C31))} -> 0 | H31: {=INDEX(INDIRECT("'"&$B31&"_05'!$B$40:$M$40"),1,MONTH($C31))} -> 0
B32: Green Vita | C32: =DATE(2025,1+INT((ROW(A30)-1)/6),1) -> 45778 | D32: {=INDEX(INDIRECT("'"&$B32&"_05'!$B$6:$M$6"),1,MONTH($C32))} -> 88333.2 | E32: {=INDEX(INDIRECT("'"&$B32&"_05'!$B$11:$M$11"),1,MONTH($C32))} -> -24308.35 | F32: {=INDEX(INDIRECT("'"&$B32&"_05'!$B$17:$M$17"),1,MONTH($C32))} -> -2815.37 | G32: {=INDEX(INDIRECT("'"&$B32&"_05'!$B$31:$M$31"),1,MONTH($C32))} -> -21911.7 | H32: {=INDEX(INDIRECT("'"&$B32&"_05'!$B$33:$M$33"),1,MONTH($C32))} -> 0
B33: Restaurants | C33: =DATE(2025,1+INT((ROW(A31)-1)/6),1) -> 45809
B34: Empresa | C34: =DATE(2025,1+INT((ROW(A32)-1)/6),1) -> 45809
B35: Casaments | C35: =DATE(2025,1+INT((ROW(A33)-1)/6),1) -> 45809
B36: Precuinats | C36: =DATE(2025,1+INT((ROW(A34)-1)/6),1) -> 45809
B37: FoodLovers | C37: =DATE(2025,1+INT((ROW(A35)-1)/6),1) -> 45809
B38: Green Vita | C38: =DATE(2025,1+INT((ROW(A36)-1)/6),1) -> 45809
B39: Restaurants | C39: =DATE(2025,1+INT((ROW(A37)-1)/6),1) -> 45839
B40: Empresa | C40: =DATE(2025,1+INT((ROW(A38)-1)/6),1) -> 45839
B41: Casaments | C41: =DATE(2025,1+INT((ROW(A39)-1)/6),1) -> 45839
B42: Precuinats | C42: =DATE(2025,1+INT((ROW(A40)-1)/6),1) -> 45839
B43: FoodLovers | C43: =DATE(2025,1+INT((ROW(A41)-1)/6),1) -> 45839
B44: Green Vita | C44: =DATE(2025,1+INT((ROW(A42)-1)/6),1) -> 45839
... B74: Green Vita | C74: =DATE(2025,1+INT((ROW(A72)-1)/6),1) -> 45992

Sheet TDatos
A3: Etiquetas de fila | B3: Suma de TOTAL INGRESSOS | D3: Etiquetas de fila | E3: Suma de Cost compres Positiu
A4: ene | B4: 289300.57 | D4: Empresa | E4: 1050740.8
A5: feb | B5: 522944.53 | D5: 45658 | E5: 117198.31
A6: mar | B6: 693442.52 | D6: 45689 | E6: 184843.45
A7: abr | B7: 532165.29 | D7: 45717 | E7: 244031.05
A8: may | B8: 1373718.1 | D8: 45748 | E8: 189805.56
A9: jun | D9: 45778 | E9: 314862.38
A10: Total general | B10: 3411571 | D10: 45809 | E10: 0
D11: Total general | E11: 1050740.8
B16: Suma de EBITDA | D16: Etiquetas de fila | E16: Suma de TOTAL DESPESES GESTIO
A17: Empresa | B17: 332374.7 | D17: ene | E17: -66031.821
A18: ene | B18: -151814.56 | D18: feb | E18: -95753.586
A19: feb | B19: -9506.6579 | D19: mar | E19: -145195.97
A20: mar | B20: 27642.532 | D20: abr | E20: -157750.76
A21: abr | B21: -107436.81 | D21: may | E21: -231232.4
A22: may | B22: 573490.2 | D22: jun
A23: jun | D23: Total general | E23: -695964.54
A24: Total general | B24: 332374.7
D25: Suma de TOTAL INGRESSOS | E25: Etiquetas de columna
A26: Etiquetas de fila | B26: Suma de Cost Salarial Positiu | E26: ene | F26: feb | G26: mar | H26: abr | I26: may | J26: jun | K26: Total general
A27: ene | B27: 257884.99
A28: feb | B28: 251854.16 | D28: Etiquetas de fila
A29: mar | B29: 276572.97 | D29: Empresa | E29: 289300.57 | F29: 522944.53 | G29: 693442.52 | H29: 532165.29 | I29: 1373718.1 | K29: 3411571
A30: abr | B30: 292045.78 | D30: Total general | E30: 289300.57 | F30: 522944.53 | G30: 693442.52 | H30: 532165.29 | I30: 1373718.1 | K30: 3411571
A31: may | B31: 254133.09
A32: jun | B32: 0
A33: Total general | B33: 1332491

Sheet Dashboard
