Workbook
Name CONSECUENCIAS: [1]Listas!$M$4:$M$15
Name Documentado: [1]Listas!$K$4:$K$5
Name Evidencia_del_Contol: [1]Listas!$I$4:$I$5
Name FACTOR_DE_RIESGO: [1]Listas!$O$4:$O$8
Name Forma_de_ejecución: [1]Listas!$E$4:$E$6
Name Frecuencia: [1]Listas!$G$4:$G$12
Name MACROPROCESO: [1]Listas!$N$4:$N$15
Name Tipo_de_Control: [1]Listas!$C$4:$C$6

Sheet Matriz Principal
A1: PROCESS | B1: RISK | C1: CAUSE | D1: RISK FACTOR | E1: CONSEQUENCE | F1: PROBABILITY | G1: ocultar | H1: Rep | I1: Legal | J1: Eco | K1: Oper | L1: IMPACT | M1: ocultar | N1: ocultar | O1: RESULT
A2: Portfolio Management | B2: - Desaceleración a largo plazo en los fundamentos/técnicos/sentimiento de los diferentes nichos de mercado donde se realizan inversiones. | C2: Los administradores realizan inversiones que infringen las pautas de inversión, los estatutos regulatorios y las políticas de cumplimiento y riesgo del grupo. | D2: Humano | E2: Reputational & economic | F2: 2 | G2: =VLOOKUP($F$2,'hoja de trabajo'!$A$1:$B$5,2,FALSE) -> 0.4 | H2: 4 | I2: 2 | J2: 5 | K2: 2 | L2: =ROUND(AVERAGE(H2:K2),0) -> 3 | M2: =VLOOKUP($L2,'hoja de trabajo'!$A$1:$B$5,2,FALSE) -> 0.6 | N2: =+CONCATENATE(F2,L2) -> 23 | O2: =+VLOOKUP(N2,'hoja de trabajo'!$F$2:$G$26,2,0) -> Moderate
A3: Fund Raising | B3: - Los problemas de capacidad del mercado y el aumento de la competencia limitan el crecimiento | C3: Omisiones en la identificación de oportunidades, fortalezas, amenazas y debilidades | D3: Humano | E3: Economic | F3: 2 | G3: =VLOOKUP($F$2,'hoja de trabajo'!$A$1:$B$5,2,FALSE) -> 0.4 | H3: 2 | I3: 2 | J3: 5 | K3: 2 | L3: =ROUND(AVERAGE(H3:K3),0) -> 3 | M3: =VLOOKUP($L3,'hoja de trabajo'!$A$1:$B$5,2,FALSE) -> 0.6 | N3: =+CONCATENATE(F3,L3) -> 23 | O3: =+VLOOKUP(N3,'hoja de trabajo'!$F$2:$G$26,2,0) -> Moderate
A4: ESG | B4: - Cambio climático, sostenibilidad y sus implicaciones para particulares, empresas e inversores | C4: Este es el riesgo de no comprender y planificar el impacto potencial para el negocio que el sentimiento de los inversores/empresas, el cambio climático y las regulaciones de sostenibilidad pueden tener en las preferencias de productos y en los precios de los activos subyacentes que pueden verse afectados por la transición a una economía con emisiones bajas de carbono. | D4: Proceso | E4: Reputational, economic & operational | F4: 3 | G4: =VLOOKUP($F$2,'hoja de trabajo'!$A$1:$B$5,2,FALSE) -> 0.4 | H4: 3 | I4: 2 | J4: 4 | K4: 2 | L4: =ROUND(AVERAGE(H4:K4),0) -> 3 | M4: =VLOOKUP($L4,'hoja de trabajo'!$A$1:$B$5,2,FALSE) -> 0.6 | N4: =+CONCATENATE(F4,L4) -> 33 | O4: =+VLOOKUP(N4,'hoja de trabajo'!$F$2:$G$26,2,0) -> High
A5: Fund Raising | B5: - Riesgo reputacional de los medios tradicionales, digitales y sociales. | C5: La reputación de la empresa se ve afectada por la prensa negativa, los informes inexactos y/o el posible abuso de fuentes tanto tradicionales como digitales. | D5: Externo | E5: Reputational & economic | F5: 2 | G5: =VLOOKUP($F$2,'hoja de trabajo'!$A$1:$B$5,2,FALSE) -> 0.4 | H5: 4 | I5: 3 | J5: 2 | K5: 2 | L5: =ROUND(AVERAGE(H5:K5),0) -> 3 | M5: =VLOOKUP($L5,'hoja de trabajo'!$A$1:$B$5,2,FALSE) -> 0.6 | N5: =+CONCATENATE(F5,L5) -> 23 | O5: =+VLOOKUP(N5,'hoja de trabajo'!$F$2:$G$26,2,0) -> Moderate
A6: Operations | B6: - Fraude interno perpetrado contra entidades, fondos o inversiones de la Compañía. | C6: El riesgo de que un administrador de fondos o cualquier persona en las áreas de apoyo del Grupo cometa un acto de fraude contra el grupo o uno de sus Fondos. | D6: Humano | E6: Economic | F6: 3 | G6: =VLOOKUP($F$2,'hoja de trabajo'!$A$1:$B$5,2,FALSE) -> 0.4 | H6: 2 | I6: 2 | J6: 5 | K6: 3 | L6: =ROUND(AVERAGE(H6:K6),0) -> 3 | M6: =VLOOKUP($L6,'hoja de trabajo'!$A$1:$B$5,2,FALSE) -> 0.6 | N6: =+CONCATENATE(F6,L6) -> 33 | O6: =+VLOOKUP(N6,'hoja de trabajo'!$F$2:$G$26,2,0) -> High
A7: Operations | B7: - Fraude externo e incumplimiento de contrato perpetrado contra la Compañía | C7: El riesgo de que un proveedor de servicios o un tercero cometa un acto de fraude contra el grupo o uno de sus Fondos | D7: Externo | E7: Economic | F7: 3 | G7: =VLOOKUP($F$2,'hoja de trabajo'!$A$1:$B$5,2,FALSE) -> 0.4 | H7: 2 | I7: 2 | J7: 5 | K7: 3 | L7: =ROUND(AVERAGE(H7:K7),0) -> 3 | M7: =VLOOKUP($L7,'hoja de trabajo'!$A$1:$B$5,2,FALSE) -> 0.6 | N7: =+CONCATENATE(F7,L7) -> 33 | O7: =+VLOOKUP(N7,'hoja de trabajo'!$F$2:$G$26,2,0) -> High
A8: Portfolio Management | B8: - Caída en el desempeño a largo plazo de las compañías donde se realizan las inversiones. | C8: La desaceleración a largo plazo de los fundamentos/aumento del riesgo geopolítico conduce a un período prolongado de salida neta de fondos, desempeño adverso y/o pérdida de confianza de los inversores. | D8: Externo | E8: Reputational & economic | F8: 3 | G8: =VLOOKUP($F$2,'hoja de trabajo'!$A$1:$B$5,2,FALSE) -> 0.4 | H8: 4 | I8: 2 | J8: 5 | K8: 2 | L8: =ROUND(AVERAGE(H8:K8),0) -> 3 | M8: =VLOOKUP($L8,'hoja de trabajo'!$A$1:$B$5,2,FALSE) -> 0.6 | N8: =+CONCATENATE(F8,L8) -> 33 | O8: =+VLOOKUP(N8,'hoja de trabajo'!$F$2:$G$26,2,0) -> High
A9: Investor Relations | B9: - Supervisión inadecuada del cliente, incluida la alineación de intereses. | C9: Inadecuados canales de comunicación y reporte para alinear las expectativas de los clientes potenciales. | D9: Proceso | E9: Reputational & economic | F9: 2 | G9: =VLOOKUP($F$2,'hoja de trabajo'!$A$1:$B$5,2,FALSE) -> 0.4 | H9: 3 | I9: 2 | J9: 4 | K9: 2 | L9: =ROUND(AVERAGE(H9:K9),0) -> 3 | M9: =VLOOKUP($L9,'hoja de trabajo'!$A$1:$B$5,2,FALSE) -> 0.6 | N9: =+CONCATENATE(F9,L9) -> 23 | O9: =+VLOOKUP(N9,'hoja de trabajo'!$F$2:$G$26,2,0) -> Moderate
A10: Human Resources | B10: - Nivel de recursos, que incluye la pérdida de personal clave o la incapacidad de atraer personal y/u otros requisitos de salud y seguridad. | C10: Falta de capacidad para generar planes de continuidad del negocio y planes de carrera atractivos para los profesionales. | D10: Proceso | E10: Operational & economic | F10: 2 | G10: =VLOOKUP($F$2,'hoja de trabajo'!$A$1:$B$5,2,FALSE) -> 0.4 | H10: 2 | I10: 2 | J10: 5 | K10: 4 | L10: =ROUND(AVERAGE(H10:K10),0) -> 3 | M10: =VLOOKUP($L10,'hoja de trabajo'!$A$1:$B$5,2,FALSE) -> 0.6 | N10: =+CONCATENATE(F10,L10) -> 23 | O10: =+VLOOKUP(N10,'hoja de trabajo'!$F$2:$G$26,2,0) -> Moderate
A11: Operations | B11: - Fallas en la seguridad de la información, incluidas protecciones y medidas adecuadas en relación con ataques cibernéticos y de ransomware | C11: Controles inadecuados en torno a la seguridad de la información que resultan en pérdida de datos, pérdida financiera y/o uso inadecuado de la información. | D11: Proceso | E11: Operational & economic | F11: 2 | G11: =VLOOKUP($F$2,'hoja de trabajo'!$A$1:$B$5,2,FALSE) -> 0.4 | H11: 2 | I11: 2 | J11: 5 | K11: 4 | L11: =ROUND(AVERAGE(H11:K11),0) -> 3 | M11: =VLOOKUP($L11,'hoja de trabajo'!$A$1:$B$5,2,FALSE) -> 0.6 | N11: =+CONCATENATE(F11,L11) -> 23 | O11: =+VLOOKUP(N11,'hoja de trabajo'!$F$2:$G$26,2,0) -> Moderate
A12: Operations | B12: - Inadecuada planificación de la continuidad del negocio (BCP) que cubre personas, edificios y sistemas. | C12: Fallas en los servicios tecnológicos de redes y comunicaciones prestados por la matriz | D12: Proceso | E12: Operational | F12: 2 | G12: =VLOOKUP($F$2,'hoja de trabajo'!$A$1:$B$5,2,FALSE) -> 0.4 | H12: 2 | I12: 2 | J12: 5 | K12: 4 | L12: =ROUND(AVERAGE(H12:K12),0) -> 3 | M12: =VLOOKUP($L12,'hoja de trabajo'!$A$1:$B$5,2,FALSE) -> 0.6 | N12: =+CONCATENATE(F12,L12) -> 23 | O12: =+VLOOKUP(N12,'hoja de trabajo'!$F$2:$G$26,2,0) -> Moderate
A13: Legal & Compliance | B13: - Acción legal por o contra la Compañía por parte de partes externas y/o empleados | C13: Acción legal por o contra la Compañía y/o sus fondos por parte de partes externas y/o empleados | D13: Externo | E13: Legal, reputational & economic | F13: 1 | G13: =VLOOKUP($F$2,'hoja de trabajo'!$A$1:$B$5,2,FALSE) -> 0.4 | H13: 1 | I13: 4 | J13: 3 | K13: 2 | L13: =ROUND(AVERAGE(H13:K13),0) -> 3 | M13: =VLOOKUP($L13,'hoja de trabajo'!$A$1:$B$5,2,FALSE) -> 0.6 | N13: =+CONCATENATE(F13,L13) -> 13 | O13: =+VLOOKUP(N13,'hoja de trabajo'!$F$2:$G$26,2,0) -> Moderate
... A21: Finance | B21: - Provisión adecuada de solvencia y liquidez (incluido el capital regulatorio). | C21: Errores u omisiones en la parametrización de límites en sistemas de monitorización | D21: Humano | E21: Legal & Economic | F21: 2 | G21: =VLOOKUP($F$2,'hoja de trabajo'!$A$1:$B$5,2,FALSE) -> 0.4 | H21: 1 | I21: 3 | J21: 5 | K21: 2 | L21: =ROUND(AVERAGE(H21:K21),0) -> 3 | M21: =VLOOKUP($L21,'hoja de trabajo'!$A$1:$B$5,2,FALSE) -> 0.6 | N21: =+CONCATENATE(F21,L21) -> 23 | O21: =+VLOOKUP(N21,'hoja de trabajo'!$F$2:$G$26,2,0) -> Moderate

Sheet Mapa
D2: Inherent Risk Profile | L2: Residual Risk Profile
C3: Frequency | D3: Inherent Risk | K3: Frequency | L3: Residual Risk
B4: Probability | C4: 5. Very frequent 100% | D4: =(COUNTIF('Matriz Principal'!$N$2:$N$21,51)) -> 0 | E4: =+COUNTIF('Matriz Principal'!$N2:$N$21,52) -> 0 | F4: =+COUNTIF('Matriz Principal'!$N2:$N$21,53) -> 0 | G4: =+COUNTIF('Matriz Principal'!$N2:$N$21,54) -> 0 | H4: =+COUNTIF('Matriz Principal'!$N2:$N$21,55) -> 0 | J4: Probability | K4: 5. Very frequent 100% | L4: =+COUNTIF([1]Matrix!$AP$6:$AP$5858,51) -> 0 | M4: =+COUNTIF([1]Matrix!$AP$6:$AP$5858,52) -> 0 | N4: =+COUNTIF([1]Matrix!$AP$6:$AP$5858,53) -> 0 | O4: =+COUNTIF([1]Matrix!$AP$6:$AP$5858,54) -> 0 | P4: =+COUNTIF([1]Matrix!$AP$6:$AP$5858,55) -> 0
C5: 4. Probable 80% | D5: =+COUNTIF('Matriz Principal'!$N2:$N$21,41) -> 0 | E5: =+COUNTIF('Matriz Principal'!$N2:$N$21,42) -> 1 | F5: =+COUNTIF('Matriz Principal'!$N2:$N$21,43) -> 0 | G5: =+COUNTIF('Matriz Principal'!$N2:$N$21,44) -> 0 | H5: =+COUNTIF('Matriz Principal'!$N2:$N$21,45) -> 0 | K5: 4. Probable 80% | L5: =+COUNTIF([1]Matrix!$AP$6:$AP$5858,41) -> 0 | M5: =+COUNTIF([1]Matrix!$AP$6:$AP$5858,42) -> 0 | N5: =+COUNTIF([1]Matrix!$AP$6:$AP$5858,43) -> 0 | O5: =+COUNTIF([1]Matrix!$AP$6:$AP$5858,44) -> 0 | P5: =+COUNTIF([1]Matrix!$AP$6:$AP$5858,45) -> 0
C6: 3. May occur 60% | D6: =+COUNTIF('Matriz Principal'!$N2:$N$21,31) -> 0 | E6: =+COUNTIF('Matriz Principal'!$N2:$N$21,32) -> 0 | F6: =+COUNTIF('Matriz Principal'!$N2:$N$21,33) -> 6 | G6: =+COUNTIF('Matriz Principal'!$N2:$N$21,34) -> 1 | H6: =+COUNTIF('Matriz Principal'!$N2:$N$21,35) -> 0 | K6: 3. May occur 60% | L6: =+COUNTIF([1]Matrix!$AP$6:$AP$5858,31) -> 0 | M6: =+COUNTIF([1]Matrix!$AP$6:$AP$5858,32) -> 2 | N6: =+COUNTIF([1]Matrix!$AP$6:$AP$5858,33) -> 0 | O6: =+COUNTIF([1]Matrix!$AP$6:$AP$5858,34) -> 0 | P6: =+COUNTIF([1]Matrix!$AP$6:$AP$5858,35) -> 0
C7: 2. Eventually 40% | D7: =+COUNTIF('Matriz Principal'!$N2:$N$21,21) -> 0 | E7: =+COUNTIF('Matriz Principal'!$N2:$N$21,22) -> 1 | F7: =+COUNTIF('Matriz Principal'!$N2:$N$21,23) -> 10 | G7: =+COUNTIF('Matriz Principal'!$N2:$N$21,24) -> 0 | H7: =+COUNTIF('Matriz Principal'!$N2:$N$21,25) -> 0 | K7: 2. Eventually 40% | L7: =+COUNTIF([1]Matrix!$AP$6:$AP$5858,21) -> 0 | M7: =+COUNTIF([1]Matrix!$AP$6:$AP$5858,22) -> 17 | N7: =+COUNTIF([1]Matrix!$AP$6:$AP$5858,23) -> 7 | O7: =+COUNTIF([1]Matrix!$AP$6:$AP$5858,24) -> 0 | P7: =+COUNTIF([1]Matrix!$AP$6:$AP$5858,25) -> 0
C8: 1. Rarely 20% | D8: =+COUNTIF('Matriz Principal'!$N2:$N$21,11) -> 0 | E8: =+COUNTIF('Matriz Principal'!$N2:$N$21,12) -> 0 | F8: =+COUNTIF('Matriz Principal'!$N2:$N$21,13) -> 1 | G8: =+COUNTIF('Matriz Principal'!$N2:$N$21,14) -> 0 | H8: =+COUNTIF('Matriz Principal'!$N2:$N$21,15) -> 0 | K8: 1. Rarely 20% | L8: =+COUNTIF([1]Matrix!$AP$6:$AP$5858,11) -> 0 | M8: =+COUNTIF([1]Matrix!$AP$6:$AP$5858,12) -> 4 | N8: =+COUNTIF([1]Matrix!$AP$6:$AP$5858,13) -> 0 | O8: =+COUNTIF([1]Matrix!$AP$6:$AP$5858,14) -> 0 | P8: =+COUNTIF([1]Matrix!$AP$6:$AP$5858,15) -> 0
D9: 1. Insignificant 20% | E9: 2. Minor 40% | F9: 3. Moderate 60% | G9: 4. Major 80% | H9: 5.High Impact 100% | L9: 1. Insignificant 20% | M9: 2. Minor 40% | N9: 3. Moderate 60% | O9: 4. Major 80% | P9: 5.High Impact 100%
D10: Impact | L10: Impact

Sheet hoja de trabajo
A1: 1 | B1: 0.2 | D1: Probability | E1: Impact | G1: Result | I1: Reputational & economic
A2: 2 | B2: 0.4 | D2: 1 | E2: 1 | F2: =+CONCATENATE(D2,E2) -> 11 | G2: Low | I2: Operational & economic
A3: 3 | B3: 0.6 | D3: 1 | E3: 2 | F3: =+CONCATENATE(D3,E3) -> 12 | G3: Low | I3: Operational, legal & economic
A4: 4 | B4: 0.8 | D4: 1 | E4: 3 | F4: =+CONCATENATE(D4,E4) -> 13 | G4: Moderate | I4: Legal, reputational & economic
A5: 5 | B5: 1 | D5: 1 | E5: 4 | F5: =+CONCATENATE(D5,E5) -> 14 | G5: High | I5: Reputational, economic & operational
D6: 1 | E6: 5 | F6: =+CONCATENATE(D6,E6) -> 15 | G6: High | I6: Legal & Economic
D7: 2 | E7: 1 | F7: =+CONCATENATE(D7,E7) -> 21 | G7: Low | I7: Operational
D8: 2 | E8: 2 | F8: =+CONCATENATE(D8,E8) -> 22 | G8: Low | I8: Economic
D9: 2 | E9: 3 | F9: =+CONCATENATE(D9,E9) -> 23 | G9: Moderate
D10: 2 | E10: 4 | F10: =+CONCATENATE(D10,E10) -> 24 | G10: High
D11: 2 | E11: 5 | F11: =+CONCATENATE(D11,E11) -> 25 | G11: Extreme
D12: 3 | E12: 1 | F12: =+CONCATENATE(D12,E12) -> 31 | G12: Low
D13: 3 | E13: 2 | F13: =+CONCATENATE(D13,E13) -> 32 | G13: Moderate
D14: 3 | E14: 3 | F14: =+CONCATENATE(D14,E14) -> 33 | G14: High
D15: 3 | E15: 4 | F15: =+CONCATENATE(D15,E15) -> 34 | G15: Extreme
D16: 3 | E16: 5 | F16: =+CONCATENATE(D16,E16) -> 35 | G16: Extreme
D17: 4 | E17: 1 | F17: =+CONCATENATE(D17,E17) -> 41 | G17: Low
D18: 4 | E18: 2 | F18: =+CONCATENATE(D18,E18) -> 42 | G18: Moderate
D19: 4 | E19: 3 | F19: =+CONCATENATE(D19,E19) -> 43 | G19: High
D20: 4 | E20: 4 | F20: =+CONCATENATE(D20,E20) -> 44 | G20: Extreme
... D26: 5 | E26: 5 | F26: =+CONCATENATE(D26,E26) -> 55 | G26: Extreme
