Workbook

Sheet Principal
C6: Nº | D6: Departamento | E6: Función del proceso | F6: Falla potencial | G6: Efecto potencial | H6: Severidad | I6: Causas Potenciales de las fallas | J6: Ocurrencia | K6: valor matriu
C7: 1 | D7: Compras | E7: Pedido de compra | F7: Suministro materia prima Subida substancial de precio. | G7: No se puede producir. Falta de genereo en el evento. | H7: 4 | I7: No tener segundos proveedores Tener materias substitutivas | J7: 1 | K7: =+CONCATENATE(J7,H7) -> 14
C8: 2 | D8: Comercial | E8: Oferta comercial | F8: No se adecua con las nuevas tendencias | G8: Bajada de las ventas | H8: 4 | I8: ampliar la gamma de produictos a ofrecer. No tener diferente tipologia de cliente. | J8: 2 | K8: =+CONCATENATE(J8,H8) -> 24
C9: 3 | D9: Centros Externos | E9: Venta menus | F9: No es oportuna nuestra oferta gastronomica a nuestro cliente final | G9: Bajada de ingresos. Mayor % coste salarial Menor rotación de procuto. | H9: 3 | I9: Poca flexibilidad . Baja oferta de menús Mala ubicación del centro. | J9: 3 | K9: =+CONCATENATE(J9,H9) -> 33
C10: 4 | D10: Marqueting | E10: Comunicar RRSS | F10: Mala imagen en un Evento de gran repercusión | G10: Baja reputación. Perdida de clientes potenciales Afectaciones a las otras lineas de negocio | H10: 3 | I10: Mala Ejecucion del evento. Mala planificación. Mala comunicación | J10: 1 | K10: =+CONCATENATE(J10,H10) -> 13
C11: 5 | D11: Recursos Humanos | E11: Contratación Personal | F11: Falta personal en el sector | G11: Mal servicio Exceso de hora extras | H11: 3 | I11: Falta de previsión. Falta de un plan motivacional para gente quiera venir a trabajar. Falta Plan de carrera laboral para el futuro trabajador. | J11: 5 | K11: =+CONCATENATE(J11,H11) -> 53
C12: 6 | D12: Logistica | E12: Preparación Evento | F12: Rotura de estoc | G12: Falta de materiales / maquinaria / mobiliario en los eventos | H12: 2 | I12: Falta de procesos de control | J12: 3 | K12: =+CONCATENATE(J12,H12) -> 32
C13: 7 | D13: Cocina Central | E13: Produccion producto final. | F13: Capcidad de planta | G13: No llegar a ucbrir los pedidos. Mal servicio y ambiente de trabajo. | H13: 4 | I13: Falta de prevision. Mno tener controlada la cpacidad de prodcuccion. | J13: 1 | K13: =+CONCATENATE(J13,H13) -> 14
C14: 8 | D14: Mantenimiento | E14: Adjudicacion de maquinaria | F14: No tener apunto la maquinaria | G14: Tener que ejcutar el evento con maquinaria no apropiada | H14: 2 | I14: falta de personal Mala planificacion de las cargas de trabajo Falta de suministro de materiales. | J14: 5 | K14: =+CONCATENATE(J14,H14) -> 52
C15: 9 | D15: Logística | E15: Transporte de mercaderias | F15: Perdida / Accidente del trasnporte | G15: Producir con urgencia Retraso en el evneto sobrecoste | H15: 5 | I15: Falta de mantenimineto del transporte Mala practesis del transportista Previsión de ruta Mala suerte. | J15: 1 | K15: =+CONCATENATE(J15,H15) -> 15
C16: 10 | D16: Financiero | E16: Pago de Préstamos | F16: subida tpo de intereses | G16: Mayor coste | H16: 1 | I16: Realización tabla de costes. Previsión de subida. No tener seguro sobre subida tipo interes. | J16: 2 | K16: =+CONCATENATE(J16,H16) -> 21

Sheet hoja de trabajo
B2: 1 | C2: 0.1 | E2: Ocurrencia | F2: Severidad | H2: Impacto
B3: 2 | C3: 0.2 | E3: 1 | F3: 1 | G3: =+CONCATENATE(E3,F3) -> 11 | H3: Bajo
B4: 3 | C4: 0.3 | E4: 1 | F4: 2 | G4: =+CONCATENATE(E4,F4) -> 12 | H4: Bajo
B5: 4 | C5: 0.4 | E5: 1 | F5: 3 | G5: =+CONCATENATE(E5,F5) -> 13 | H5: Moderado
B6: 5 | C6: 0.5 | E6: 1 | F6: 4 | G6: =+CONCATENATE(E6,F6) -> 14 | H6: Alto
B7: 6 | C7: 0.6 | E7: 1 | F7: 5 | G7: =+CONCATENATE(E7,F7) -> 15 | H7: Alto
B8: 7 | C8: 0.7 | E8: 2 | F8: 1 | G8: =+CONCATENATE(E8,F8) -> 21 | H8: Bajo
B9: 8 | C9: 0.8 | E9: 2 | F9: 2 | G9: =+CONCATENATE(E9,F9) -> 22 | H9: Moderado
B10: 9 | C10: 0.9 | E10: 2 | F10: 3 | G10: =+CONCATENATE(E10,F10) -> 23 | H10: Moderado
B11: 10 | C11: 1 | E11: 2 | F11: 4 | G11: =+CONCATENATE(E11,F11) -> 24 | H11: Alto
E12: 2 | F12: 5 | G12: =+CONCATENATE(E12,F12) -> 25 | H12: Muy alto
E13: 3 | F13: 1 | G13: =+CONCATENATE(E13,F13) -> 31 | H13: Bajo
E14: 3 | F14: 2 | G14: =+CONCATENATE(E14,F14) -> 32 | H14: Moderado
E15: 3 | F15: 3 | G15: =+CONCATENATE(E15,F15) -> 33 | H15: Alto
E16: 3 | F16: 4 | G16: =+CONCATENATE(E16,F16) -> 34 | H16: Muy alto
E17: 3 | F17: 5 | G17: =+CONCATENATE(E17,F17) -> 35 | H17: Muy alto
E18: 4 | F18: 1 | G18: =+CONCATENATE(E18,F18) -> 41 | H18: Moderado
E19: 4 | F19: 2 | G19: =+CONCATENATE(E19,F19) -> 42 | H19: Moderado
E20: 4 | F20: 3 | G20: =+CONCATENATE(E20,F20) -> 43 | H20: Alto
E21: 4 | F21: 4 | G21: =+CONCATENATE(E21,F21) -> 44 | H21: Muy alto
E22: 4 | F22: 5 | G22: =+CONCATENATE(E22,F22) -> 45 | H22: Muy alto
E23: 5 | F23: 1 | G23: =+CONCATENATE(E23,F23) -> 51 | H23: Moderado
... E27: 5 | F27: 5 | G27: =+CONCATENATE(E27,F27) -> 55 | H27: Muy alto

Sheet MAPA
A4: Probabilidad | B4: 5 - Muy frecuente | C4: =COUNTIF(Principal!$K$7:$K$16,51) -> 0 | D4: =COUNTIF(Principal!$K$7:$K$16,52) -> 1 | E4: =COUNTIF(Principal!$K$7:$K$16,53) -> 1 | F4: =COUNTIF(Principal!$K$7:$K$16,54) -> 0 | G4: =COUNTIF(Principal!$K$7:$K$16,55) -> 0
B5: 4 -Probable | C5: =COUNTIF(Principal!$K$7:$K$16,41) -> 0 | D5: =COUNTIF(Principal!$K$7:$K$16,42) -> 0 | E5: =COUNTIF(Principal!$K$7:$K$16,43) -> 0 | F5: =COUNTIF(Principal!$K$7:$K$16,44) -> 0 | G5: =COUNTIF(Principal!$K$7:$K$16,45) -> 0
B6: 3- Raramente | C6: =COUNTIF(Principal!$K$7:$K$16,31) -> 0 | D6: =COUNTIF(Principal!$K$7:$K$16,32) -> 1 | E6: =COUNTIF(Principal!$K$7:$K$16,33) -> 1 | F6: =COUNTIF(Principal!$K$7:$K$16,34) -> 0 | G6: =COUNTIF(Principal!$K$7:$K$16,35) -> 0
B7: 2- Ocasionalmente | C7: =COUNTIF(Principal!$K$7:$K$16,21) -> 1 | D7: =COUNTIF(Principal!$K$7:$K$16,22) -> 0 | E7: =COUNTIF(Principal!$K$7:$K$16,22) -> 0 | F7: =COUNTIF(Principal!$K$7:$K$16,24) -> 1 | G7: =COUNTIF(Principal!$K$7:$K$16,25) -> 0
B8: 1- Casi nunca | C8: =COUNTIF(Principal!$K$7:$K$16,11) -> 0 | D8: =COUNTIF(Principal!$K$7:$K$16,12) -> 0 | E8: =COUNTIF(Principal!$K$7:$K$16,13) -> 1 | F8: =COUNTIF(Principal!$K$7:$K$16,14) -> 2 | G8: =COUNTIF(Principal!$K$7:$K$16,15) -> 1
C9: 1-Insignificante | D9: 2- Menor | E9: 3- Moderado | F9: 4- Alto | G9: 5- Extremo
C11: Impacto
