Workbook

Sheet Sheet1
A1: # | B1: Node | C1: Description | D1: TOTAL | E1: CCR00000 | F1: CCR00001 | G1: CCR00002 | H1: CCR00003 | I1: CCR00004 | J1: CCR00005 | K1: CCR00006 | L1: CCR00007 | M1: CCR00009 | N1: CCR00010 | O1: Sin Cent
A2: 1 | B2: 1 | C2: COMPTE DE RESULTATS | D2: 0 | E2: 0 | F2: 0 | G2: 0 | H2: 0 | I2: 0 | J2: 0 | K2: 0 | L2: 0 | M2: 0 | N2: 0 | O2: 0
A3: 2 | B3: 2 | C3: . VENDES | D3: =SUM(E3:N3) -> 642279.98 | E3: 0 | F3: 33967.08 | G3: 136858.38 | H3: =187948.27+2185.44 -> 190133.71 | I3: 121798.71 | J3: 17474.96 | K3: 96794.86 | L3: 19731.36 | M3: 4375 | N3: 21145.92 | O3: 0
A4: 3 | B4: 3 | C4: . PRESTACIO DE SEVEIS | D4: =SUM(E4:N4) -> 0 | E4: 0 | F4: 0 | G4: 0 | H4: 0 | I4: 0 | J4: 0 | K4: 0 | L4: 0 | M4: 0 | N4: 0 | O4: 0
A5: 4 | B5: 4 | C5: . ALTRES INGRESSOS | D5: =SUM(E5:N5) -> 4617.95 | E5: 0 | F5: 0 | G5: 0 | H5: 317.95 | I5: 0 | J5: 0 | K5: 0 | L5: 4300 | M5: 0 | N5: 0 | O5: 0
A6: 5 | B6: 5 | C6: . VARIACIO EXISTENCIES | D6: =SUM(E6:N6) -> 0 | E6: 0 | F6: 0 | G6: 0 | H6: 0 | I6: 0 | J6: 0 | K6: 0 | L6: 0 | M6: 0 | N6: 0 | O6: 0
A7: 6 | B7: 6 | C7: TOTAL INGRESSOS EXPLOTACIO | D7: =SUM(D3:D6) -> 646897.93 | E7: =SUM(E3:E6) -> 0 | F7: =SUM(F3:F6) -> 33967.08 | G7: =SUM(G3:G6) -> 136858.38 | H7: =SUM(H3:H6) -> 190451.66 | I7: =SUM(I3:I6) -> 121798.71 | J7: =SUM(J3:J6) -> 17474.96 | K7: =SUM(K3:K6) -> 96794.86 | ... N7: =SUM(N3:N6) -> 21145.92 | O7: 0
A8: 7 | B8: 7 | C8: . COMPRES | D8: =SUM(E8:N8) -> -130129.79 | E8: 0 | F8: -8643.92 | G8: -27957.1 | H8: -38115.44 | I8: -22034.97 | J8: -4520 | K8: -20498.49 | L8: -2164.37 | M8: -1272.26 | N8: -4923.24 | O8: 0
A9: 8 | B9: 8 | C9: . ALTRES APROVISIONAMENTS | D9: =SUM(E9:N9) -> -8068.66 | E9: 0 | F9: -436.94 | G9: -1180.38 | H9: -2481.5 | I9: -416.43 | J9: -382.18 | K9: -2577.15 | L9: -21.85 | M9: -7.72 | N9: -564.51 | O9: 0
A10: 9 | B10: 9 | C10: . CONSUMS INTERNS | D10: =SUM(E10:N10) -> -69917.98 | E10: 0 | F10: ='Consums Interns'!B13 -> -7297.03 | G10: ='Consums Interns'!C13 -> -13640.98 | H10: ='Consums Interns'!D13 -> -20280.87 | I10: ='Consums Interns'!E13 -> -7562.89 | J10: ='Consums Interns'!F13 -> -3814.06 | K10: ='Consums Interns'!G13 -> -11218.3 | L10: ='Consums Interns'!H13 -> -2188.87 | M10: ='Consums Interns'!J13 -> -1085.24 | N10: ='Consums Interns'!K13 -> -2829.74 | O10: 0
A11: 10 | B11: 10 | C11: . VARIACIO EXISTENICIES COMPRES | D11: =SUM(E11:N11) -> 0 | E11: 0 | F11: 0 | G11: 0 | H11: 0 | I11: 0 | J11: 0 | K11: 0 | L11: 0 | M11: 0 | N11: 0 | O11: 0
A12: 11 | B12: 11 | C12: TOTAL COMPRES | D12: =SUM(D8:D11) -> -208116.43 | E12: =SUM(E8:E11) -> 0 | F12: =SUM(F8:F11) -> -16377.89 | G12: =SUM(G8:G11) -> -42778.46 | H12: =SUM(H8:H11) -> -60877.81 | I12: =SUM(I8:I11) -> -30014.29 | J12: =SUM(J8:J11) -> -8716.24 | K12: =SUM(K8:K11) -> -34293.94 | ... N12: =SUM(N8:N11) -> -8317.49 | O12: 0 | P12: =D12/D7 -> -0.32171448
A13: 12 | B13: 12 | C13: MARGE BRUT TOTAL | D13: 521786.53 | E13: 0 | F13: 25646.34 | G13: 112653.34 | H13: 152451.29 | I13: 99986.25 | J13: 13267.26 | K13: 76576.53 | L13: 21954.31 | M13: 3135.43 | N13: 16115.78 | O13: 0
A14: 13 | B14: 13 | C14: . SOUS I SALARIS | D14: =SUM(E14:N14) -> -262022.04 | E14: =-21913.97-20000+2006.7 -> -39907.27 | F14: =-15329.84-611.75+2790.8-720 -> -13870.79 | G14: =-47216.24-804.25-1540.2 -> -49560.69 | H14: =-55201.27-507+2333.3-1943.4 -> -55318.37 | I14: =-30946.54+1492.5-597.9 -> -30051.94 | J14: =-8840.63-1240.25+75.6 -> -10005.28 | K14: =-31152.63-949.16+1079.74-425.1 -> -31447.15 | L14: =-12910.25-349 -> -13259.25 | M14: =-6371.22+4795.2-355.5 -> -1931.52 | N14: =-23240.78-860+8006.7-575.7 -> -16669.78 | O14: 0
A15: 14 | B15: 14 | C15: . INDEMNITZACIONS | D15: =SUM(E15:N15) -> -2200 | E15: 0 | F15: 0 | G15: 0 | H15: 0 | I15: -2200 | J15: 0 | K15: 0 | L15: 0 | M15: 0 | N15: 0 | O15: 0
A16: 15 | B16: 15 | C16: . SEGURETAT SOCIAL | D16: =SUM(E16:N16) -> -75385.48 | E16: -6794.11 | F16: -4438.09 | G16: -12436.82 | H16: -16841.82 | I16: -8926.75 | J16: -2954.4 | K16: -10112 | L16: -3987 | M16: -2099.85 | N16: -6794.64 | O16: 0
A17: 16 | B17: 16 | C17: . ALTRES DESPESES SOCIALS | D17: =SUM(E17:N17) -> -1778.57 | E17: -533.02 | F17: 0 | G17: -22.2 | H17: -31.8 | I17: -476.58 | J17: -486.57 | K17: 0 | L17: -228.4 | M17: 0 | N17: 0 | O17: 0
A18: 17 | B18: 17 | C18: TOTAL COST SALARIAL | D18: =SUM(D14:D17) -> -341386.09 | E18: =SUM(E14:E17) -> -47234.4 | F18: =SUM(F14:F17) -> -18308.88 | G18: =SUM(G14:G17) -> -62019.71 | H18: =SUM(H14:H17) -> -72191.99 | I18: =SUM(I14:I17) -> -41655.27 | J18: =SUM(J14:J17) -> -13446.25 | K18: =SUM(K14:K17) -> -41559.15 | ... N18: =SUM(N14:N17) -> -23464.42 | O18: 0 | P18: =D18/D7 -> -0.52772791
A19: 18 | B19: 18 | C19: . ARRENDAMENTS I CANONS | D19: =SUM(E19:N19) -> -40399.14 | E19: 0 | F19: 0 | G19: -5131.99 | H19: -267.58 | I19: -24359.07 | J19: -1500 | K19: -4220.36 | L19: 0 | M19: -1729.9 | N19: -3190.24 | O19: 0
A20: 19 | B20: 19 | C20: . REPARACIONS I CONSERVACIO | D20: =SUM(E20:N20) -> -16224.73 | E20: 0 | F20: -797.99 | G20: -763.74 | H20: -3403.34 | I20: -328.34 | J20: -509.48 | K20: -8521.21 | L20: -422.49 | M20: -44 | N20: -1434.14 | O20: 0
A21: 20 | B21: 20 | C21: . SERVEIS PROFESSIONALS | D21: =SUM(E21:N21) -> -6783.63 | E21: 0 | F21: -260.21 | G21: -1076.21 | H21: =-1182.96-200 -> -1382.96 | I21: -63.86 | J21: -288.26 | K21: -250.01 | L21: -86.81 | M21: -62 | N21: -3313.31 | O21: 0
A22: 21 | B22: 21 | C22: . TRANSPORTS | D22: =SUM(E22:N22) -> 0 | E22: 0 | F22: 0 | G22: 0 | H22: 0 | I22: 0 | J22: 0 | K22: 0 | L22: 0 | M22: 0 | N22: 0 | O22: 0
A23: 22 | B23: 22 | C23: . PRIMES D'ASSEGURANCES | D23: =SUM(E23:N23) -> -1417.17 | E23: 0 | F23: -439.61 | G23: -150.36 | H23: -374.13 | I23: -40.81 | J23: -96.37 | K23: -287.54 | L23: 0 | M23: -14.18 | N23: -14.17 | O23: 0
A24: 23 | B24: 23 | C24: . SERVEIS BANCARIS | D24: =SUM(E24:N24) -> -2927.84 | E24: 0 | F24: -148.58 | G24: -445.24 | H24: -473.9 | I24: -1249.49 | J24: -96.01 | K24: -339.2 | L24: -67.01 | M24: -38.69 | N24: -69.72 | O24: 0
A25: 24 | B25: 24 | C25: . PUBLICITAT I PROPAGANDA | D25: =SUM(E25:N25) -> -1248.74 | E25: 0 | F25: -10.74 | G25: 0 | H25: 0 | I25: 0 | J25: -800 | K25: 0 | L25: 0 | M25: 0 | N25: -438 | O25: 0
A26: 25 | B26: 25 | C26: . SUBMINISTRAMENTS | D26: =SUM(E26:N26) -> -18492.4 | E26: 0 | F26: -1591.65 | G26: -1700 | H26: -4936.12 | I26: -1034 | J26: 0 | K26: -3099.2 | L26: 0 | M26: -1770 | N26: -4361.43 | O26: 0
A27: 26 | B27: 26 | C27: . ALTRES DESPESES | D27: =SUM(E27:N27) -> -8604.39 | E27: -120 | F27: -672.77 | G27: -965.93 | H27: -3689.8 | I27: -967.62 | J27: -118.78 | K27: -1386.57 | L27: -124 | M27: 0 | N27: -558.92 | O27: 0
A28: 27 | B28: 27 | C28: . ALTRES TRIBUTS | D28: =SUM(E28:N28) -> -2891.37 | E28: 0 | F28: -1159.76 | G28: -656.64 | H28: -276.39 | I28: -207.23 | J28: -114 | K28: -161.45 | L28: 0 | M28: -25.33 | N28: -290.57 | O28: 0
A29: 28 | B29: 28 | C29: . DOTACIO PER INSOLVENCIA | D29: =SUM(E29:N29) -> 0 | E29: 0 | F29: 0 | G29: 0 | H29: 0 | I29: 0 | J29: 0 | K29: 0 | L29: 0 | M29: 0 | N29: 0 | O29: 0
A30: 29 | B30: 29 | C30: MOVIMENTS INTERNS | D30: =SUM(E30:N30) -> 0 | E30: 0 | F30: 0 | G30: 0 | H30: 0 | I30: 0 | J30: 0 | K30: 0 | L30: 0 | M30: 0 | N30: 0 | O30: 0
A31: 30 | B31: 30 | C31: TOTAL DESPESES GESTIO | D31: =SUM(D19:D30) -> -98989.41 | E31: =SUM(E19:E30) -> -120 | F31: =SUM(F19:F30) -> -5081.31 | G31: =SUM(G19:G30) -> -10890.11 | H31: =SUM(H19:H30) -> -14804.22 | I31: =SUM(I19:I30) -> -28250.42 | J31: =SUM(J19:J30) -> -3522.9 | K31: =SUM(K19:K30) -> -18265.54 | ... N31: =SUM(N19:N30) -> -13670.5 | O31: 0
A32: 31 | B32: 31 | C32: TOTAL GESTIO + SALARIS | D32: -65871.92 | E32: -120 | F32: -4735.02 | G32: -9107.92 | H32: -9464.07 | I32: -5730.91 | J32: -3502.54 | K32: -17571.73 | L32: 149.35 | M32: -3640.1 | N32: -12148.98 | O32: 0
A33: 32 | B33: 32 | C33: EBITDA | D33: =D7+(D12+D18+D31) -> -1594 | E33: =E7+(E12+E18+E31) -> -47354.4 | F33: =F7+(F12+F18+F31) -> -5801 | G33: =G7+(G12+G18+G31) -> 21170.1 | H33: =H7+(H12+H18+H31) -> 42577.64 | I33: =I7+(I12+I18+I31) -> 21878.73 | J33: =J7+(J12+J18+J31) -> -8210.43 | K33: =K7+(K12+K18+K31) -> 2676.23 | ... N33: =N7+(N12+N18+N31) -> -24306.49 | O33: 0

Sheet Consums Interns
A1: Nom Proveïdor | B1: ORIGENS | C1: NAUTIC | D1: LA MASIA | E1: CAMP NOU | F1: TARRACO | G1: MIRADOR | H1: JUNO HOUSE | I1: FDLC | J1: PLURAL | K1: SOLIVER | L1: Total Base Imposable
A2: CB BASES | B2: 3573.37 | C2: 5118.07 | D2: 8212.04 | E2: 3673.77 | F2: 930.3 | G2: 3937.21 | H2: 898.51 | I2: 1160.2 | J2: 626.39 | K2: 832.8 | L2: 47989.78
A3: CB BEGUDES | B3: 15.88 | C3: 778.73 | D3: 1007 | E3: 1242.58 | F3: 597.04 | G3: 828.39 | H3: 0 | I3: 752.7 | J3: 0 | K3: 302.72 | L3: 6240.21
A4: CB CONGELAT | B4: 2534.96 | C4: 5099.66 | D4: 6224.79 | E4: 1038.08 | F4: 1317.18 | G4: 3782.57 | H4: 372.08 | I4: 553.2 | J4: 219.46 | K4: 777.77 | L4: 25325.02
A5: CB EMBALATGE CUINA | B5: 102.93 | C5: 77.65 | D5: 138.09 | E5: 12.49 | F5: 19.77 | G5: 13.52 | H5: 3.48 | I5: 38.28 | J5: 1.5 | K5: 25.05 | L5: 432.76
A6: CB FRESC | B6: 160.28 | C6: 95.5 | D6: 1579.82 | E6: 59.36 | F6: 114.74 | G6: 734.63 | H6: 308.05 | I6: 251.81 | J6: 32 | K6: 211.01 | L6: 4748.35
A7: CB MATERIAL | B7: 209.15 | C7: 310.13 | D7: 84.54 | E7: 292.62 | F7: 235.2 | G7: 217.29 | H7: 10 | I7: 32.3 | J7: 0 | K7: 0 | L7: 1391.23
A8: CB MATERIAL OFICINA | B8: 0 | C8: 30 | D8: 110.88 | E8: 83.2 | F8: 8.88 | G8: 0 | H8: 0 | I8: 0 | J8: 0 | K8: 13.08 | L8: 246.04
A9: CB NETEJA | B9: 0 | C9: 0 | D9: 34.11 | E9: 34.12 | F9: 60 | G9: 0 | H9: 124.55 | I9: 0 | J9: 19.31 | K9: 15.68 | L9: 287.77
A10: CB PARAMENT | B10: 0 | C10: 452.93 | D10: 32.22 | E10: 0 | F10: 0 | G10: 0 | H10: 0 | I10: 0 | J10: 0 | K10: 0 | L10: 485.15
A11: CB SEC | B11: 700.46 | C11: 1678.31 | D11: 2857.38 | E11: 1126.67 | F11: 530.95 | G11: 1704.69 | H11: 472.2 | I11: 1060.04 | J11: 186.58 | K11: 651.63 | L11: 11225.68
B13: =SUM(B2:B11)*-1 -> -7297.03 | C13: =SUM(C2:C11)*-1 -> -13640.98 | D13: =SUM(D2:D11)*-1 -> -20280.87 | E13: =SUM(E2:E11)*-1 -> -7562.89 | F13: =SUM(F2:F11)*-1 -> -3814.06 | G13: =SUM(G2:G11)*-1 -> -11218.3 | H13: =SUM(H2:H11)*-1 -> -2188.87 | I13: =SUM(I2:I11)*-1 -> -3848.53 | ... L13: =SUM(L2:L11)*-1 -> -98371.99

Sheet OFICIAL
A1: Node | B1: Description | C1: TOTAL | D1: CCR00000 | E1: CCR00001 | F1: CCR00002 | G1: CCR00003 | H1: CCR00004 | I1: CCR00005 | J1: CCR00006 | K1: CCR00007 | L1: CCR00009 | M1: CCR00010 | N1: Sin Cent
A2: 1 | B2: COMPTE DE RESULTATS | C2: 0 | D2: 0 | E2: 0 | F2: 0 | G2: 0 | H2: 0 | I2: 0 | J2: 0 | K2: 0 | L2: 0 | M2: 0 | N2: 0
A3: 2 | B3: . VENDES | C3: 640094.54 | D3: 0 | E3: 33967.08 | F3: 136858.38 | G3: 187948.27 | H3: 121798.71 | I3: 17474.96 | J3: 96794.86 | K3: 19731.36 | L3: 4375 | M3: 21145.92 | N3: 0
A4: 3 | B4: . PRESTACIO DE SEVEIS | C4: 0 | D4: 0 | E4: 0 | F4: 0 | G4: 0 | H4: 0 | I4: 0 | J4: 0 | K4: 0 | L4: 0 | M4: 0 | N4: 0
A5: 4 | B5: . ALTRES INGRESSOS | C5: 4617.95 | D5: 0 | E5: 0 | F5: 0 | G5: 317.95 | H5: 0 | I5: 0 | J5: 0 | K5: 4300 | L5: 0 | M5: 0 | N5: 0
A6: 5 | B6: . VARIACIO EXISTENCIES | C6: 0 | D6: 0 | E6: 0 | F6: 0 | G6: 0 | H6: 0 | I6: 0 | J6: 0 | K6: 0 | L6: 0 | M6: 0 | N6: 0
A7: 6 | B7: TOTAL INGRESSOS EXPLOTACIO | C7: 644712.49 | D7: 0 | E7: 33967.08 | F7: 136858.38 | G7: 188266.22 | H7: 121798.71 | I7: 17474.96 | J7: 96794.86 | K7: 24031.36 | L7: 4375 | M7: 21145.92 | N7: 0
A8: 7 | B8: . COMPRES | C8: -130129.79 | D8: 0 | E8: -8643.92 | F8: -27957.1 | G8: -38115.44 | H8: -22034.97 | I8: -4520 | J8: -20498.49 | K8: -2164.37 | L8: -1272.26 | M8: -4923.24 | N8: 0
A9: 8 | B9: . ALTRES APROVISIONAMENTS | C9: -8068.66 | D9: 0 | E9: -436.94 | F9: -1180.38 | G9: -2481.5 | H9: -416.43 | I9: -382.18 | J9: -2577.15 | K9: -21.85 | L9: -7.72 | M9: -564.51 | N9: 0
A10: 9 | B10: . CONSUMS INTERNS | C10: 0 | D10: 0 | E10: 0 | F10: 0 | G10: 0 | H10: 0 | I10: 0 | J10: 0 | K10: 0 | L10: 0 | M10: 0 | N10: 0
A11: 10 | B11: . VARIACIO EXISTENICIES COMPRES | C11: 0 | D11: 0 | E11: 0 | F11: 0 | G11: 0 | H11: 0 | I11: 0 | J11: 0 | K11: 0 | L11: 0 | M11: 0 | N11: 0
A12: 11 | B12: TOTAL COMPRES | C12: -138198.45 | D12: 0 | E12: -9080.86 | F12: -29137.48 | G12: -40596.94 | H12: -22451.4 | I12: -4902.18 | J12: -23075.64 | K12: -2186.22 | L12: -1279.98 | M12: -5487.75 | N12: 0
A13: 12 | B13: MARGE BRUT TOTAL | C13: 506514.04 | D13: 0 | E13: 24886.22 | F13: 107720.9 | G13: 147669.28 | H13: 99347.31 | I13: 12572.78 | J13: 73719.22 | K13: 21845.14 | L13: 3095.02 | M13: 15658.17 | N13: 0
... A45: 999 | B45: . No definido !!! | C45: 0 | D45: 0 | E45: 0 | F45: 0 | G45: 0 | H45: 0 | I45: 0 | J45: 0 | K45: 0 | L45: 0 | M45: 0 | N45: 0
