Workbook

Sheet Servidores
C4: Coste Adquisición | D4: Amortización del ejercicio | E4: Valor contable fin de ejercicio | F4: Costes financieros | G4: Resto de gastos imputables | I4: Precio alquiler ofertado
B5: Servidor 1 | C5: 150947.88 | D5: -7547.39 | E5: 132079.39 | F5: 4431.95 | G5: 3668.85 | I5: 30000
B6: Servidor 2 | C6: 153940.44 | D6: -7697.02 | E6: 139829.23 | F6: 5031.44 | G6: 3668.85 | I6: 30000
B7: Servidor 3 | C7: 182110.41 | D7: -9105.52 | E7: 169969.72 | F7: 6076.84 | G7: 3668.85 | I7: 30000
B8: Servidor 4 | C8: 183200.25 | D8: -9160.01 | E8: 171750.23 | F8: 3294.72 | G8: 3668.85 | I8: 30000
C9: =SUM(C5:C8) -> 670198.98 | D9: =SUM(D5:D8) -> -33509.94 | E9: =SUM(E5:E8) -> 613628.57 | F9: =SUM(F5:F8) -> 18834.95 | G9: =SUM(G5:G8) -> 14675.4 | I9: =SUM(I5:I8) -> 120000
B14: Calculo ROA
B15: Total Ingresos | C15: =+I9 -> 120000
B17: Costees directos
B18: Amortización | C18: =+D9 -> -33509.94
B19: Costes financieros | C19: =-F9 -> -18834.95
B20: Resto de gastos imputables | C20: =-G9 -> -14675.4
C21: =SUM(C18:C20) -> -67020.29
B23: Resultado | C23: =+C15+C21 -> 52979.71
B25: Coste Propiedad | C25: =+C9 -> 670198.98
B27: ROA | C27: =+C23/C25 -> 0.079050717
B33: Comparabilidad:
C34: Mínimo | D34: Cuartil bajo | E34: Mediana | F34: Cuartil alto | G34: Máximo
B35: Valores comparabilidad | C35: =+'Empresas comparables'!N14 -> 0.023962148 | D35: =+'Empresas comparables'!N15 -> 0.044691766 | E35: =+'Empresas comparables'!N16 -> 0.062721631 | F35: =+'Empresas comparables'!N17 -> 0.091675744 | G35: =+'Empresas comparables'!N18 -> 0.12126283

Sheet Empresas comparables
B2: EMPRESAS QUE PRESTAN SERVICIOS DE ARRENDAMIENTO DE EQUIPOS INFORMÁTICOS
J4: ROA
B5: EMPRESA 1 | K5: 2018 | L5: 2017 | M5: 2016 | N5: Promedio 2 años
C6: 2018 | D6: 2017 | E6: 2016 | F6: 2015 | G6: 2014 | J6: EMPRESA 1 | K6: =+C19 -> 0.079025923 | L6: =+D19 -> 0.082877698 | M6: =+E19 -> #VALUE! | N6: =AVERAGE(K6:L6) -> 0.08095181
B7: Turnover | C7: 2223 | D7: 1192 | E7: 440 | F7: n.a. | G7: n.a. | J7: EMPRESA 2 | K7: =+C35 -> 0.09437751 | L7: =+D35 -> 0.14814815 | M7: =+E35 -> 0.04787234 | N7: =AVERAGE(K7:L7) -> 0.12126283
B8: Cost of goods sold | C8: 144 | D8: 65 | E8: 17 | F8: n.a. | G8: n.a. | J8: EMPRESA 3 | K8: =+C51 -> 0.025990099 | L8: =+D51 -> 0.021934197 | M8: =+E51 -> 0.031865042 | N8: =AVERAGE(K8:L8) -> 0.023962148
B9: Gross profit | C9: 2078 | D9: 1128 | E9: 423 | F9: n.a. | G9: n.a. | J9: EMPRESA 4 | K9: =+C67 -> 0.075503356 | L9: =+D67 -> 0.041894353 | M9: =+E67 -> 0.064030132 | N9: =AVERAGE(K9:L9) -> 0.058698855
B10: Other operating expenses | C10: 1575 | D10: 840 | E10: 382 | F10: n.a. | G10: n.a. | J10: EMPRESA 5 | K10: =+C83 -> 0.04921466 | L10: =+D83 -> 0.012154696 | M10: =+E83 -> -0.024444444 | N10: =AVERAGE(K10:L10) -> 0.030684678
B11: Operating P/L | C11: 503 | D11: 288 | E11: 41 | F11: n.a. | G11: n.a. | J11: EMPRESA 6 | K11: =+C99 -> 0.021276596 | L11: =+D99 -> 0.10416667 | M11: =+E99 -> 0.11904762 | N11: =AVERAGE(K11:L11) -> 0.062721631
B12: Total fixed assets | C12: 5390 | D12: 2790 | E12: n.a. | F12: n.a. | G12: n.a. | J12: EMPRESA 7 | K12: =+C115 -> 0.01532567 | L12: =+D115 -> 0.18947368 | M12: =+E115 -> 0.125 | N12: =AVERAGE(K12:L12) -> 0.10239968
B13: Intangible fixed assets | C13: 0 | D13: 0 | E13: n.a. | F13: n.a. | G13: n.a.
B14: Stocks | C14: 0 | D14: 0 | E14: n.a. | F14: n.a. | G14: n.a. | M14: Minimo | N14: =MIN(N6:N12) -> 0.023962148
B15: Debtors | C15: 859 | D15: 498 | E15: n.a. | F15: n.a. | G15: n.a. | M15: Cuartil bajo | N15: =QUARTILE(N6:N12,1) -> 0.044691766
B16: Cash | C16: 93 | D16: 176 | E16: n.a. | F16: n.a. | G16: n.a. | M16: Mediana | N16: =MEDIAN(N6:N12) -> 0.062721631
B17: Total assets | C17: 6365 | D17: 3475 | E17: n.a. | F17: n.a. | G17: n.a. | M17: Cuartil alto | N17: =QUARTILE(N6:N12,3) -> 0.091675744
B18: Creditors | C18: 534 | D18: 177 | E18: n.a. | F18: n.a. | G18: n.a. | M18: Máximo | N18: =MAX(N6:N12) -> 0.12126283
C19: =+C11/C17 -> 0.079025923 | D19: =+D11/D17 -> 0.082877698 | E19: =+E11/E17 -> #VALUE!
B21: EMPRESA 2
C22: 2018 | D22: 2017 | E22: 2016 | F22: 2015 | G22: 2014
B23: Turnover | C23: 308 | D23: 267 | E23: 233 | F23: 243 | G23: 207
B24: Cost of goods sold | C24: 56 | D24: 50 | E24: 41 | F24: 44 | G24: 34
B25: Gross profit | C25: 252 | D25: 217 | E25: 192 | F25: 199 | G25: 173
B26: Other operating expenses | C26: 206 | D26: 153 | E26: 174 | F26: 187 | G26: 158
B27: Operating P/L | C27: 47 | D27: 64 | E27: 18 | F27: 12 | G27: 15
B28: Total fixed assets | C28: 155 | D28: 125 | E28: 103 | F28: 110 | G28: 116
B29: Intangible fixed assets | C29: 0 | D29: 0 | E29: 0 | F29: 0 | G29: 0
B30: Stocks | C30: 0 | D30: 0 | E30: 0 | F30: 0 | G30: 0
B31: Debtors | C31: 294 | D31: 278 | E31: 246 | F31: 313 | G31: 291
B32: Cash | C32: 49 | D32: 29 | E32: 27 | F32: 28 | G32: 23
B33: Total assets | C33: 498 | D33: 432 | E33: 376 | F33: 451 | G33: 430
B34: Creditors | C34: 145 | D34: 232 | E34: 227 | F34: 271 | G34: 264
C35: =+C27/C33 -> 0.09437751 | D35: =+D27/D33 -> 0.14814815 | E35: =+E27/E33 -> 0.04787234
B37: EMPRESA 3
C38: 2018 | D38: 2017 | E38: 2016 | F38: 2015 | G38: 2014
B39: Turnover | C39: 949 | D39: 1143 | E39: 1158 | F39: 1074 | G39: 998
B40: Cost of goods sold | C40: 370 | D40: 511 | E40: 552 | F40: 392 | G40: 391
B41: Gross profit | C41: 579 | D41: 632 | E41: 606 | F41: 682 | G41: 607
B42: Other operating expenses | C42: 558 | D42: 610 | E42: 572 | F42: 622 | G42: 538
B43: Operating P/L | C43: 21 | D43: 22 | E43: 34 | F43: 60 | G43: 69
B44: Total fixed assets | C44: 313 | D44: 407 | E44: 487 | F44: 535 | G44: 537
B45: Intangible fixed assets | C45: 0 | D45: 0 | E45: 0 | F45: 2 | G45: 5
B46: Stocks | C46: 157 | D46: 122 | E46: 165 | F46: 189 | G46: 163
B47: Debtors | C47: 310 | D47: 430 | E47: 366 | F47: 282 | G47: 266
B48: Cash | C48: 27 | D48: 42 | E48: 47 | F48: 42 | G48: 44
B49: Total assets | C49: 808 | D49: 1003 | E49: 1067 | F49: 1050 | G49: 1011
B50: Creditors | C50: 152 | D50: 224 | E50: 240 | F50: 197 | G50: 144
C51: =+C43/C49 -> 0.025990099 | D51: =+D43/D49 -> 0.021934197 | E51: =+E43/E49 -> 0.031865042
B53: EMPRESA 4
C54: 2018 | D54: 2017 | E54: 2016 | F54: 2015 | G54: 2014
B55: Turnover | C55: 764 | D55: 972 | E55: 702 | F55: 1106 | G55: 705
B56: Cost of goods sold | C56: 366 | D56: 529 | E56: 245 | F56: 693 | G56: 274
B57: Gross profit | C57: 399 | D57: 443 | E57: 456 | F57: 413 | G57: 431
B58: Other operating expenses | C58: 353 | D58: 420 | E58: 422 | F58: 388 | G58: 400
B59: Operating P/L | C59: 45 | D59: 23 | E59: 34 | F59: 25 | G59: 31
B60: Total fixed assets | C60: 337 | D60: 283 | E60: 275 | F60: 268 | G60: 266
B61: Intangible fixed assets | C61: 0 | D61: 0 | E61: 0 | F61: 0 | G61: 0
B62: Stocks | C62: 114 | D62: 113 | E62: 104 | F62: 87 | G62: 81
B63: Debtors | C63: 107 | D63: 90 | E63: 96 | F63: 101 | G63: 81
B64: Cash | C64: 39 | D64: 63 | E64: 56 | F64: 25 | G64: 34
B65: Total assets | C65: 596 | D65: 549 | E65: 531 | F65: 495 | G65: 477
B66: Creditors | C66: 16 | D66: 20 | E66: 14 | F66: 13 | G66: 12
C67: =+C59/C65 -> 0.075503356 | D67: =+D59/D65 -> 0.041894353 | E67: =+E59/E65 -> 0.064030132
B69: EMPRESA 5
C70: 2018 | D70: 2017 | E70: 2016 | F70: 2015 | G70: 2014
B71: Turnover | C71: 206 | D71: 227 | E71: 143 | F71: 201 | G71: 260
B72: Cost of goods sold | C72: 3 | D72: 2 | E72: 5 | F72: 6 | G72: 3
B73: Gross profit | C73: 203 | D73: 225 | E73: 138 | F73: 195 | G73: 257
B74: Other operating expenses | C74: 156 | D74: 214 | E74: 160 | F74: 196 | G74: 192
B75: Operating P/L | C75: 47 | D75: 11 | E75: -22 | F75: -1 | G75: 64
B76: Total fixed assets | C76: 328 | D76: 373 | E76: 426 | F76: 440 | G76: 438
B77: Intangible fixed assets | C77: 0 | D77: 0 | E77: 0 | F77: 0 | G77: 0
B78: Stocks | C78: 3 | D78: 3 | E78: 3 | F78: 3 | G78: 3
B79: Debtors | C79: 10 | D79: 28 | E79: 70 | F79: 95 | G79: 90
B80: Cash | C80: 249 | D80: 181 | E80: 72 | F80: 43 | G80: 116
B81: Total assets | C81: 955 | D81: 905 | E81: 900 | F81: 928 | G81: 918
B82: Creditors | C82: 505 | D82: 506 | E82: 508 | F82: 514 | G82: 259
C83: =+C75/C81 -> 0.04921466 | D83: =+D75/D81 -> 0.012154696 | E83: =+E75/E81 -> -0.024444444
B85: EMPRESA 6
C86: 2018 | D86: 2017 | E86: 2016 | F86: 2015 | G86: 2014
B87: Turnover | C87: 28 | D87: 46 | E87: 41 | F87: 57 | G87: n.a.
B88: Cost of goods sold | C88: n.a. | D88: n.a. | E88: n.a. | F88: n.a. | G88: n.a.
B89: Gross profit | C89: n.a. | D89: n.a. | E89: n.a. | F89: n.a. | G89: n.a.
B90: Other operating expenses | C90: n.a. | D90: n.a. | E90: n.a. | F90: n.a. | G90: n.a.
B91: Operating P/L | C91: 1 | D91: 5 | E91: 5 | F91: 3 | G91: n.a.
B92: Total fixed assets | C92: 44 | D92: 44 | E92: 38 | F92: n.a. | G92: n.a.
B93: Intangible fixed assets | C93: 0 | D93: 0 | E93: 0 | F93: n.a. | G93: n.a.
B94: Stocks | C94: 0 | D94: 0 | E94: 0 | F94: n.a. | G94: n.a.
B95: Debtors | C95: 1 | D95: 1 | E95: 3 | F95: n.a. | G95: n.a.
B96: Cash | C96: 2 | D96: 2 | E96: 1 | F96: n.a. | G96: n.a.
B97: Total assets | C97: 47 | D97: 48 | E97: 42 | F97: n.a. | G97: n.a.
B98: Creditors | C98: 0 | D98: 0 | E98: 0 | F98: n.a. | G98: n.a.
C99: =+C91/C97 -> 0.021276596 | D99: =+D91/D97 -> 0.10416667 | E99: =+E91/E97 -> 0.11904762
B101: EMPESA 7
C102: 2018 | D102: 2017 | E102: 2016 | F102: 2015 | G102: 2014
B103: Turnover | C103: 833 | D103: 617 | E103: 345 | F103: 262 | G103: 145
B104: Cost of goods sold | C104: 543 | D104: 332 | E104: 177 | F104: 187 | G104: 110
B105: Gross profit | C105: 290 | D105: 284 | E105: 168 | F105: 74 | G105: 35
B106: Other operating expenses | C106: 286 | D106: 248 | E106: 156 | F106: 86 | G106: 25
B107: Operating P/L | C107: 4 | D107: 36 | E107: 12 | F107: -12 | G107: 10
B108: Total fixed assets | C108: 89 | D108: 70 | E108: 24 | F108: 0 | G108: n.a.
...
